Workbook

Sheet Sheet1
A1: Item Number | B1: Item Description | C1: Item Segment | D1: HS-Code
A2: 1109656820 | B2: CHEESEMATE 3036 | C2: Savory | D2: A210600
A3: OVP-L | B3: OVP-L - 25KG | C3: Savory | D3: A210600
A4: 077001020 | B4: FD&C RED NO.40 POWDER 20KG | C4: Colors | D4: A320400
A5: 1050478800 | B5: PROTEX 2617 - 25KG | C5: Savory | D5: A210600
A6: IDF2005 | B6: DB XF1951 10KG | C6: Sweet | D6: A210600
A7: 2024444 | B7: CINNABON Caramel Topping | C7: Sweet | D7: A210600
A8: 03509A014 | B8: PEACH ORANGE 13.5KG | C8: Colors | D8: A320400
A9: IDF2004 | B9: DB XF1591 10KG | C9: Sweet | D9: A210600
A10: 093101020 | B10: FD&C RED 40 ALLK 35-42% (20KG) | C10: Colors | D10: A320400
A11: M86030020 | B11: EUROCERT TARTRAZINE BG 311050 | C11: Colors | D11: A320400
A12: IDF2017 | B12: DB N2945 (FML10) 10KG | C12: Sweet | D12: A210600
... A182: 096061020 | B182: FD&C YELLOW 6 ALLK 17-19% 20KG | C182: Colors | D182: A320400
A183: 355.005 | B183: #N/A | C183: #N/A
A184: 11100488 | B184: CARMINE LAKE 30% | C184: Colors | D184: A320400
A185: 036431020 | B185: BERRY MICROFINE 20KG | C185: Colors | D185: A320400
A186: 409541-0010 | B186: RUBY RED P-WS | C186: Colors | D186: A320400
A187: 096101020 | B187: FD&C YELLOW 6 ALLK 35-42% 20KG | C187: Colors | D187: A320400
A188: 951090B003 | B188: CINNABON CARAMEL TOPPING @ | C188: Dairy | D188: A210600
A189: 096231020 | B189: FD&C YELLOW 6 AL LK20-24% 20KG | C189: Colors | D189: A320400
A190: 503750.010 | B190: MIDNIGHT BLACK P-WD 10KG | C190: Colors | D190: A320400
A191: C86040O20 | B191: EUROCERT SUNSET YELLOW BG | C191: Colors | D191: A320400
A192: 509231320 | B192: BLACK IRON OXIDE 509231320 | C192: Colors | D192: A320400
A193: 503262.010 | B193: RASPBERRY RED P-WS 10KG | C193: Colors | D193: A320400
A194: M98110C20 | B194: RED NO 5 E 122 EXTRUKLEEN | C194: Colors | D194: A320400
A195: 97CB0781 | B195: NATURAL CAROTENE EMULSION | C195: Colors | D195: A320400
... A260: 9640600020 | B260: VEGAN DB COND MILK FL N14136 | C260: Sweet | D260: A210600

Sheet TDP
A5: PT. Sensient Technologies Indonesia
A6: Date - Period | B6: StatusType | C6: Order Type | D6: Invoice | E6: Customer Order | F6: Order | G6: Ship Date | H6: Customer Group | I6: Item Number | J6: Item Description | K6: Input Quantity | L6: Input UOM | M6: Total KG | N6: Unit Price | O6: Amount | P6: Amount - Sales and orders Only | Q6: Foreign per unit | R6: Foreign Amount | S6: Currency | T6: StandardCost | U6: StandardCost- Sales and orders Only | V6: Gross Margin | W6: Gross Margin % | X6: Margin - Sales and orders Only | Y6: IncoTerms | Z6: IncoTerms Description | AA6: Ship To | AB6: Ship To Name | AC6: Sales Region Desc | AD6: Sales Region | AE6: Delivery Days | AF6: GL Category | AG6: Cat6 | AH6: Cat 6 Desc | AI6: Cat7 | AJ6: Cat 7 Desc | AK6: SaleType | AL6: AffiliateType | AM6: CustomerType | AN6: HS-Code | AP6: Note Finance MB
A7: 45658 | B7: Invoiced | C7: SO | D7: 25707908 | E7: 24106304 | F7: 241200149 | G7: 45659 | H7: PT. TIGAKA DISTRINDO PERKASA JAKARTA | I7: 096091020 | J7: FD&C YELLOW 5 ALLK 35-42% 20KG | K7: 300 | L7: KG | M7: 300 | N7: 386598.59 | O7: 115979577 | P7: 115979577 | Q7: 0 | R7: 0 | S7: IDR | T7: 90253620 | U7: 90253620 | V7: 25725957 | W7: 0.22181454 | X7: 25725957 | Y7: DEL | Z7: Delivered | AA7: 15159 | AB7: PT. TIGAKA DISTRINDO PERKASA CIKARANG | AC7: ELLY HENDRA | AD7: 35 | AE7: 0 | AF7: 963 | AG7: TCSK | AH7: TRA COL SYN LAKE | AJ7: . | AK7: T | AL7: Non-Affiliate | AM7: Distributor | AN7: =VLOOKUP(I7,Sheet1!A:D,4,) -> A320400 | AP7: Invoaice di kasih sore jam pulang kerja jam 17:38.invoaice tanggal 2,10/1/25. MB terima di tanggal 17/1/25. Cortexnya masih belum bisa.
A8: 45658 | B8: Invoiced | C8: SO | D8: 25707908 | E8: 24106304 | F8: 241200149 | G8: 45659 | H8: PT. TIGAKA DISTRINDO PERKASA JAKARTA | I8: 077001020 | J8: FD&C RED NO.40 POWDER 20KG | K8: 220 | L8: KG | M8: 220 | N8: 457480.42 | O8: 1.0064569e+08 | P8: 1.0064569e+08 | Q8: 0 | R8: 0 | S8: IDR | T8: 52666862 | U8: 52666862 | V8: 47978830 | W8: 0.47671022 | X8: 47978830 | Y8: DEL | Z8: Delivered | AA8: 15159 | AB8: PT. TIGAKA DISTRINDO PERKASA CIKARANG | AC8: ELLY HENDRA | AD8: 35 | AE8: 0 | AF8: 961 | AG8: TCSP | AH8: TRA COL SYN DYE POWDER | AJ8: . | AK8: T | AL8: Non-Affiliate | AM8: Distributor | AN8: =VLOOKUP(I8,Sheet1!A:D,4,) -> A320400 | AP8: Invoaice di kasih sore jam pulang kerja jam 17:38.invoaice tanggal 2,10/1/25. MB terima di tanggal 17/1/25. Cortexnya masih belum bisa.
A9: 45658 | B9: Invoiced | C9: SO | D9: 25707909 | E9: 24106305 | F9: 241100199 | G9: 45659 | H9: PT. TIGAKA DISTRINDO PERKASA PHARMA | I9: 056011020 | J9: FD&C BLUE NO 1 POWDER 20KG | K9: 100 | L9: KG | M9: 100 | N9: 715321.2 | O9: 71532120 | P9: 71532120 | Q9: 0 | R9: 0 | S9: IDR | T9: 55963280 | U9: 55963280 | V9: 15568840 | W9: 0.21764824 | X9: 15568840 | Z9: . | AA9: 2306153 | AB9: PT. TIGAKA DISTRINDO PERKASA PHARMA | AC9: ELLY HENDRA | AD9: 35 | AE9: 0 | AF9: 961 | AG9: TCSP | AH9: TRA COL SYN DYE POWDER | AJ9: . | AK9: T | AL9: Non-Affiliate | AM9: Distributor | AN9: =VLOOKUP(I9,Sheet1!A:D,4,) -> A320400 | AP9: Invoaice di kasih sore jam pulang kerja jam 17:38.invoaice tanggal 2,10/1/25. MB terima di tanggal 17/1/25. Cortexnya masih belum bisa.
A10: 45658 | B10: Invoiced | C10: SO | D10: 25707909 | E10: 24106305 | F10: 241100199 | G10: 45659 | H10: PT. TIGAKA DISTRINDO PERKASA PHARMA | I10: K71811020 | J10: D&C YELLW #10 ALLK 14-18% 20KG | K10: 200 | L10: KG | M10: 200 | N10: 906832.19 | O10: 181366438 | P10: 181366438 | Q10: 0 | R10: 0 | S10: IDR | T10: 95025018 | U10: 95025018 | V10: 86341420 | W10: 0.47606063 | X10: 86341420 | Z10: . | AA10: 2306153 | AB10: PT. TIGAKA DISTRINDO PERKASA PHARMA | AC10: ELLY HENDRA | AD10: 35 | AE10: 0 | AF10: 961 | AG10: TMCC | AH10: TRA COS COSMETIC COLOUR | AJ10: . | AK10: T | AL10: Non-Affiliate | AM10: Distributor | AN10: =VLOOKUP(I10,Sheet1!A:D,4,) -> A320400 | AP10: Invoaice di kasih sore jam pulang kerja jam 17:38.invoaice tanggal 2,10/1/25. MB terima di tanggal 17/1/25. Cortexnya masih belum bisa.
A11: 45658 | B11: Invoiced | C11: SO | D11: 25707910 | E11: 24106355 | F11: 241100227 | G11: 45659 | H11: PT. TIGAKA DISTRINDO PERKASA PHARMA | I11: 503262.010 | J11: RASPBERRY RED P-WS 10KG | K11: 1800 | L11: KG | M11: 1800 | N11: 410282.59 | O11: 738508662 | P11: 738508662 | Q11: 0 | R11: 0 | S11: IDR | T11: 3.2545827e+08 | U11: 3.2545827e+08 | V11: 4.1305039e+08 | W11: 0.55930338 | X11: 4.1305039e+08 | Z11: . | AA11: 2306153 | AB11: PT. TIGAKA DISTRINDO PERKASA PHARMA | AC11: ELLY HENDRA | AD11: 35 | AE11: 0 | AF11: 966 | AG11: TCNP | AH11: TRA COL NAT POWDER | AJ11: . | AK11: T | AL11: Non-Affiliate | AM11: Distributor | AN11: =VLOOKUP(I11,Sheet1!A:D,4,) -> A320400 | AP11: Invoaice di kasih sore jam pulang kerja jam 17:38.invoaice tanggal 2,10/1/25. MB terima di tanggal 17/1/25. Cortexnya masih belum bisa.
A12: 45658 | B12: Invoiced | C12: SO | D12: 25707911 | E12: 24106387 | F12: 241100250 | G12: 45659 | H12: PT. TIGAKA DISTRINDO PERKASA PHARMA | I12: 409541-0010 | J12: RUBY RED P-WS | K12: 600 | L12: KG | M12: 600 | N12: 698810.88 | O12: 419286528 | P12: 419286528 | Q12: 0 | R12: 0 | S12: IDR | T12: 2.5567846e+08 | U12: 2.5567846e+08 | V12: 1.6360806e+08 | W12: 0.39020587 | X12: 1.6360806e+08 | Z12: . | AA12: 2306153 | AB12: PT. TIGAKA DISTRINDO PERKASA PHARMA | AC12: ELLY HENDRA | AD12: 35 | AE12: 0 | AF12: 960 | AH12: . | AJ12: . | AK12: T | AL12: Non-Affiliate | AM12: Distributor | AN12: =VLOOKUP(I12,Sheet1!A:D,4,) -> A320400 | AP12: Invoaice di kasih sore jam pulang kerja jam 17:38.invoaice tanggal 2,10/1/25. MB terima di tanggal 17/1/25. Cortexnya masih belum bisa.
A13: 45658 | B13: Invoiced | C13: SO | D13: 25707912 | E13: 24106404 | F13: 241200189 | G13: 45659 | H13: PT. TIGAKA DISTRINDO PERKASA JAKARTA | I13: 503651.010 | J13: HICKORY BROWN L-WS | K13: 80 | L13: KG | M13: 80 | N13: 496676.77 | O13: 39734142 | P13: 39734142 | Q13: 0 | R13: 0 | S13: IDR | T13: 14470469 | U13: 14470469 | V13: 25263673 | W13: 0.63581776 | X13: 25263673 | Y13: DEL | Z13: Delivered | AA13: 15159 | AB13: PT. TIGAKA DISTRINDO PERKASA CIKARANG | AC13: ELLY HENDRA | AD13: 35 | AE13: 0 | AF13: 966 | AG13: TCNL | AH13: TRA COL NAT LIQUID | AJ13: . | AK13: T | AL13: Non-Affiliate | AM13: Distributor | AN13: =VLOOKUP(I13,Sheet1!A:D,4,) -> A320400 | AP13: Invoaice di kasih sore jam pulang kerja jam 17:38.invoaice tanggal 2,10/1/25. MB terima di tanggal 17/1/25. Cortexnya masih belum bisa.
A14: 45658 | B14: Invoiced | C14: SO | D14: 25707913 | E14: 24106451 | F14: 241100279 | G14: 45659 | H14: PT. TIGAKA DISTRINDO PERKASA PHARMA | I14: 503651.010 | J14: HICKORY BROWN L-WS | K14: 200 | L14: KG | M14: 200 | N14: 504485.63 | O14: 100897126 | P14: 100897126 | Q14: 0 | R14: 0 | S14: IDR | T14: 36176171 | U14: 36176171 | V14: 64720955 | W14: 0.64145489 | X14: 64720955 | Z14: . | AA14: 2306153 | AB14: PT. TIGAKA DISTRINDO PERKASA PHARMA | AC14: ELLY HENDRA | AD14: 35 | AE14: 0 | AF14: 966 | AG14: TCNL | AH14: TRA COL NAT LIQUID | AJ14: . | AK14: T | AL14: Non-Affiliate | AM14: Distributor | AN14: =VLOOKUP(I14,Sheet1!A:D,4,) -> A320400 | AP14: Invoaice di kasih sore jam pulang kerja jam 17:38.invoaice tanggal 2,10/1/25. MB terima di tanggal 17/1/25. Cortexnya masih belum bisa.
A15: 45658 | B15: Invoiced | C15: SO | D15: 25707914 | E15: 24106478 | F15: 241200218 | G15: 45659 | H15: PT. TIGAKA DISTRINDO PERKASA JAKARTA | I15: 979007.001 | J15: MINT GREEN 97P-WS 1KG | K15: 3 | L15: KG | M15: 3 | N15: 10434182 | O15: 31302547 | P15: 31302547 | Q15: 0 | R15: 0 | S15: IDR | T15: 19437844 | U15: 19437844 | V15: 11864703 | W15: 0.37903314 | X15: 11864703 | Y15: DEL | Z15: Delivered | AA15: 15159 | AB15: PT. TIGAKA DISTRINDO PERKASA CIKARANG | AC15: ELLY HENDRA | AD15: 35 | AE15: 0 | AF15: 966 | AH15: . | AJ15: . | AK15: T | AL15: Non-Affiliate | AM15: Distributor | AN15: =VLOOKUP(I15,Sheet1!A:D,4,) -> A320400 | AP15: Invoaice di kasih sore jam pulang kerja jam 17:38.invoaice tanggal 2,10/1/25. MB terima di tanggal 17/1/25. Cortexnya masih belum bisa.
A16: 45658 | B16: Invoiced | C16: SO | D16: 25707915 | E16: 24106481 | F16: 241100295 | G16: 45659 | H16: PT. TIGAKA DISTRINDO PERKASA PHARMA | I16: 503651.010 | J16: HICKORY BROWN L-WS | K16: 40 | L16: KG | M16: 40 | N16: 504485.63 | O16: 20179425 | P16: 20179425 | Q16: 0 | R16: 0 | S16: IDR | T16: 7235234.3 | U16: 7235234.3 | V16: 12944191 | W16: 0.64145489 | X16: 12944191 | Z16: . | AA16: 2306153 | AB16: PT. TIGAKA DISTRINDO PERKASA PHARMA | AC16: ELLY HENDRA | AD16: 35 | AE16: 0 | AF16: 966 | AG16: TCNL | AH16: TRA COL NAT LIQUID | AJ16: . | AK16: T | AL16: Non-Affiliate | AM16: Distributor | AN16: =VLOOKUP(I16,Sheet1!A:D,4,) -> A320400 | AP16: Invoaice di kasih sore jam pulang kerja jam 17:38.invoaice tanggal 2,10/1/25. MB terima di tanggal 17/1/25. Cortexnya masih belum bisa.
A17: 45658 | B17: Invoiced | C17: SO | D17: 25707916 | E17: 24106497 | F17: 241200225 | G17: 45659 | H17: PT. TIGAKA DISTRINDO PERKASA JAKARTA -HI | I17: 03509A014 | J17: PEACH ORANGE 13.5KG | K17: 54 | L17: KG | M17: 54 | N17: 889177.2 | O17: 48015569 | P17: 48015569 | Q17: 0 | R17: 0 | S17: IDR | T17: 25437202 | U17: 25437202 | V17: 22578366 | W17: 0.47023011 | X17: 22578366 | Z17: . | AA17: 2306392 | AB17: PT. TIGAKA DISTRINDO PERKASA CIKARANG-HI | AC17: Handy Inarto | AD17: 104 | AE17: 0 | AF17: 966 | AH17: . | AJ17: . | AK17: T | AL17: Non-Affiliate | AM17: Distributor | AN17: =VLOOKUP(I17,Sheet1!A:D,4,) -> A320400 | AP17: Invoaice di kasih sore jam pulang kerja jam 17:38.invoaice tanggal 2,10/1/25. MB terima di tanggal 17/1/25. Cortexnya masih belum bisa.
A18: 45658 | B18: Invoiced | C18: SO | D18: 25707917 | E18: 24106498 | F18: 241200226 | G18: 45659 | H18: PT. TIGAKA DISTRINDO PERKASA JAKARTA -HI | I18: 03509A014 | J18: PEACH ORANGE 13.5KG | K18: 54 | L18: KG | M18: 54 | N18: 879817.44 | O18: 47510142 | P18: 47510142 | Q18: 0 | R18: 0 | S18: IDR | T18: 25437202 | U18: 25437202 | V18: 22072939 | W18: 0.46459426 | X18: 22072939 | Z18: . | AA18: 2306392 | AB18: PT. TIGAKA DISTRINDO PERKASA CIKARANG-HI | AC18: Handy Inarto | AD18: 104 | AE18: 0 | AF18: 966 | AH18: . | AJ18: . | AK18: T | AL18: Non-Affiliate | AM18: Distributor | AN18: =VLOOKUP(I18,Sheet1!A:D,4,) -> A320400 | AP18: Invoaice di kasih sore jam pulang kerja jam 17:38.invoaice tanggal 2,10/1/25. MB terima di tanggal 17/1/25. Cortexnya masih belum bisa.
A19: 45658 | B19: Invoiced | C19: SO | D19: 25707918 | E19: 24106500 | F19: 241200228 | G19: 45659 | H19: PT. TIGAKA DISTRINDO PERKASA JAKARTA -AA | I19: 979007.005 | J19: MINT GREEN 97P-WS 5KG | K19: 15 | L19: KG | M19: 15 | N19: 9178191.3 | O19: 1.3767287e+08 | P19: 1.3767287e+08 | Q19: 0 | R19: 0 | S19: IDR | T19: 95184330 | U19: 95184330 | V19: 42488539 | W19: 0.30861955 | X19: 42488539 | Z19: . | AA19: 2306495 | AB19: PT. TIGAKA DISTRINDO PERKASA CIKARANG-AA | AC19: AGNESYA ADIFILIA | AD19: 94 | AE19: 0 | AF19: 966 | AG19: TCNL | AH19: TRA COL NAT LIQUID | AJ19: . | AK19: T | AL19: Non-Affiliate | AM19: Distributor | AN19: =VLOOKUP(I19,Sheet1!A:D,4,) -> A320400 | AP19: Invoaice di kasih sore jam pulang kerja jam 17:38.invoaice tanggal 2,10/1/25. MB terima di tanggal 17/1/25. Cortexnya masih belum bisa.
A20: 45658 | B20: Invoiced | C20: SO | D20: 25707919 | E20: 24106542 | F20: 241200233 | G20: 45659 | H20: PT. TIGAKA DISTRINDO PERKASA JAKARTA -HI | I20: 979007.001 | J20: MINT GREEN 97P-WS 1KG | K20: 8 | L20: KG | M20: 8 | N20: 9801577.5 | O20: 78412620 | P20: 78412620 | Q20: 0 | R20: 0 | S20: IDR | T20: 51834252 | U20: 51834252 | V20: 26578368 | W20: 0.33895523 | X20: 26578368 | Z20: . | AA20: 2306392 | AB20: PT. TIGAKA DISTRINDO PERKASA CIKARANG-HI | AC20: Handy Inarto | AD20: 104 | AE20: 0 | AF20: 966 | AH20: . | AJ20: . | AK20: T | AL20: Non-Affiliate | AM20: Distributor | AN20: =VLOOKUP(I20,Sheet1!A:D,4,) -> A320400 | AP20: Invoaice di kasih sore jam pulang kerja jam 17:38.invoaice tanggal 2,10/1/25. MB terima di tanggal 17/1/25. Cortexnya masih belum bisa.
A21: 45658 | B21: Invoiced | C21: SO | D21: 25707920 | E21: 24106353 | F21: 241100225 | G21: 45667 | H21: PT. TIGAKA DISTRINDO PERKASA PHARMA | I21: 952360010 | J21: PONCEAU 4R LAKE MD 10KG | K21: 300 | L21: KG | M21: 300 | N21: 414064 | O21: 124219200 | P21: 124219200 | Q21: 0 | R21: 0 | S21: IDR | T21: 94383150 | U21: 94383150 | V21: 29836050 | W21: 0.24018871 | X21: 29836050 | Z21: . | AA21: 2306153 | AB21: PT. TIGAKA DISTRINDO PERKASA PHARMA | AC21: ELLY HENDRA | AD21: 35 | AE21: 0 | AF21: 963 | AG21: TCSK | AH21: TRA COL SYN LAKE | AJ21: . | AK21: T | AL21: Non-Affiliate | AM21: Distributor | AN21: =VLOOKUP(I21,Sheet1!A:D,4,) -> A320400 | AP21: Invoaice di kasih sore jam pulang kerja jam 17:38.invoaice tanggal 2,10/1/25. MB terima di tanggal 17/1/25. Cortexnya masih belum bisa.
A22: 45658 | B22: Invoiced | C22: SO | D22: 25707921 | E22: 24106394 | F22: 241100257 | G22: 45667 | H22: PT. TIGAKA DISTRINDO PERKASA PHARMA | I22: 909324B10 | J22: EUROLAKE CARMOISINE 10KG | K22: 40 | L22: KG | M22: 40 | N22: 916576.29 | O22: 36663052 | P22: 36663052 | Q22: 0 | R22: 0 | S22: IDR | T22: 15708414 | U22: 15708414 | V22: 20954638 | W22: 0.57154647 | X22: 20954638 | Z22: . | AA22: 2306153 | AB22: PT. TIGAKA DISTRINDO PERKASA PHARMA | AC22: ELLY HENDRA | AD22: 35 | AE22: 0 | AF22: 963 | AG22: TCSK | AH22: TRA COL SYN LAKE | AJ22: . | AK22: T | AL22: Non-Affiliate | AM22: Distributor | AN22: =VLOOKUP(I22,Sheet1!A:D,4,) -> A320400 | AP22: Invoaice di kasih sore jam pulang kerja jam 17:38.invoaice tanggal 2,10/1/25. MB terima di tanggal 17/1/25. Cortexnya masih belum bisa.
A23: 45658 | B23: Invoiced | C23: SO | D23: 25707922 | E23: 24106414 | F23: 241100262 | G23: 45667 | H23: PT. TIGAKA DISTRINDO PERKASA PHARMA | I23: 097331001 | J23: FD&C YELLOW 5 ALLK 14-16% 1KG | K23: 14 | L23: KG | M23: 14 | N23: 2440321.1 | O23: 34164496 | P23: 34164496 | Q23: 0 | R23: 0 | S23: IDR | T23: 7027874.3 | U23: 7027874.3 | V23: 27136622 | W23: 0.79429305 | X23: 27136622 | Z23: . | AA23: 2306153 | AB23: PT. TIGAKA DISTRINDO PERKASA PHARMA | AC23: ELLY HENDRA | AD23: 35 | AE23: 0 | AF23: 963 | AG23: TCSK | AH23: TRA COL SYN LAKE | AJ23: . | AK23: T | AL23: Non-Affiliate | AM23: Distributor | AN23: =VLOOKUP(I23,Sheet1!A:D,4,) -> A320400 | AP23: Invoaice di kasih sore jam pulang kerja jam 17:38.invoaice tanggal 2,10/1/25. MB terima di tanggal 17/1/25. Cortexnya masih belum bisa.
A24: 45658 | B24: Invoiced | C24: SO | D24: 25707923 | E24: 24106422 | F24: 241100269 | G24: 45667 | H24: PT. TIGAKA DISTRINDO PERKASA PHARMA | I24: 097331001 | J24: FD&C YELLOW 5 ALLK 14-16% 1KG | K24: 6 | L24: KG | M24: 6 | N24: 2440321.1 | O24: 14641927 | P24: 14641927 | Q24: 0 | R24: 0 | S24: IDR | T24: 3011946.1 | U24: 3011946.1 | V24: 11629981 | W24: 0.79429305 | X24: 11629981 | Z24: . | AA24: 2306153 | AB24: PT. TIGAKA DISTRINDO PERKASA PHARMA | AC24: ELLY HENDRA | AD24: 35 | AE24: 0 | AF24: 963 | AG24: TCSK | AH24: TRA COL SYN LAKE | AJ24: . | AK24: T | AL24: Non-Affiliate | AM24: Distributor | AN24: =VLOOKUP(I24,Sheet1!A:D,4,) -> A320400 | AP24: Invoaice di kasih sore jam pulang kerja jam 17:38.invoaice tanggal 2,10/1/25. MB terima di tanggal 17/1/25. Cortexnya masih belum bisa.
A25: 45658 | B25: Invoiced | C25: SO | D25: 25707924 | E25: 24106472 | F25: 241200215 | G25: 45667 | H25: PT. TIGAKA DISTRINDO PERKASA JAKARTA -HI | I25: 091451020 | J25: BROWN LAKE BLEND R | K25: 40 | L25: KG | M25: 40 | N25: 1290582.2 | O25: 51623290 | P25: 51623290 | Q25: 0 | R25: 0 | S25: IDR | T25: 28066874 | U25: 28066874 | V25: 23556416 | W25: 0.45631373 | X25: 23556416 | Z25: . | AA25: 2306392 | AB25: PT. TIGAKA DISTRINDO PERKASA CIKARANG-HI | AC25: Handy Inarto | AD25: 104 | AE25: 0 | AF25: 960 | AH25: . | AJ25: . | AK25: T | AL25: Non-Affiliate | AM25: Distributor | AN25: =VLOOKUP(I25,Sheet1!A:D,4,) -> A320400 | AP25: Invoaice di kasih sore jam pulang kerja jam 17:38.invoaice tanggal 2,10/1/25. MB terima di tanggal 17/1/25. Cortexnya masih belum bisa.
A26: 45658 | B26: Invoiced | C26: SO | D26: 25707925 | E26: 24106482 | F26: 241200219 | G26: 45667 | H26: PT. TIGAKA DISTRINDO PERKASA JAKARTA | I26: 036431020 | J26: BERRY MICROFINE 20KG | K26: 40 | L26: KG | M26: 40 | N26: 739372.65 | O26: 29574906 | P26: 29574906 | Q26: 0 | R26: 0 | S26: IDR | T26: 21789983 | U26: 21789983 | V26: 7784923.3 | W26: 0.26322732 | X26: 7784923.3 | Y26: DEL | Z26: Delivered | AA26: 15159 | AB26: PT. TIGAKA DISTRINDO PERKASA CIKARANG | AC26: ELLY HENDRA | AD26: 35 | AE26: 0 | AF26: 960 | AH26: . | AJ26: . | AK26: T | AL26: Non-Affiliate | AM26: Distributor | AN26: =VLOOKUP(I26,Sheet1!A:D,4,) -> A320400 | AP26: Invoaice di kasih sore jam pulang kerja jam 17:38.invoaice tanggal 2,10/1/25. MB terima di tanggal 17/1/25. Cortexnya masih belum bisa.
A27: 45658 | B27: Invoiced | C27: SO | D27: 25707926 | E27: 24106486 | F27: 241200221 | G27: 45667 | H27: PT. TIGAKA DISTRINDO PERKASA JAKARTA | I27: 97CB0935 | J27: CM RED 500CPWD | K27: 10 | L27: KG | M27: 10 | N27: 6944461.5 | O27: 69444615 | P27: 69444615 | Q27: 0 | R27: 0 | S27: IDR | T27: 71648053 | U27: 71648053 | V27: -2203437.6 | W27: -0.031729424 | X27: -2203437.6 | Y27: DEL | Z27: Delivered | AA27: 15159 | AB27: PT. TIGAKA DISTRINDO PERKASA CIKARANG | AC27: ELLY HENDRA | AD27: 35 | AE27: 0 | AF27: 966 | AG27: TCSB | AH27: TRA COL SYN DYE POWDER BLEND | AJ27: . | AK27: T | AL27: Non-Affiliate | AM27: Distributor | AN27: =VLOOKUP(I27,Sheet1!A:D,4,) -> A320400 | AP27: Invoaice di kasih sore jam pulang kerja jam 17:38.invoaice tanggal 2,10/1/25. MB terima di tanggal 17/1/25. Cortexnya masih belum bisa.
A28: 45658 | B28: Invoiced | C28: SO | D28: 25707927 | E28: 24106528 | F28: 241200229 | G28: 45667 | H28: PT. TIGAKA DISTRINDO PERKASA JAKARTA -AA | I28: T230104 | J28: EUROBLEND GREEN 973 | K28: 75 | L28: KG | M28: 75 | N28: 568857.3 | O28: 42664298 | P28: 42664298 | Q28: 0 | R28: 0 | S28: IDR | T28: 26080628 | U28: 26080628 | V28: 16583669 | W28: 0.38870133 | X28: 16583669 | Z28: . | AA28: 2306495 | AB28: PT. TIGAKA DISTRINDO PERKASA CIKARANG-AA | AC28: AGNESYA ADIFILIA | AD28: 94 | AE28: 0 | AF28: 960 | AH28: . | AJ28: . | AK28: T | AL28: Non-Affiliate | AM28: Distributor | AN28: =VLOOKUP(I28,Sheet1!A:D,4,) -> A320400 | AP28: Invoaice di kasih sore jam pulang kerja jam 17:38.invoaice tanggal 2,10/1/25. MB terima di tanggal 17/1/25. Cortexnya masih belum bisa.
A29: 45658 | B29: Invoiced | C29: SO | D29: 25707941 | E29: 24106353 | F29: 241100225 | G29: 45659 | H29: PT. TIGAKA DISTRINDO PERKASA PHARMA | I29: 077001020 | J29: FD&C RED NO.40 POWDER 20KG | K29: 180 | L29: KG | M29: 180 | N29: 860427.52 | O29: 1.5487695e+08 | P29: 1.5487695e+08 | Q29: 0 | R29: 0 | S29: IDR | T29: 43091069 | U29: 43091069 | V29: 1.1178588e+08 | W29: 0.72177223 | X29: 1.1178588e+08 | Z29: . | AA29: 2306153 | AB29: PT. TIGAKA DISTRINDO PERKASA PHARMA | AC29: ELLY HENDRA | AD29: 35 | AE29: 0 | AF29: 961 | AG29: TCSP | AH29: TRA COL SYN DYE POWDER | AJ29: . | AK29: T | AL29: Non-Affiliate | AM29: Distributor | AN29: =VLOOKUP(I29,Sheet1!A:D,4,) -> A320400 | AP29: Invoice dikasih jam 09:30. invoice tanggal 2,10,14,17/1/25. MB terima di tanggal 23/1/25.
A30: 45658 | B30: Invoiced | C30: SO | D30: 25707942 | E30: 24106393 | F30: 241100256 | G30: 45659 | H30: PT. TIGAKA DISTRINDO PERKASA PHARMA | I30: 030131005 | J30: BETA CAROTENE ORANGE P 10% 5KG | K30: 5 | L30: KG | M30: 5 | N30: 4207423.8 | O30: 21037119 | P30: 21037119 | Q30: 0 | R30: 0 | S30: IDR | T30: 15728978 | U30: 15728978 | V30: 5308141.1 | W30: 0.25232262 | X30: 5308141.1 | Z30: . | AA30: 2306153 | AB30: PT. TIGAKA DISTRINDO PERKASA PHARMA | AC30: ELLY HENDRA | AD30: 35 | AE30: 0 | AF30: 966 | AG30: TCNP | AH30: TRA COL NAT POWDER | AJ30: . | AK30: T | AL30: Non-Affiliate | AM30: Distributor | AN30: =VLOOKUP(I30,Sheet1!A:D,4,) -> A320400 | AP30: Invoice dikasih jam 09:30. invoice tanggal 2,10,14,17/1/25. MB terima di tanggal 23/1/25.
A31: 45658 | B31: Invoiced | C31: SO | D31: 25707943 | E31: 24106387 | F31: 241100250 | G31: 45667 | H31: PT. TIGAKA DISTRINDO PERKASA PHARMA | I31: 036431020 | J31: BERRY MICROFINE 20KG | K31: 120 | L31: KG | M31: 120 | N31: 790453.18 | O31: 94854382 | P31: 94854382 | Q31: 0 | R31: 0 | S31: IDR | T31: 65369948 | U31: 65369948 | V31: 29484434 | W31: 0.31083892 | X31: 29484434 | Z31: . | AA31: 2306153 | AB31: PT. TIGAKA DISTRINDO PERKASA PHARMA | AC31: ELLY HENDRA | AD31: 35 | AE31: 0 | AF31: 960 | AH31: . | AJ31: . | AK31: T | AL31: Non-Affiliate | AM31: Distributor | AN31: =VLOOKUP(I31,Sheet1!A:D,4,) -> A320400 | AP31: Invoice dikasih jam 09:30. invoice tanggal 2,10,14,17/1/25. MB terima di tanggal 23/1/25.
A32: 45658 | B32: Invoiced | C32: SO | D32: 25707944 | E32: 24106447 | F32: 241200205 | G32: 45667 | H32: PT. TIGAKA DISTRINDO PERKASA JAKARTA | I32: 030131005 | J32: BETA CAROTENE ORANGE P 10% 5KG | K32: 5 | L32: KG | M32: 5 | N32: 4185316.2 | O32: 20926581 | P32: 20926581 | Q32: 0 | R32: 0 | S32: IDR | T32: 15728978 | U32: 15728978 | V32: 5197602.7 | W32: 0.24837324 | X32: 5197602.7 | Y32: DEL | Z32: Delivered | AA32: 15159 | AB32: PT. TIGAKA DISTRINDO PERKASA CIKARANG | AC32: ELLY HENDRA | AD32: 35 | AE32: 0 | AF32: 966 | AG32: TCNP | AH32: TRA COL NAT POWDER | AJ32: . | AK32: T | AL32: Non-Affiliate | AM32: Distributor | AN32: =VLOOKUP(I32,Sheet1!A:D,4,) -> A320400 | AP32: Invoice dikasih jam 09:30. invoice tanggal 2,10,14,17/1/25. MB terima di tanggal 23/1/25.
A33: 45658 | B33: Invoiced | C33: SO | D33: 25707945 | E33: 24106474 | F33: 241200216 | G33: 45667 | H33: PT. TIGAKA DISTRINDO PERKASA JAKARTA | I33: 97CA0826 | J33: SPIRULINA DISPERSION OB | K33: 200 | L33: KG | M33: 200 | N33: 1459753.6 | O33: 291950730 | P33: 291950730 | Q33: 0 | R33: 0 | S33: IDR | T33: 2.2329358e+08 | U33: 2.2329358e+08 | V33: 68657148 | W33: 0.2351669 | X33: 68657148 | Y33: DEL | Z33: Delivered | AA33: 15159 | AB33: PT. TIGAKA DISTRINDO PERKASA CIKARANG | AC33: ELLY HENDRA | AD33: 35 | AE33: 0 | AF33: 960 | AH33: . | AJ33: . | AK33: T | AL33: Non-Affiliate | AM33: Distributor | AN33: =VLOOKUP(I33,Sheet1!A:D,4,) -> A320400 | AP33: Invoice dikasih jam 09:30. invoice tanggal 2,10,14,17/1/25. MB terima di tanggal 23/1/25.
A34: 45658 | B34: Invoiced | C34: SO | D34: 25707946 | E34: 25106558 | F34: 251200003 | G34: 45671 | H34: PT. TIGAKA DISTRINDO PERKASA JAKARTA -AA | I34: 979007.001 | J34: MINT GREEN 97P-WS 1KG | K34: 1 | L34: KG | M34: 1 | N34: 10445174 | O34: 10445174 | P34: 10445174 | Q34: 0 | R34: 0 | S34: IDR | T34: 6479281.5 | U34: 6479281.5 | V34: 3965892.5 | W34: 0.37968659 | X34: 3965892.5 | Z34: . | AA34: 2306495 | AB34: PT. TIGAKA DISTRINDO PERKASA CIKARANG-AA | AC34: AGNESYA ADIFILIA | AD34: 94 | AE34: 0 | AF34: 966 | AH34: . | AJ34: . | AK34: T | AL34: Non-Affiliate | AM34: Distributor | AN34: =VLOOKUP(I34,Sheet1!A:D,4,) -> A320400 | AP34: Invoice dikasih jam 09:30. invoice tanggal 2,10,14,17/1/25. MB terima di tanggal 23/1/25.
A35: 45658 | B35: Invoiced | C35: SO | D35: 25707947 | E35: 25106559 | F35: 251200004 | G35: 45671 | H35: PT. TIGAKA DISTRINDO PERKASA JAKARTA | I35: 979007.001 | J35: MINT GREEN 97P-WS 1KG | K35: 1 | L35: KG | M35: 1 | N35: 10751121 | O35: 10751121 | P35: 10751121 | Q35: 0 | R35: 0 | S35: IDR | T35: 6479281.5 | U35: 6479281.5 | V35: 4271839.7 | W35: 0.397339 | X35: 4271839.7 | Y35: DEL | Z35: Delivered | AA35: 15159 | AB35: PT. TIGAKA DISTRINDO PERKASA CIKARANG | AC35: ELLY HENDRA | AD35: 35 | AE35: 0 | AF35: 966 | AH35: . | AJ35: . | AK35: T | AL35: Non-Affiliate | AM35: Distributor | AN35: =VLOOKUP(I35,Sheet1!A:D,4,) -> A320400 | AP35: Invoice dikasih jam 09:30. invoice tanggal 2,10,14,17/1/25. MB terima di tanggal 23/1/25.
A36: 45658 | B36: Invoiced | C36: SO | D36: 25707948 | E36: 25106563 | F36: 251200006 | G36: 45674 | H36: PT. TIGAKA DISTRINDO PERKASA JAKARTA -HI | I36: IC10348 | J36: BRIGHT RED P-WS | K36: 2 | L36: KG | M36: 2 | N36: 2706505.3 | O36: 5413010.6 | P36: 5413010.6 | Q36: 0 | R36: 0 | S36: IDR | T36: 0 | U36: 0 | V36: 5413010.6 | W36: 1 | X36: 5413010.6 | Z36: . | AA36: 2306392 | AB36: PT. TIGAKA DISTRINDO PERKASA CIKARANG-HI | AC36: Handy Inarto | AD36: 104 | AE36: 0 | AF36: 960 | AH36: . | AJ36: . | AK36: T | AL36: Non-Affiliate | AM36: Distributor | AN36: =VLOOKUP(I36,Sheet1!A:D,4,) -> A320400 | AP36: Invoice dikasih jam 09:30. invoice tanggal 2,10,14,17/1/25. MB terima di tanggal 23/1/25.
A37: 45658 | B37: Invoiced | C37: SO | D37: 25707951 | E37: 24106304 | F37: 241200149 | G37: 45680 | H37: PT. TIGAKA DISTRINDO PERKASA JAKARTA | I37: 077001020 | J37: FD&C RED NO.40 POWDER 20KG | K37: 20 | L37: KG | M37: 20 | N37: 457480.42 | O37: 9149608.4 | P37: 9149608.4 | Q37: 0 | R37: 0 | S37: IDR | T37: 4787896.5 | U37: 4787896.5 | V37: 4361711.8 | W37: 0.47671022 | X37: 4361711.8 | Y37: DEL | Z37: Delivered | AA37: 15159 | AB37: PT. TIGAKA DISTRINDO PERKASA CIKARANG | AC37: ELLY HENDRA | AD37: 35 | AE37: 0 | AF37: 961 | AG37: TCSP | AH37: TRA COL SYN DYE POWDER | AJ37: . | AK37: T | AL37: Non-Affiliate | AM37: Distributor | AN37: =VLOOKUP(I37,Sheet1!A:D,4,) -> A320400 | AP37: Invoice di kasih tanggal 28/1/25. Invoice tgl 15,23,24. coratex masih nyoba,MB terima di tanggal 28/1/25. jam 11:08.
A38: 45658 | B38: Invoiced | C38: SO | D38: 25707952 | E38: 24106393 | F38: 241100256 | G38: 45680 | H38: PT. TIGAKA DISTRINDO PERKASA PHARMA | I38: 030131005 | J38: BETA CAROTENE ORANGE P 10% 5KG | K38: 5 | L38: KG | M38: 5 | N38: 4207423.8 | O38: 21037119 | P38: 21037119 | Q38: 0 | R38: 0 | S38: IDR | T38: 15728978 | U38: 15728978 | V38: 5308141.1 | W38: 0.25232262 | X38: 5308141.1 | Z38: . | AA38: 2306153 | AB38: PT. TIGAKA DISTRINDO PERKASA PHARMA | AC38: ELLY HENDRA | AD38: 35 | AE38: 0 | AF38: 966 | AG38: TCNP | AH38: TRA COL NAT POWDER | AJ38: . | AK38: T | AL38: Non-Affiliate | AM38: Distributor | AN38: =VLOOKUP(I38,Sheet1!A:D,4,) -> A320400 | AP38: Invoice di kasih tanggal 28/1/25. Invoice tgl 15,23,24. coratex masih nyoba,MB terima di tanggal 28/1/25. jam 11:08.
A39: 45658 | B39: Invoiced | C39: SO | D39: 25707953 | E39: 24106404 | F39: 241200189 | G39: 45680 | H39: PT. TIGAKA DISTRINDO PERKASA JAKARTA | I39: 503651.010 | J39: HICKORY BROWN L-WS | K39: 40 | L39: KG | M39: 40 | N39: 496676.77 | O39: 19867071 | P39: 19867071 | Q39: 0 | R39: 0 | S39: IDR | T39: 7235234.3 | U39: 7235234.3 | V39: 12631837 | W39: 0.63581776 | X39: 12631837 | Y39: DEL | Z39: Delivered | AA39: 15159 | AB39: PT. TIGAKA DISTRINDO PERKASA CIKARANG | AC39: ELLY HENDRA | AD39: 35 | AE39: 0 | AF39: 966 | AG39: TCNL | AH39: TRA COL NAT LIQUID | AJ39: . | AK39: T | AL39: Non-Affiliate | AM39: Distributor | AN39: =VLOOKUP(I39,Sheet1!A:D,4,) -> A320400 | AP39: Invoice di kasih tanggal 28/1/25. Invoice tgl 15,23,24. coratex masih nyoba,MB terima di tanggal 28/1/25. jam 11:08.
A40: 45658 | B40: Invoiced | C40: SO | D40: 25707954 | E40: 24106454 | F40: 241200209 | G40: 45680 | H40: PT. TIGAKA DISTRINDO PERKASA JAKARTA | I40: 506091C-0013 | J40: FUSION HAZELNUT BROWN L-WS | K40: 13 | L40: KG | M40: 13 | N40: 730500.18 | O40: 9496502.3 | P40: 9496502.3 | Q40: 0 | R40: 0 | S40: IDR | T40: 3426516 | U40: 3426516 | V40: 6069986.3 | W40: 0.63918126 | X40: 6069986.3 | Y40: DEL | Z40: Delivered | AA40: 15159 | AB40: PT. TIGAKA DISTRINDO PERKASA CIKARANG | AC40: ELLY HENDRA | AD40: 35 | AE40: 0 | AF40: 960 | AH40: . | AJ40: . | AK40: T | AL40: Non-Affiliate | AM40: Distributor | AN40: =VLOOKUP(I40,Sheet1!A:D,4,) -> A320400 | AP40: Invoice di kasih tanggal 28/1/25. Invoice tgl 15,23,24. coratex masih nyoba,MB terima di tanggal 28/1/25. jam 11:08.
A41: 45658 | B41: Invoiced | C41: SO | D41: 25707955 | E41: 24106471 | F41: 241200214 | G41: 45680 | H41: PT. TIGAKA DISTRINDO PERKASA JAKARTA | I41: 409050.005 | J41: PAPRIKA EXT 20000 CU L-WS 5KG | K41: 25 | L41: KG | M41: 25 | N41: 1452750.5 | O41: 36318763 | P41: 36318763 | Q41: 0 | R41: 0 | S41: IDR | T41: 8948520.5 | U41: 8948520.5 | V41: 27370242 | W41: 0.75361164 | X41: 27370242 | Y41: DEL | Z41: Delivered | AA41: 15159 | AB41: PT. TIGAKA DISTRINDO PERKASA CIKARANG | AC41: ELLY HENDRA | AD41: 35 | AE41: 0 | AF41: 966 | AG41: TCNL | AH41: TRA COL NAT LIQUID | AJ41: . | AK41: T | AL41: Non-Affiliate | AM41: Distributor | AN41: =VLOOKUP(I41,Sheet1!A:D,4,) -> A320400 | AP41: Invoice di kasih tanggal 28/1/25. Invoice tgl 15,23,24. coratex masih nyoba,MB terima di tanggal 28/1/25. jam 11:08.
A42: 45658 | B42: Invoiced | C42: SO | D42: 25707956 | E42: 24106495 | F42: 241100301 | G42: 45680 | H42: PT. TIGAKA DISTRINDO PERKASA PHARMA | I42: 503651.010 | J42: HICKORY BROWN L-WS | K42: 140 | L42: KG | M42: 140 | N42: 512722.96 | O42: 71781214 | P42: 71781214 | Q42: 0 | R42: 0 | S42: IDR | T42: 25323320 | U42: 25323320 | V42: 46457894 | W42: 0.64721522 | X42: 46457894 | Z42: . | AA42: 2306153 | AB42: PT. TIGAKA DISTRINDO PERKASA PHARMA | AC42: ELLY HENDRA | AD42: 35 | AE42: 0 | AF42: 966 | AG42: TCNL | AH42: TRA COL NAT LIQUID | AJ42: . | AK42: T | AL42: Non-Affiliate | AM42: Distributor | AN42: =VLOOKUP(I42,Sheet1!A:D,4,) -> A320400 | AP42: Invoice di kasih tanggal 28/1/25. Invoice tgl 15,23,24. coratex masih nyoba,MB terima di tanggal 28/1/25. jam 11:08.
A43: 45658 | B43: Invoiced | C43: SO | D43: 25707957 | E43: 24106502 | F43: 241100304 | G43: 45680 | H43: PT. TIGAKA DISTRINDO PERKASA PHARMA | I43: 503651.010 | J43: HICKORY BROWN L-WS | K43: 10 | L43: KG | M43: 10 | N43: 512722.96 | O43: 5127229.6 | P43: 5127229.6 | Q43: 0 | R43: 0 | S43: IDR | T43: 1808808.6 | U43: 1808808.6 | V43: 3318421 | W43: 0.64721522 | X43: 3318421 | Z43: . | AA43: 2306153 | AB43: PT. TIGAKA DISTRINDO PERKASA PHARMA | AC43: ELLY HENDRA | AD43: 35 | AE43: 0 | AF43: 966 | AG43: TCNL | AH43: TRA COL NAT LIQUID | AJ43: . | AK43: T | AL43: Non-Affiliate | AM43: Distributor | AN43: =VLOOKUP(I43,Sheet1!A:D,4,) -> A320400 | AP43: Invoice di kasih tanggal 28/1/25. Invoice tgl 15,23,24. coratex masih nyoba,MB terima di tanggal 28/1/25. jam 11:08.
A44: 45658 | B44: Invoiced | C44: SO | D44: 25707958 | E44: 24106528 | F44: 241200229 | G44: 45680 | H44: PT. TIGAKA DISTRINDO PERKASA JAKARTA -AA | I44: 979007.005 | J44: MINT GREEN 97P-WS 5KG | K44: 15 | L44: KG | M44: 15 | N44: 9178191.3 | O44: 1.3767287e+08 | P44: 1.3767287e+08 | Q44: 0 | R44: 0 | S44: IDR | T44: 95184330 | U44: 95184330 | V44: 42488539 | W44: 0.30861955 | X44: 42488539 | Z44: . | AA44: 2306495 | AB44: PT. TIGAKA DISTRINDO PERKASA CIKARANG-AA | AC44: AGNESYA ADIFILIA | AD44: 94 | AE44: 0 | AF44: 966 | AG44: TCNL | AH44: TRA COL NAT LIQUID | AJ44: . | AK44: T | AL44: Non-Affiliate | AM44: Distributor | AN44: =VLOOKUP(I44,Sheet1!A:D,4,) -> A320400 | AP44: Invoice di kasih tanggal 28/1/25. Invoice tgl 15,23,24. coratex masih nyoba,MB terima di tanggal 28/1/25. jam 11:08.
A45: 45658 | B45: Invoiced | C45: SO | D45: 25707959 | E45: 25106575 | F45: 251200012 | G45: 45680 | H45: PT. TIGAKA DISTRINDO PERKASA JAKARTA -AA | I45: 086211020 | J45: SUNSET YELLOW CS 20KG | K45: 80 | L45: KG | M45: 80 | N45: 321116.34 | O45: 25689307 | P45: 25689307 | Q45: 0 | R45: 0 | S45: IDR | T45: 11548865 | U45: 11548865 | V45: 14140442 | W45: 0.55044076 | X45: 14140442 | Z45: . | AA45: 2306495 | AB45: PT. TIGAKA DISTRINDO PERKASA CIKARANG-AA | AC45: AGNESYA ADIFILIA | AD45: 94 | AE45: 0 | AF45: 961 | AG45: TCSP | AH45: TRA COL SYN DYE POWDER | AJ45: . | AK45: T | AL45: Non-Affiliate | AM45: Distributor | AN45: =VLOOKUP(I45,Sheet1!A:D,4,) -> A320400 | AP45: Invoice di kasih tanggal 28/1/25. Invoice tgl 15,23,24. coratex masih nyoba,MB terima di tanggal 28/1/25. jam 11:08.
A46: 45658 | B46: Invoiced | C46: SO | D46: 25707961 | E46: 25106585 | F46: 251200006 | G46: 45674 | H46: PT. TIGAKA DISTRINDO PERKASA JAKARTA | I46: IC10348 | J46: BRIGHT RED P-WS | K46: 2 | L46: KG | M46: 2 | N46: 2706505.3 | O46: 5413010.6 | P46: 5413010.6 | Q46: 0 | R46: 0 | S46: IDR | T46: 4160416.8 | U46: 4160416.8 | V46: 1252593.8 | W46: 0.23140428 | X46: 1252593.8 | Y46: DEL | Z46: Delivered | AA46: 15159 | AB46: PT. TIGAKA DISTRINDO PERKASA CIKARANG | AC46: ELLY HENDRA | AD46: 35 | AE46: 0 | AF46: 960 | AH46: . | AJ46: . | AK46: T | AL46: Non-Affiliate | AM46: Distributor | AN46: =VLOOKUP(I46,Sheet1!A:D,4,) -> A320400 | AP46: Invoice di kasih tanggal 28/1/25. Invoice tgl 15,23,24. coratex masih nyoba,MB terima di tanggal 28/1/25. jam 11:08.
A47: 45689 | B47: Invoiced | C47: SO | D47: 25707966 | E47: 24106442 | F47: 241200200 | G47: 45692 | H47: PT. TIGAKA DISTRINDO PERKASA JAKARTA | I47: C86040O20 | J47: EUROCERT SUNSET YELLOW BG | K47: 300 | L47: KG | M47: 300 | N47: 192785.98 | O47: 57835794 | P47: 57835794 | Q47: 0 | R47: 0 | S47: IDR | T47: 35293705 | U47: 35293705 | V47: 22542089 | W47: 0.38976017 | X47: 22542089 | Y47: DEL | Z47: Delivered | AA47: 15159 | AB47: PT. TIGAKA DISTRINDO PERKASA CIKARANG | AC47: ELLY HENDRA | AD47: 35 | AE47: 0 | AF47: 960 | AH47: . | AJ47: . | AK47: T | AL47: Non-Affiliate | AM47: Distributor | AN47: =VLOOKUP(I47,Sheet1!A:D,4,) -> A320400 | AP47: Invoice di kasih tanggal 7/02/25. Finance abis clossing. MB terima di tanggal 7/2/25 jam 18:19
A48: 45689 | B48: Invoiced | C48: SO | D48: 25707967 | E48: 24106459 | F48: 241200210 | G48: 45692 | H48: PT. TIGAKA DISTRINDO PERKASA JAKARTA | I48: 043771020 | J48: YELLOW MICROFINE | K48: 100 | L48: KG | M48: 100 | N48: 1715811.5 | O48: 171581152 | P48: 171581152 | Q48: 0 | R48: 0 | S48: IDR | T48: 1.437859e+08 | U48: 1.437859e+08 | V48: 27795253 | W48: 0.16199479 | X48: 27795253 | Y48: DEL | Z48: Delivered | AA48: 15159 | AB48: PT. TIGAKA DISTRINDO PERKASA CIKARANG | AC48: ELLY HENDRA | AD48: 35 | AE48: 0 | AF48: 966 | AH48: . | AJ48: . | AK48: T | AL48: Non-Affiliate | AM48: Distributor | AN48: =VLOOKUP(I48,Sheet1!A:D,4,) -> A320400 | AP48: Invoice di kasih tanggal 7/02/25. Finance abis clossing. MB terima di tanggal 7/2/25 jam 18:19
A49: 45689 | B49: Invoiced | C49: SO | D49: 25707968 | E49: 24106484 | F49: 241200220 | G49: 45692 | H49: PT. TIGAKA DISTRINDO PERKASA JAKARTA | I49: 503651.010 | J49: HICKORY BROWN L-WS | K49: 60 | L49: KG | M49: 60 | N49: 504485.63 | O49: 30269138 | P49: 30269138 | Q49: 0 | R49: 0 | S49: IDR | T49: 10861707 | U49: 10861707 | V49: 19407430 | W49: 0.64116231 | X49: 19407430 | Y49: DEL | Z49: Delivered | AA49: 15159 | AB49: PT. TIGAKA DISTRINDO PERKASA CIKARANG | AC49: ELLY HENDRA | AD49: 35 | AE49: 0 | AF49: 966 | AG49: TCNL | AH49: TRA COL NAT LIQUID | AJ49: . | AK49: T | AL49: Non-Affiliate | AM49: Distributor | AN49: =VLOOKUP(I49,Sheet1!A:D,4,) -> A320400 | AP49: Invoice di kasih tanggal 7/02/25. Finance abis clossing. MB terima di tanggal 7/2/25 jam 18:19
A50: 45689 | B50: Invoiced | C50: SO | D50: 25707969 | E50: 24106489 | F50: 241200222 | G50: 45692 | H50: PT. TIGAKA DISTRINDO PERKASA JAKARTA | I50: 97CA0826 | J50: SPIRULINA DISPERSION OB | K50: 200 | L50: KG | M50: 200 | N50: 1459753.6 | O50: 291950730 | P50: 291950730 | Q50: 0 | R50: 0 | S50: IDR | T50: 2.2579017e+08 | U50: 2.2579017e+08 | V50: 66160564 | W50: 0.22661551 | X50: 66160564 | Y50: DEL | Z50: Delivered | AA50: 15159 | AB50: PT. TIGAKA DISTRINDO PERKASA CIKARANG | AC50: ELLY HENDRA | AD50: 35 | AE50: 0 | AF50: 960 | AH50: . | AJ50: . | AK50: T | AL50: Non-Affiliate | AM50: Distributor | AN50: =VLOOKUP(I50,Sheet1!A:D,4,) -> A320400 | AP50: Invoice di kasih tanggal 7/02/25. Finance abis clossing. MB terima di tanggal 7/2/25 jam 18:19
A51: 45689 | B51: Invoiced | C51: SO | D51: 25707970 | E51: 24106499 | F51: 241200227 | G51: 45692 | H51: PT. TIGAKA DISTRINDO PERKASA JAKARTA | I51: 97CB0907 | J51: NATURAL CAROTENE LOS | K51: 15 | L51: KG | M51: 15 | N51: 1990618 | O51: 29859270 | P51: 29859270 | Q51: 0 | R51: 0 | S51: IDR | T51: 15229820 | U51: 15229820 | V51: 14629451 | W51: 0.48994669 | X51: 14629451 | Y51: DEL | Z51: Delivered | AA51: 15159 | AB51: PT. TIGAKA DISTRINDO PERKASA CIKARANG | AC51: ELLY HENDRA | AD51: 35 | AE51: 0 | AF51: 966 | AH51: . | AJ51: . | AK51: T | AL51: Non-Affiliate | AM51: Distributor | AN51: =VLOOKUP(I51,Sheet1!A:D,4,) -> A320400 | AP51: Invoice di kasih tanggal 7/02/25. Finance abis clossing. MB terima di tanggal 7/2/25 jam 18:19
A52: 45689 | B52: Invoiced | C52: SO | D52: 25707971 | E52: 25106548 | F52: 251100002 | G52: 45692 | H52: PT. TIGAKA DISTRINDO PERKASA PHARMA | I52: 503651.010 | J52: HICKORY BROWN L-WS | K52: 120 | L52: KG | M52: 120 | N52: 519809.41 | O52: 62377129 | P52: 62377129 | Q52: 0 | R52: 0 | S52: IDR | T52: 21723415 | U52: 21723415 | V52: 40653714 | W52: 0.65174071 | X52: 40653714 | Z52: . | AA52: 2306153 | AB52: PT. TIGAKA DISTRINDO PERKASA PHARMA | AC52: ELLY HENDRA | AD52: 35 | AE52: 0 | AF52: 966 | AG52: TCNL | AH52: TRA COL NAT LIQUID | AJ52: . | AK52: T | AL52: Non-Affiliate | AM52: Distributor | AN52: =VLOOKUP(I52,Sheet1!A:D,4,) -> A320400 | AP52: Invoice di kasih tanggal 7/02/25. Finance abis clossing. MB terima di tanggal 7/2/25 jam 18:19
A53: 45689 | B53: Invoiced | C53: SO | D53: 25707972 | E53: 24106315 | F53: 241200153 | G53: 45692 | H53: PT. TIGAKA DISTRINDO PERKASA JAKARTA | I53: 993060010 | J53: EUROLAKE ERYTHROSINE 10KG 10KG | K53: 100 | L53: KG | M53: 100 | N53: 1593215.4 | O53: 159321540 | P53: 159321540 | Q53: 0 | R53: 0 | S53: IDR | T53: 124665800 | U53: 124665800 | V53: 34655740 | W53: 0.21752074 | X53: 34655740 | Y53: DEL | Z53: Delivered | AA53: 15159 | AB53: PT. TIGAKA DISTRINDO PERKASA CIKARANG | AC53: ELLY HENDRA | AD53: 35 | AE53: 0 | AF53: 963 | AG53: TCSK | AH53: TRA COL SYN LAKE | AJ53: . | AK53: T | AL53: Non-Affiliate | AM53: Distributor | AN53: =VLOOKUP(I53,Sheet1!A:D,4,) -> A320400 | AP53: Invoice di kasih tanggal 7/02/25. Finance abis clossing. MB terima di tanggal 7/2/25 jam 18:19
A54: 45689 | B54: Invoiced | C54: SO | D54: 25707973 | E54: 24106353 | F54: 241100225 | G54: 45692 | H54: PT. TIGAKA DISTRINDO PERKASA PHARMA | I54: 096231020 | J54: FD&C YELLOW 6 AL LK20-24% 20KG | K54: 300 | L54: KG | M54: 300 | N54: 384600.54 | O54: 115380162 | P54: 115380162 | Q54: 0 | R54: 0 | S54: IDR | T54: 69828751 | U54: 69828751 | V54: 45551411 | W54: 0.39479413 | X54: 45551411 | Z54: . | AA54: 2306153 | AB54: PT. TIGAKA DISTRINDO PERKASA PHARMA | AC54: ELLY HENDRA | AD54: 35 | AE54: 0 | AF54: 963 | AG54: TCSK | AH54: TRA COL SYN LAKE | AJ54: . | AK54: T | AL54: Non-Affiliate | AM54: Distributor | AN54: =VLOOKUP(I54,Sheet1!A:D,4,) -> A320400 | AP54: Invoice di kasih tanggal 7/02/25. Finance abis clossing. MB terima di tanggal 7/2/25 jam 18:19
A55: 45689 | B55: Invoiced | C55: SO | D55: 25707973 | E55: 24106353 | F55: 241100225 | G55: 45692 | H55: PT. TIGAKA DISTRINDO PERKASA PHARMA | I55: 503262.010 | J55: RASPBERRY RED P-WS 10KG | K55: 600 | L55: KG | M55: 600 | N55: 410282.59 | O55: 246169554 | P55: 246169554 | Q55: 0 | R55: 0 | S55: IDR | T55: 1.0842934e+08 | U55: 1.0842934e+08 | V55: 1.3774022e+08 | W55: 0.55953393 | X55: 1.3774022e+08 | Z55: . | AA55: 2306153 | AB55: PT. TIGAKA DISTRINDO PERKASA PHARMA | AC55: ELLY HENDRA | AD55: 35 | AE55: 0 | AF55: 966 | AG55: TCNP | AH55: TRA COL NAT POWDER | AJ55: . | AK55: T | AL55: Non-Affiliate | AM55: Distributor | AN55: =VLOOKUP(I55,Sheet1!A:D,4,) -> A320400 | AP55: Invoice di kasih tanggal 7/02/25. Finance abis clossing. MB terima di tanggal 7/2/25 jam 18:19
A56: 45689 | B56: Invoiced | C56: SO | D56: 25707973 | E56: 24106353 | F56: 241100225 | G56: 45692 | H56: PT. TIGAKA DISTRINDO PERKASA PHARMA | I56: 503213.020 | J56: VITIS RED 4P-WS 20KG | K56: 60 | L56: KG | M56: 60 | N56: 1543916.7 | O56: 92635003 | P56: 92635003 | Q56: 0 | R56: 0 | S56: IDR | T56: 39273673 | U56: 39273673 | V56: 53361330 | W56: 0.57603852 | X56: 53361330 | Z56: . | AA56: 2306153 | AB56: PT. TIGAKA DISTRINDO PERKASA PHARMA | AC56: ELLY HENDRA | AD56: 35 | AE56: 0 | AF56: 966 | AG56: TCNP | AH56: TRA COL NAT POWDER | AJ56: . | AK56: T | AL56: Non-Affiliate | AM56: Distributor | AN56: =VLOOKUP(I56,Sheet1!A:D,4,) -> A320400 | AP56: Invoice di kasih tanggal 7/02/25. Finance abis clossing. MB terima di tanggal 7/2/25 jam 18:19
A57: 45689 | B57: Invoiced | C57: SO | D57: 25707974 | E57: 24106356 | F57: 241100228 | G57: 45692 | H57: PT. TIGAKA DISTRINDO PERKASA PHARMA | I57: 503262.010 | J57: RASPBERRY RED P-WS 10KG | K57: 590 | L57: KG | M57: 590 | N57: 410282.59 | O57: 2.4206673e+08 | P57: 2.4206673e+08 | Q57: 0 | R57: 0 | S57: IDR | T57: 1.0662218e+08 | U57: 1.0662218e+08 | V57: 1.3544455e+08 | W57: 0.55953393 | X57: 1.3544455e+08 | Z57: . | AA57: 2306153 | AB57: PT. TIGAKA DISTRINDO PERKASA PHARMA | AC57: ELLY HENDRA | AD57: 35 | AE57: 0 | AF57: 966 | AG57: TCNP | AH57: TRA COL NAT POWDER | AJ57: . | AK57: T | AL57: Non-Affiliate | AM57: Distributor | AN57: =VLOOKUP(I57,Sheet1!A:D,4,) -> A320400 | AP57: Invoice di kasih tanggal 7/02/25. Finance abis clossing. MB terima di tanggal 7/2/25 jam 18:19
A58: 45689 | B58: Invoiced | C58: SO | D58: 25707974 | E58: 24106356 | F58: 241100228 | G58: 45692 | H58: PT. TIGAKA DISTRINDO PERKASA PHARMA | I58: 503213.020 | J58: VITIS RED 4P-WS 20KG | K58: 60 | L58: KG | M58: 60 | N58: 1543916.7 | O58: 92635003 | P58: 92635003 | Q58: 0 | R58: 0 | S58: IDR | T58: 39273673 | U58: 39273673 | V58: 53361330 | W58: 0.57603852 | X58: 53361330 | Z58: . | AA58: 2306153 | AB58: PT. TIGAKA DISTRINDO PERKASA PHARMA | AC58: ELLY HENDRA | AD58: 35 | AE58: 0 | AF58: 966 | AG58: TCNP | AH58: TRA COL NAT POWDER | AJ58: . | AK58: T | AL58: Non-Affiliate | AM58: Distributor | AN58: =VLOOKUP(I58,Sheet1!A:D,4,) -> A320400 | AP58: Invoice di kasih tanggal 7/02/25. Finance abis clossing. MB terima di tanggal 7/2/25 jam 18:19
A59: 45689 | B59: Invoiced | C59: SO | D59: 25707975 | E59: 24106388 | F59: 241100251 | G59: 45692 | H59: PT. TIGAKA DISTRINDO PERKASA PHARMA | I59: 036431020 | J59: BERRY MICROFINE 20KG | K59: 120 | L59: KG | M59: 120 | N59: 790453.18 | O59: 94854382 | P59: 94854382 | Q59: 0 | R59: 0 | S59: IDR | T59: 65369948 | U59: 65369948 | V59: 29484434 | W59: 0.31083892 | X59: 29484434 | Z59: . | AA59: 2306153 | AB59: PT. TIGAKA DISTRINDO PERKASA PHARMA | AC59: ELLY HENDRA | AD59: 35 | AE59: 0 | AF59: 960 | AH59: . | AJ59: . | AK59: T | AL59: Non-Affiliate | AM59: Distributor | AN59: =VLOOKUP(I59,Sheet1!A:D,4,) -> A320400 | AP59: Invoice di kasih tanggal 7/02/25. Finance abis clossing. MB terima di tanggal 7/2/25 jam 18:19
A60: 45689 | B60: Invoiced | C60: SO | D60: 25707976 | E60: 24106408 | F60: 241200190 | G60: 45692 | H60: PT. TIGAKA DISTRINDO PERKASA JAKARTA | I60: 952360010 | J60: PONCEAU 4R LAKE MD 10KG | K60: 300 | L60: KG | M60: 300 | N60: 402735.74 | O60: 120820722 | P60: 120820722 | Q60: 0 | R60: 0 | S60: IDR | T60: 93780030 | U60: 93780030 | V60: 27040692 | W60: 0.2238084 | X60: 27040692 | Y60: DEL | Z60: Delivered | AA60: 15159 | AB60: PT. TIGAKA DISTRINDO PERKASA CIKARANG | AC60: ELLY HENDRA | AD60: 35 | AE60: 0 | AF60: 963 | AG60: TCSK | AH60: TRA COL SYN LAKE | AJ60: . | AK60: T | AL60: Non-Affiliate | AM60: Distributor | AN60: =VLOOKUP(I60,Sheet1!A:D,4,) -> A320400 | AP60: Invoice di kasih tanggal 7/02/25. Finance abis clossing. MB terima di tanggal 7/2/25 jam 18:19
A61: 45689 | B61: Invoiced | C61: SO | D61: 25707977 | E61: 24106443 | F61: 241100276 | G61: 45692 | H61: PT. TIGAKA DISTRINDO PERKASA PHARMA | I61: 077001020 | J61: FD&C RED NO.40 POWDER 20KG | K61: 40 | L61: KG | M61: 40 | N61: 431239.87 | O61: 17249595 | P61: 17249595 | Q61: 0 | R61: 0 | S61: IDR | T61: 9575793.1 | U61: 9575793.1 | V61: 7673801.7 | W61: 0.44486852 | X61: 7673801.7 | Z61: . | AA61: 2306153 | AB61: PT. TIGAKA DISTRINDO PERKASA PHARMA | AC61: ELLY HENDRA | AD61: 35 | AE61: 0 | AF61: 961 | AG61: TCSP | AH61: TRA COL SYN DYE POWDER | AJ61: . | AK61: T | AL61: Non-Affiliate | AM61: Distributor | AN61: =VLOOKUP(I61,Sheet1!A:D,4,) -> A320400 | AP61: Invoice di kasih tanggal 7/02/25. Finance abis clossing. MB terima di tanggal 7/2/25 jam 18:19
A62: 45689 | B62: Invoiced | C62: SO | D62: 25707977 | E62: 24106443 | F62: 241100276 | G62: 45692 | H62: PT. TIGAKA DISTRINDO PERKASA PHARMA | I62: 030131005 | J62: BETA CAROTENE ORANGE P 10% 5KG | K62: 10 | L62: KG | M62: 10 | N62: 4207423.8 | O62: 42074238 | P62: 42074238 | Q62: 0 | R62: 0 | S62: IDR | T62: 31457956 | U62: 31457956 | V62: 10616282 | W62: 0.25232262 | X62: 10616282 | Z62: . | AA62: 2306153 | AB62: PT. TIGAKA DISTRINDO PERKASA PHARMA | AC62: ELLY HENDRA | AD62: 35 | AE62: 0 | AF62: 966 | AG62: TCNP | AH62: TRA COL NAT POWDER | AJ62: . | AK62: T | AL62: Non-Affiliate | AM62: Distributor | AN62: =VLOOKUP(I62,Sheet1!A:D,4,) -> A320400 | AP62: Invoice di kasih Jam 15:00, invoice tanggal 6/2/25. MB terima di tanggal 11/2/25
A63: 45689 | B63: Invoiced | C63: SO | D63: 25707978 | E63: 24106465 | F63: 241100284 | G63: 45692 | H63: PT. TIGAKA DISTRINDO PERKASA PHARMA | I63: 057581020 | J63: GRAPE SHADE R SD | K63: 20 | L63: KG | M63: 20 | N63: 1126492.6 | O63: 22529852 | P63: 22529852 | Q63: 0 | R63: 0 | S63: IDR | T63: 10425191 | U63: 10425191 | V63: 12104661 | W63: 0.53727212 | X63: 12104661 | Z63: . | AA63: 2306153 | AB63: PT. TIGAKA DISTRINDO PERKASA PHARMA | AC63: ELLY HENDRA | AD63: 35 | AE63: 0 | AF63: 960 | AH63: . | AJ63: . | AK63: T | AL63: Non-Affiliate | AM63: Distributor | AN63: =VLOOKUP(I63,Sheet1!A:D,4,) -> A320400 | AP63: Invoice di kasih Jam 15:00, invoice tanggal 6/2/25. MB terima di tanggal 11/2/25
A64: 45689 | B64: Invoiced | C64: SO | D64: 25707984 | E64: 25106592 | F64: 251100026 | G64: 45694 | H64: PT. TIGAKA DISTRINDO PERKASA PHARMA | I64: 88011C | J64: SPECTRABLEND CLEAR | K64: 25 | L64: KG | M64: 25 | N64: 362987.27 | O64: 9074681.8 | P64: 9074681.8 | Q64: 0 | R64: 0 | S64: IDR | T64: 18082698 | U64: 18082698 | V64: -9008016.2 | W64: -0.99265368 | X64: -9008016.2 | Z64: . | AA64: 2306153 | AB64: PT. TIGAKA DISTRINDO PERKASA PHARMA | AC64: ELLY HENDRA | AD64: 35 | AE64: 0 | AF64: 960 | AH64: . | AJ64: . | AK64: T | AL64: Non-Affiliate | AM64: Distributor | AN64: =VLOOKUP(I64,Sheet1!A:D,4,) -> #N/A | AP64: Invoice di kasih Jam 15:00, invoice tanggal 6/2/25. MB terima di tanggal 11/2/25
A65: 45689 | B65: Invoiced | C65: SO | D65: 25707984 | E65: 25106592 | F65: 251100026 | G65: 45694 | H65: PT. TIGAKA DISTRINDO PERKASA PHARMA | I65: CM-2234 | J65: SPECTRABLEND CCZ WHITE | K65: 25 | L65: KG | M65: 25 | N65: 376328.8 | O65: 9408220 | P65: 9408220 | Q65: 0 | R65: 0 | S65: IDR | T65: 18381938 | U65: 18381938 | V65: -8973718.4 | W65: -0.95381681 | X65: -8973718.4 | Z65: . | AA65: 2306153 | AB65: PT. TIGAKA DISTRINDO PERKASA PHARMA | AC65: ELLY HENDRA | AD65: 35 | AE65: 0 | AF65: 960 | AH65: . | AJ65: . | AK65: T | AL65: Non-Affiliate | AM65: Distributor | AN65: =VLOOKUP(I65,Sheet1!A:D,4,) -> #N/A | AP65: Invoice di kasih Jam 15:00, invoice tanggal 6/2/25. MB terima di tanggal 11/2/25
A66: 45689 | B66: Invoiced | C66: SO | D66: 25707985 | E66: 25106575 | F66: 251200012 | G66: 45694 | H66: PT. TIGAKA DISTRINDO PERKASA JAKARTA -AA | I66: T230104 | J66: EUROBLEND GREEN 973 | K66: 100 | L66: KG | M66: 100 | N66: 586934.7 | O66: 58693470 | P66: 58693470 | Q66: 0 | R66: 0 | S66: IDR | T66: 34575569 | U66: 34575569 | V66: 24117901 | W66: 0.41091285 | X66: 24117901 | Z66: . | AA66: 2306495 | AB66: PT. TIGAKA DISTRINDO PERKASA CIKARANG-AA | AC66: AGNESYA ADIFILIA | AD66: 94 | AE66: 0 | AF66: 960 | AH66: . | AJ66: . | AK66: T | AL66: Non-Affiliate | AM66: Distributor | AN66: =VLOOKUP(I66,Sheet1!A:D,4,) -> A320400 | AP66: Invoice di kasih Jam 15:00, invoice tanggal 6/2/25. MB terima di tanggal 11/2/25
A67: 45689 | B67: Invoiced | C67: SO | D67: 25707986 | E67: 25106593 | F67: 251100027 | G67: 45694 | H67: PT. TIGAKA DISTRINDO PERKASA JAKARTA -HI | I67: 11100444 | J67: LIQUID CARMINE PURPLE 2G | K67: 8 | L67: KG | M67: 8 | N67: 878588.64 | O67: 7028709.1 | P67: 7028709.1 | Q67: 0 | R67: 0 | S67: IDR | T67: 4238518 | U67: 4238518 | V67: 2790191.1 | W67: 0.39697063 | X67: 2790191.1 | Z67: . | AA67: 2306392 | AB67: PT. TIGAKA DISTRINDO PERKASA CIKARANG-HI | AC67: Handy Inarto | AD67: 104 | AE67: 0 | AF67: 960 | AH67: . | AJ67: . | AK67: T | AL67: Non-Affiliate | AM67: Distributor | AN67: =VLOOKUP(I67,Sheet1!A:D,4,) -> A320400 | AP67: Invoice di kasih Jam 15:00, invoice tanggal 6/2/25. MB terima di tanggal 11/2/25
A68: 45689 | B68: Invoiced | C68: SO | D68: 25707988 | E68: 24106439 | F68: 241200199 | G68: 45695 | H68: PT. TIGAKA DISTRINDO PERKASA JAKARTA | I68: 500095X25 | J68: KOWET TITANIUM DIOXIDE 25KG* | K68: 18000 | L68: KG | M68: 18000 | N68: 79995.46 | O68: 1439918280 | P68: 1439918280 | Q68: 0 | R68: 0 | S68: IDR | T68: 1.0987351e+09 | U68: 1.0987351e+09 | V68: 3.4118317e+08 | W68: 0.23694621 | X68: 3.4118317e+08 | Y68: DEL | Z68: Delivered | AA68: 15159 | AB68: PT. TIGAKA DISTRINDO PERKASA CIKARANG | AC68: ELLY HENDRA | AD68: 35 | AE68: 0 | AF68: 966 | AG68: TCNP | AH68: TRA COL NAT POWDER | AJ68: . | AK68: T | AL68: Non-Affiliate | AM68: Distributor | AN68: =VLOOKUP(I68,Sheet1!A:D,4,) -> A320400 | AP68: Invoice di kasih Jam 15:00, invoice tanggal 6/2/25. MB terima di tanggal 11/2/25
A69: 45689 | B69: Invoiced | C69: SO | D69: 25707994 | E69: 24106443 | F69: 241100276 | G69: 45699 | H69: PT. TIGAKA DISTRINDO PERKASA PHARMA | I69: 030131005 | J69: BETA CAROTENE ORANGE P 10% 5KG | K69: 20 | L69: KG | M69: 20 | N69: 4207423.8 | O69: 84148477 | P69: 84148477 | Q69: 0 | R69: 0 | S69: IDR | T69: 62915912 | U69: 62915912 | V69: 21232564 | W69: 0.25232262 | X69: 21232564 | Z69: . | AA69: 2306153 | AB69: PT. TIGAKA DISTRINDO PERKASA PHARMA | AC69: AGNESYA ADIFILIA | AD69: 94 | AE69: 0 | AF69: 966 | AG69: TCNP | AH69: TRA COL NAT POWDER | AJ69: . | AK69: T | AL69: Non-Affiliate | AM69: Distributor | AN69: =VLOOKUP(I69,Sheet1!A:D,4,) -> A320400 | AP69: Invoice di kasih jam 17:30.Invoice tanggal 11,15/2/25. MB terima di tanggal 19/2/25. Sore di tanggal yang sama
A70: 45689 | B70: Invoiced | C70: SO | D70: 25707995 | E70: 24106500 | F70: 241200228 | G70: 45699 | H70: PT. TIGAKA DISTRINDO PERKASA JAKARTA -AA | I70: 11100414 | J70: CARMINE WS 5% - 20KG | K70: 20 | L70: KG | M70: 20 | N70: 1056068.7 | O70: 21121374 | P70: 21121374 | Q70: 0 | R70: 0 | S70: IDR | T70: 13956470 | U70: 13956470 | V70: 7164903.7 | W70: 0.33922527 | X70: 7164903.7 | Z70: . | AA70: 2306495 | AB70: PT. TIGAKA DISTRINDO PERKASA CIKARANG-AA | AC70: AGNESYA ADIFILIA | AD70: 94 | AE70: 0 | AF70: 960 | AH70: . | AJ70: . | AK70: T | AL70: Non-Affiliate | AM70: Distributor | AN70: =VLOOKUP(I70,Sheet1!A:D,4,) -> A320400 | AP70: Invoice di kasih jam 17:30.Invoice tanggal 11,15/2/25. MB terima di tanggal 19/2/25. Sore di tanggal yang sama
A71: 45689 | B71: Invoiced | C71: SO | D71: 25707996 | E71: 24106528 | F71: 241200229 | G71: 45699 | H71: PT. TIGAKA DISTRINDO PERKASA JAKARTA -AA | I71: 11100414 | J71: CARMINE WS 5% - 20KG | K71: 20 | L71: KG | M71: 20 | N71: 1010309.4 | O71: 20206187 | P71: 20206187 | Q71: 0 | R71: 0 | S71: IDR | T71: 13956470 | U71: 13956470 | V71: 6249717.3 | W71: 0.30929721 | X71: 6249717.3 | Z71: . | AA71: 2306495 | AB71: PT. TIGAKA DISTRINDO PERKASA CIKARANG-AA | AC71: AGNESYA ADIFILIA | AD71: 94 | AE71: 0 | AF71: 960 | AH71: . | AJ71: . | AK71: T | AL71: Non-Affiliate | AM71: Distributor | AN71: =VLOOKUP(I71,Sheet1!A:D,4,) -> A320400 | AP71: Invoice di kasih jam 17:30.Invoice tanggal 11,15/2/25. MB terima di tanggal 19/2/25. Sore di tanggal yang sama
A72: 45689 | B72: Invoiced | C72: SO | D72: 25707997 | E72: 25106567 | F72: 251200010 | G72: 45699 | H72: PT. TIGAKA DISTRINDO PERKASA JAKARTA -AA | I72: 043771020 | J72: YELLOW MICROFINE | K72: 60 | L72: KG | M72: 60 | N72: 1964696.7 | O72: 1.178818e+08 | P72: 1.178818e+08 | Q72: 0 | R72: 0 | S72: IDR | T72: 86271540 | U72: 86271540 | V72: 31610262 | W72: 0.26815218 | X72: 31610262 | Z72: . | AA72: 2306495 | AB72: PT. TIGAKA DISTRINDO PERKASA CIKARANG-AA | AC72: AGNESYA ADIFILIA | AD72: 94 | AE72: 0 | AF72: 966 | AH72: . | AJ72: . | AK72: T | AL72: Non-Affiliate | AM72: Distributor | AN72: =VLOOKUP(I72,Sheet1!A:D,4,) -> A320400 | AP72: Invoice di kasih jam 17:30.Invoice tanggal 11,15/2/25. MB terima di tanggal 19/2/25. Sore di tanggal yang sama
A73: 45689 | B73: Invoiced | C73: SO | D73: 25707998 | E73: 24106471 | F73: 241200214 | G73: 45703 | H73: PT. TIGAKA DISTRINDO PERKASA JAKARTA | I73: 409050.005 | J73: PAPRIKA EXT 20000 CU L-WS 5KG | K73: 5 | L73: KG | M73: 5 | N73: 1452750.5 | O73: 7263752.5 | P73: 7263752.5 | Q73: 0 | R73: 0 | S73: IDR | T73: 1711818.6 | U73: 1711818.6 | V73: 5551933.9 | W73: 0.76433412 | X73: 5551933.9 | Y73: DEL | Z73: Delivered | AA73: 15159 | AB73: PT. TIGAKA DISTRINDO PERKASA CIKARANG | AC73: Handy Inarto | AD73: 104 | AE73: 0 | AF73: 966 | AG73: TCNL | AH73: TRA COL NAT LIQUID | AJ73: . | AK73: T | AL73: Non-Affiliate | AM73: Distributor | AN73: =VLOOKUP(I73,Sheet1!A:D,4,) -> A320400 | AP73: Invoice di kasih jam 17:30.Invoice tanggal 11,15/2/25. MB terima di tanggal 19/2/25. Sore di tanggal yang sama
A74: 45689 | B74: Invoiced | C74: SO | D74: 25707999 | E74: 25106560 | F74: 251200005 | G74: 45703 | H74: PT. TIGAKA DISTRINDO PERKASA JAKARTA | I74: 419360-0010 | J74: AVALANCHE MB P-WD 10KG | K74: 10 | L74: KG | M74: 10 | N74: 399520.28 | O74: 3995202.8 | P74: 3995202.8 | Q74: 0 | R74: 0 | S74: IDR | T74: 2221116 | U74: 2221116 | V74: 1774086.8 | W74: 0.44405425 | X74: 1774086.8 | Y74: DEL | Z74: Delivered | AA74: 15159 | AB74: PT. TIGAKA DISTRINDO PERKASA CIKARANG | AC74: Handy Inarto | AD74: 104 | AE74: 0 | AF74: 966 | AH74: . | AJ74: . | AK74: T | AL74: Non-Affiliate | AM74: Distributor | AN74: =VLOOKUP(I74,Sheet1!A:D,4,) -> A320400 | AP74: Invoice di kasih jam 17:30.Invoice tanggal 11,15/2/25. MB terima di tanggal 19/2/25. Sore di tanggal yang sama
A75: 45689 | B75: Invoiced | C75: SO | D75: 25708000 | E75: 25106566 | F75: 251100012 | G75: 45703 | H75: PT. TIGAKA DISTRINDO PERKASA PHARMA | I75: 409050.005 | J75: PAPRIKA EXT 20000 CU L-WS 5KG | K75: 100 | L75: KG | M75: 100 | N75: 1496877.9 | O75: 149687787 | P75: 149687787 | Q75: 0 | R75: 0 | S75: IDR | T75: 34236373 | U75: 34236373 | V75: 1.1545141e+08 | W75: 0.77128146 | X75: 1.1545141e+08 | Z75: . | AA75: 2306153 | AB75: PT. TIGAKA DISTRINDO PERKASA PHARMA | AC75: AGNESYA ADIFILIA | AD75: 94 | AE75: 0 | AF75: 966 | AG75: TCNL | AH75: TRA COL NAT LIQUID | AJ75: . | AK75: T | AL75: Non-Affiliate | AM75: Distributor | AN75: =VLOOKUP(I75,Sheet1!A:D,4,) -> A320400 | AP75: Invoice di kasih jam 17:30.Invoice tanggal 11,15/2/25. MB terima di tanggal 19/2/25. Sore di tanggal yang sama
A76: 45689 | B76: Invoiced | C76: SO | D76: 25708001 | E76: 25106589 | F76: 251100022 | G76: 45703 | H76: PT. TIGAKA DISTRINDO PERKASA PHARMA | I76: 503651.010 | J76: HICKORY BROWN L-WS | K76: 40 | L76: KG | M76: 40 | N76: 519809.41 | O76: 20792376 | P76: 20792376 | Q76: 0 | R76: 0 | S76: IDR | T76: 7241138.3 | U76: 7241138.3 | V76: 13551238 | W76: 0.65174071 | X76: 13551238 | Z76: . | AA76: 2306153 | AB76: PT. TIGAKA DISTRINDO PERKASA PHARMA | AC76: AGNESYA ADIFILIA | AD76: 94 | AE76: 0 | AF76: 966 | AG76: TCNL | AH76: TRA COL NAT LIQUID | AJ76: . | AK76: T | AL76: Non-Affiliate | AM76: Distributor | AN76: =VLOOKUP(I76,Sheet1!A:D,4,) -> A320400 | AP76: Invoice di kasih jam 17:30.Invoice tanggal 11,15/2/25. MB terima di tanggal 19/2/25. Sore di tanggal yang sama
A77: 45689 | B77: Invoiced | C77: SO | D77: 25708002 | E77: 25106594 | F77: 251200020 | G77: 45703 | H77: PT. TIGAKA DISTRINDO PERKASA JAKARTA | I77: 419360-0010 | J77: AVALANCHE MB P-WD 10KG | K77: 150 | L77: KG | M77: 150 | N77: 405289.69 | O77: 60793454 | P77: 60793454 | Q77: 0 | R77: 0 | S77: IDR | T77: 33316740 | U77: 33316740 | V77: 27476714 | W77: 0.45196829 | X77: 27476714 | Y77: DEL | Z77: Delivered | AA77: 15159 | AB77: PT. TIGAKA DISTRINDO PERKASA CIKARANG | AC77: Handy Inarto | AD77: 104 | AE77: 0 | AF77: 966 | AH77: . | AJ77: . | AK77: T | AL77: Non-Affiliate | AM77: Distributor | AN77: =VLOOKUP(I77,Sheet1!A:D,4,) -> A320400 | AP77: Invoice di kasih jam 17:30.Invoice tanggal 11,15/2/25. MB terima di tanggal 19/2/25. Sore di tanggal yang sama
A78: 45689 | B78: Invoiced | C78: SO | D78: 25708016 | E78: 25106583 | F78: 251100018 | G78: 45700 | H78: PT. TIGAKA DISTRINDO PERKASA PHARMA | I78: 509191020 | J78: NO.50919 RED IRON OXIDE 20KG | K78: 20 | L78: KG | M78: 20 | N78: 2759272.1 | O78: 55185443 | P78: 55185443 | Q78: 0 | R78: 0 | S78: IDR | T78: 43499784 | U78: 43499784 | V78: 11685659 | W78: 0.21175256 | X78: 11685659 | Z78: . | AA78: 2306153 | AB78: PT. TIGAKA DISTRINDO PERKASA PHARMA | AC78: AGNESYA ADIFILIA | AD78: 94 | AE78: 0 | AF78: 968 | AH78: . | AJ78: . | AK78: T | AL78: Non-Affiliate | AM78: Distributor | AN78: =VLOOKUP(I78,Sheet1!A:D,4,) -> A320400 | AP78: Invoice dikasih pas Mau Makan Siang, Invoice tgl 17,12,19,.MB terima Di tanggal 25/2/25. jam 12:25
A79: 45689 | B79: Invoiced | C79: SO | D79: 25708017 | E79: 25106611 | F79: 251200032 | G79: 45707 | H79: PT. TIGAKA DISTRINDO PERKASA JAKARTA | I79: 661541300 | J79: SPECTRACOL QUINOLINE YELLOW LK | K79: 10 | L79: KG | M79: 10 | N79: 1532649.1 | O79: 15326491 | P79: 15326491 | Q79: 0 | R79: 0 | S79: IDR | T79: 7954843 | U79: 7954843 | V79: 7371647.7 | W79: 0.48097427 | X79: 7371647.7 | Y79: DEL | Z79: Delivered | AA79: 15159 | AB79: PT. TIGAKA DISTRINDO PERKASA CIKARANG | AC79: Handy Inarto | AD79: 104 | AE79: 0 | AF79: 963 | AG79: TCSK | AH79: TRA COL SYN LAKE | AJ79: . | AK79: T | AL79: Non-Affiliate | AM79: Distributor | AN79: =VLOOKUP(I79,Sheet1!A:D,4,) -> A320400 | AP79: Invoice dikasih pas Mau Makan Siang, Invoice tgl 17,12,19,.MB terima Di tanggal 25/2/25. jam 12:25
A80: 45689 | B80: Invoiced | C80: SO | D80: 25708018 | E80: 24106481 | F80: 241100295 | G80: 45707 | H80: PT. TIGAKA DISTRINDO PERKASA PHARMA | I80: 509231020 | J80: BLACK IRON OXIDE | K80: 100 | L80: KG | M80: 100 | N80: 2064172.8 | O80: 206417278 | P80: 206417278 | Q80: 0 | R80: 0 | S80: IDR | T80: 1.3441051e+08 | U80: 1.3441051e+08 | V80: 72006769 | W80: 0.3488408 | X80: 72006769 | Z80: . | AA80: 2306153 | AB80: PT. TIGAKA DISTRINDO PERKASA PHARMA | AC80: AGNESYA ADIFILIA | AD80: 94 | AE80: 0 | AF80: 966 | AH80: . | AJ80: . | AK80: T | AL80: Non-Affiliate | AM80: Distributor | AN80: =VLOOKUP(I80,Sheet1!A:D,4,) -> A320400 | AP80: Invoice dikasih pas Mau Makan Siang, Invoice tgl 17,12,19,.MB terima Di tanggal 25/2/25. jam 12:25
A81: 45689 | B81: Invoiced | C81: SO | D81: 25708019 | E81: 24106341 | F81: POPD/GMC/24080292 | G81: 45707 | H81: PT. GRAND MULTI CHEMICALS JAKARTA | I81: 1103880820 | J81: FSS-060301-SN | K81: 2340 | L81: KG | M81: 2340 | N81: 178014.15 | O81: 416553111 | P81: 416553111 | Q81: 0 | R81: 0 | S81: IDR | T81: 3.0253467e+08 | U81: 3.0253467e+08 | V81: 1.1401844e+08 | W81: 0.27371886 | X81: 1.1401844e+08 | Y81: DEL | Z81: Delivered | AA81: 15161 | AB81: PT. GRAND MULTI CHEMICALS TANGERANG | AC81: AGNESYA ADIFILIA | AD81: 94 | AE81: 0 | AF81: 201 | AG81: TSYE | AH81: TRA SAV YEAST EXTRACT | AJ81: . | AK81: T | AL81: Non-Affiliate | AM81: Distributor | AN81: =VLOOKUP(I81,Sheet1!A:D,4,) -> A210600 | AP81: Invoice dikasih pas Mau Makan Siang, Invoice tgl 17,12,19,.MB terima Di tanggal 25/2/25. jam 12:25
A82: 45689 | B82: Invoiced | C82: SO | D82: 25708020 | E82: 25106608 | F82: 251200029 | G82: 45707 | H82: PT. TIGAKA DISTRINDO PERKASA JAKARTA -AA | I82: 086211020 | J82: SUNSET YELLOW CS 20KG | K82: 120 | L82: KG | M82: 120 | N82: 326975.4 | O82: 39237048 | P82: 39237048 | Q82: 0 | R82: 0 | S82: IDR | T82: 17323298 | U82: 17323298 | V82: 21913750 | W82: 0.55849639 | X82: 21913750 | Z82: . | AA82: 2306495 | AB82: PT. TIGAKA DISTRINDO PERKASA CIKARANG-AA | AC82: AGNESYA ADIFILIA | AD82: 94 | AE82: 0 | AF82: 961 | AG82: TCSP | AH82: TRA COL SYN DYE POWDER | AJ82: . | AK82: T | AL82: Non-Affiliate | AM82: Distributor | AN82: =VLOOKUP(I82,Sheet1!A:D,4,) -> A320400 | AP82: Invoice dikasih pas Mau Makan Siang, Invoice tgl 17,12,19,.MB terima Di tanggal 25/2/25. jam 12:25
A83: 45689 | B83: Invoiced | C83: SO | D83: 25708021 | E83: 25106548 | F83: 251100002 | G83: 45707 | H83: PT. TIGAKA DISTRINDO PERKASA PHARMA | I83: 501841010 | J83: YELLOW IRON OXIDE 10KG | K83: 40 | L83: KG | M83: 40 | N83: 2091587.3 | O83: 83663492 | P83: 83663492 | Q83: 0 | R83: 0 | S83: IDR | T83: 54776218 | U83: 54776218 | V83: 28887274 | W83: 0.34527932 | X83: 28887274 | Z83: . | AA83: 2306153 | AB83: PT. TIGAKA DISTRINDO PERKASA PHARMA | AC83: AGNESYA ADIFILIA | AD83: 94 | AE83: 0 | AF83: 968 | AH83: . | AJ83: . | AK83: T | AL83: Non-Affiliate | AM83: Distributor | AN83: =VLOOKUP(I83,Sheet1!A:D,4,) -> A320400 | AP83: Invoice dikasih sore tanggal 26/2/25. Invoice tanggal 19,24/2/25. MB terima di tanggal 26/2/25 jam 15:45
A84: 45689 | B84: Invoiced | C84: SO | D84: 25708028 | E84: 25106564 | F84: 251200007 | G84: 45712 | H84: PT. TIGAKA DISTRINDO PERKASA JAKARTA | I84: 503269-0013 | J84: RASPBERRY RED L-WS 13KG | K84: 130 | L84: KG | M84: 130 | N84: 495751.58 | O84: 64447705 | P84: 64447705 | Q84: 0 | R84: 0 | S84: IDR | T84: 19675450 | U84: 19675450 | V84: 44772256 | W84: 0.69470674 | X84: 44772256 | Y84: DEL | Z84: Delivered | AA84: 15159 | AB84: PT. TIGAKA DISTRINDO PERKASA CIKARANG | AC84: Handy Inarto | AD84: 104 | AE84: 0 | AF84: 960 | AH84: . | AJ84: . | AK84: T | AL84: Non-Affiliate | AM84: Distributor | AN84: =VLOOKUP(I84,Sheet1!A:D,4,) -> A320400 | AP84: Invoice dikasih sore tanggal 26/2/25. Invoice tanggal 19,24/2/25. MB terima di tanggal 26/2/25 jam 15:45
A85: 45689 | B85: Invoiced | C85: SO | D85: 25708028 | E85: 25106564 | F85: 251200007 | G85: 45712 | H85: PT. TIGAKA DISTRINDO PERKASA JAKARTA | I85: 409812-0010 | J85: TRUE PINEAPPLE YELLOW 13L-WS | K85: 70 | L85: KG | M85: 70 | N85: 1184286.5 | O85: 82900057 | P85: 82900057 | Q85: 0 | R85: 0 | S85: IDR | T85: 27623254 | U85: 27623254 | V85: 55276803 | W85: 0.66678848 | X85: 55276803 | Y85: DEL | Z85: Delivered | AA85: 15159 | AB85: PT. TIGAKA DISTRINDO PERKASA CIKARANG | AC85: Handy Inarto | AD85: 104 | AE85: 0 | AF85: 966 | AH85: . | AJ85: . | AK85: T | AL85: Non-Affiliate | AM85: Distributor | AN85: =VLOOKUP(I85,Sheet1!A:D,4,) -> A320400 | AP85: Invoice dikasih sore tanggal 26/2/25. Invoice tanggal 19,24/2/25. MB terima di tanggal 26/2/25 jam 15:45
A86: 45689 | B86: Invoiced | C86: SO | D86: 25708029 | E86: 25106568 | F86: 251200009 | G86: 45712 | H86: PT. TIGAKA DISTRINDO PERKASA JAKARTA | I86: 419104-0010 | J86: Bright Pink P-WS | K86: 20 | L86: KG | M86: 20 | N86: 825504.17 | O86: 16510083 | P86: 16510083 | Q86: 0 | R86: 0 | S86: IDR | T86: 10072540 | U86: 10072540 | V86: 6437543.4 | W86: 0.38991586 | X86: 6437543.4 | Y86: DEL | Z86: Delivered | AA86: 15159 | AB86: PT. TIGAKA DISTRINDO PERKASA CIKARANG | AC86: Handy Inarto | AD86: 104 | AE86: 0 | AF86: 960 | AH86: . | AJ86: . | AK86: T | AL86: Non-Affiliate | AM86: Distributor | AN86: =VLOOKUP(I86,Sheet1!A:D,4,) -> A320400 | AP86: Invoice dikasih sore tanggal 26/2/25. Invoice tanggal 19,24/2/25. MB terima di tanggal 26/2/25 jam 15:45
A87: 45689 | B87: Invoiced | C87: SO | D87: 25708029 | E87: 25106568 | F87: 251200009 | G87: 45712 | H87: PT. TIGAKA DISTRINDO PERKASA JAKARTA | I87: 503212-0010 | J87: Vitis Red 3P-WS | K87: 60 | L87: KG | M87: 60 | N87: 1048440 | O87: 62906401 | P87: 62906401 | Q87: 0 | R87: 0 | S87: IDR | T87: 40302715 | U87: 40302715 | V87: 22603686 | W87: 0.35932251 | X87: 22603686 | Y87: DEL | Z87: Delivered | AA87: 15159 | AB87: PT. TIGAKA DISTRINDO PERKASA CIKARANG | AC87: Handy Inarto | AD87: 104 | AE87: 0 | AF87: 960 | AH87: . | AJ87: . | AK87: T | AL87: Non-Affiliate | AM87: Distributor | AN87: =VLOOKUP(I87,Sheet1!A:D,4,) -> A320400 | AP87: Invoice dikasih sore tanggal 26/2/25. Invoice tanggal 19,24/2/25. MB terima di tanggal 26/2/25 jam 15:45
A88: 45689 | B88: Invoiced | C88: SO | D88: 25708029 | E88: 25106568 | F88: 251200009 | G88: 45712 | H88: PT. TIGAKA DISTRINDO PERKASA JAKARTA | I88: 409197.005 | J88: TRUE MANDARIN ORANGE 10 P-WD | K88: 20 | L88: KG | M88: 20 | N88: 1172899.2 | O88: 23457983 | P88: 23457983 | Q88: 0 | R88: 0 | S88: IDR | T88: 44028980 | U88: 44028980 | V88: -20570997 | W88: -0.87692947 | X88: -20570997 | Y88: DEL | Z88: Delivered | AA88: 15159 | AB88: PT. TIGAKA DISTRINDO PERKASA CIKARANG | AC88: Handy Inarto | AD88: 104 | AE88: 0 | AF88: 966 | AG88: TCNP | AH88: TRA COL NAT POWDER | AJ88: . | AK88: T | AL88: Non-Affiliate | AM88: Distributor | AN88: =VLOOKUP(I88,Sheet1!A:D,4,) -> A320400 | AP88: Invoice dikasih sore tanggal 26/2/25. Invoice tanggal 19,24/2/25. MB terima di tanggal 26/2/25 jam 15:45
A89: 45689 | B89: Invoiced | C89: SO | D89: 25708030 | E89: 25106597 | F89: 251200021 | G89: 45712 | H89: PT. TIGAKA DISTRINDO PERKASA JAKARTA | I89: 979007.001 | J89: MINT GREEN 97P-WS 1KG | K89: 18 | L89: KG | M89: 18 | N89: 10906376 | O89: 1.9631477e+08 | P89: 1.9631477e+08 | Q89: 0 | R89: 0 | S89: IDR | T89: 1.1662707e+08 | U89: 1.1662707e+08 | V89: 79687707 | W89: 0.40591803 | X89: 79687707 | Y89: DEL | Z89: Delivered | AA89: 15159 | AB89: PT. TIGAKA DISTRINDO PERKASA CIKARANG | AC89: Handy Inarto | AD89: 104 | AE89: 0 | AF89: 966 | AH89: . | AJ89: . | AK89: T | AL89: Non-Affiliate | AM89: Distributor | AN89: =VLOOKUP(I89,Sheet1!A:D,4,) -> A320400 | AP89: Invoice dikasih sore tanggal 26/2/25. Invoice tanggal 19,24/2/25. MB terima di tanggal 26/2/25 jam 15:45
A90: 45689 | B90: Invoiced | C90: SO | D90: 25708031 | E90: 25106619 | F90: 251200036 | G90: 45713 | H90: PT. TIGAKA DISTRINDO PERKASA JAKARTA | I90: 409050.005 | J90: PAPRIKA EXT 20000 CU L-WS 5KG | K90: 1 | L90: KG | M90: 1 | N90: 1518494 | O90: 1518494 | P90: 1518494 | Q90: 0 | R90: 0 | S90: IDR | T90: 342363.73 | U90: 342363.73 | V90: 1176130.3 | W90: 0.77453732 | X90: 1176130.3 | Y90: DEL | Z90: Delivered | AA90: 15159 | AB90: PT. TIGAKA DISTRINDO PERKASA CIKARANG | AC90: Handy Inarto | AD90: 104 | AE90: 0 | AF90: 966 | AG90: TCNL | AH90: TRA COL NAT LIQUID | AJ90: . | AK90: T | AL90: Non-Affiliate | AM90: Distributor | AN90: =VLOOKUP(I90,Sheet1!A:D,4,) -> A320400 | AP90: Invoice dikasih jam 12:38. Invoice tgl 24,25,26/2/25. MB terima di tanggal 27/2/25. Abis Maksi terima
A91: 45689 | B91: Invoiced | C91: SO | D91: 25708033 | E91: 24106338 | F91: 241100220 | G91: 45714 | H91: PT. TIGAKA DISTRINDO PERKASA PHARMA | I91: AA000545 | J91: EUROCERT COFFEE BROWN @ | K91: 120 | L91: KG | M91: 120 | N91: 808963.25 | O91: 97075590 | P91: 97075590 | Q91: 0 | R91: 0 | S91: IDR | T91: 58364550 | U91: 58364550 | V91: 38711040 | W91: 0.39877213 | X91: 38711040 | Z91: . | AA91: 2306153 | AB91: PT. TIGAKA DISTRINDO PERKASA PHARMA | AC91: AGNESYA ADIFILIA | AD91: 94 | AE91: 0 | AF91: 961 | AG91: MCSP | AH91: MAN COL SYN DYE POWDER | AI91: 9611 | AJ91: COLOUR DYE BLENDS | AK91: T | AL91: Non-Affiliate | AM91: Distributor | AN91: =VLOOKUP(I91,Sheet1!A:D,4,) -> A320400 | AP91: Invoice dikasih jam 12:38. Invoice tgl 24,25,26/2/25. MB terima di tanggal 27/2/25. Abis Maksi terima
A92: 45689 | B92: Invoiced | C92: SO | D92: 25708033 | E92: 24106338 | F92: 241100220 | G92: 45714 | H92: PT. TIGAKA DISTRINDO PERKASA PHARMA | I92: 952616 | J92: BROWN HT | K92: 100 | L92: KG | M92: 100 | N92: 1266281.1 | O92: 126628110 | P92: 126628110 | Q92: 0 | R92: 0 | S92: IDR | T92: 97914622 | U92: 97914622 | V92: 28713488 | W92: 0.22675445 | X92: 28713488 | Z92: . | AA92: 2306153 | AB92: PT. TIGAKA DISTRINDO PERKASA PHARMA | AC92: AGNESYA ADIFILIA | AD92: 94 | AE92: 0 | AF92: 961 | AG92: TCSP | AH92: TRA COL SYN DYE POWDER | AJ92: . | AK92: T | AL92: Non-Affiliate | AM92: Distributor | AN92: =VLOOKUP(I92,Sheet1!A:D,4,) -> A320400 | AP92: Invoice dikasih jam 12:38. Invoice tgl 24,25,26/2/25. MB terima di tanggal 27/2/25. Abis Maksi terima
A93: 45689 | B93: Invoiced | C93: SO | D93: 25708034 | E93: 25106546 | F93: 251200001 | G93: 45714 | H93: PT. TIGAKA DISTRINDO PERKASA JAKARTA | I93: 952777 | J93: YELLOW COLOR | K93: 60 | L93: KG | M93: 60 | N93: 1431976.8 | O93: 85918608 | P93: 85918608 | Q93: 0 | R93: 0 | S93: IDR | T93: 37962298 | U93: 37962298 | V93: 47956310 | W93: 0.55815977 | X93: 47956310 | Y93: DEL | Z93: Delivered | AA93: 15159 | AB93: PT. TIGAKA DISTRINDO PERKASA CIKARANG | AC93: Handy Inarto | AD93: 104 | AE93: 0 | AF93: 960 | AH93: . | AJ93: . | AK93: T | AL93: Non-Affiliate | AM93: Distributor | AN93: =VLOOKUP(I93,Sheet1!A:D,4,) -> A320400 | AP93: Invoice dikasih jam 12:38. Invoice tgl 24,25,26/2/25. MB terima di tanggal 27/2/25. Abis Maksi terima
A94: 45689 | B94: Invoiced | C94: SO | D94: 25708035 | E94: 25106568 | F94: 251200009 | G94: 45714 | H94: PT. TIGAKA DISTRINDO PERKASA JAKARTA | I94: 952777 | J94: YELLOW COLOR | K94: 10 | L94: KG | M94: 10 | N94: 1172899.2 | O94: 11728992 | P94: 11728992 | Q94: 0 | R94: 0 | S94: IDR | T94: 6327049.6 | U94: 6327049.6 | V94: 5401942 | W94: 0.46056321 | X94: 5401942 | Y94: DEL | Z94: Delivered | AA94: 15159 | AB94: PT. TIGAKA DISTRINDO PERKASA CIKARANG | AC94: Handy Inarto | AD94: 104 | AE94: 0 | AF94: 960 | AH94: . | AJ94: . | AK94: T | AL94: Non-Affiliate | AM94: Distributor | AN94: =VLOOKUP(I94,Sheet1!A:D,4,) -> A320400 | AP94: Invoice dikasih jam 12:38. Invoice tgl 24,25,26/2/25. MB terima di tanggal 27/2/25. Abis Maksi terima
A95: 45689 | B95: Invoiced | C95: SO | D95: 25708036 | E95: 25106568 | F95: 251200009 | G95: 45712 | H95: PT. TIGAKA DISTRINDO PERKASA JAKARTA | I95: 419104-0010 | J95: Bright Pink P-WS | K95: 20 | L95: KG | M95: 20 | N95: 825504.17 | O95: 16510083 | P95: 16510083 | Q95: 0 | R95: 0 | S95: IDR | T95: 10072540 | U95: 10072540 | V95: 6437543.4 | W95: 0.38991586 | X95: 6437543.4 | Y95: DEL | Z95: Delivered | AA95: 15159 | AB95: PT. TIGAKA DISTRINDO PERKASA CIKARANG | AC95: Handy Inarto | AD95: 104 | AE95: 0 | AF95: 960 | AH95: . | AJ95: . | AK95: T | AL95: Non-Affiliate | AM95: Distributor | AN95: =VLOOKUP(I95,Sheet1!A:D,4,) -> A320400 | AP95: Invoice dikasih jam 12:38. Invoice tgl 24,25,26/2/25. MB terima di tanggal 27/2/25. Abis Maksi terima
A96: 45689 | B96: Invoiced | C96: SO | D96: 25708036 | E96: 25106568 | F96: 251200009 | G96: 45712 | H96: PT. TIGAKA DISTRINDO PERKASA JAKARTA | I96: 503212-0010 | J96: Vitis Red 3P-WS | K96: 60 | L96: KG | M96: 60 | N96: 1048440 | O96: 62906401 | P96: 62906401 | Q96: 0 | R96: 0 | S96: IDR | T96: 40302715 | U96: 40302715 | V96: 22603686 | W96: 0.35932251 | X96: 22603686 | Y96: DEL | Z96: Delivered | AA96: 15159 | AB96: PT. TIGAKA DISTRINDO PERKASA CIKARANG | AC96: Handy Inarto | AD96: 104 | AE96: 0 | AF96: 960 | AH96: . | AJ96: . | AK96: T | AL96: Non-Affiliate | AM96: Distributor | AN96: =VLOOKUP(I96,Sheet1!A:D,4,) -> A320400 | AP96: Invoice dikasih sore jam balik kerja jam 17:46. Invoice tgl 24/2/25.MB terima di tanggal 28/2/25.
A97: 45689 | B97: Invoiced | C97: SO | D97: 25708036 | E97: 25106568 | F97: 251200009 | G97: 45712 | H97: PT. TIGAKA DISTRINDO PERKASA JAKARTA | I97: 409197.005 | J97: TRUE MANDARIN ORANGE 10 P-WD | K97: 20 | L97: KG | M97: 20 | N97: 5740197 | O97: 114803941 | P97: 114803941 | Q97: 0 | R97: 0 | S97: IDR | T97: 44028980 | U97: 44028980 | V97: 70774961 | W97: 0.61648547 | X97: 70774961 | Y97: DEL | Z97: Delivered | AA97: 15159 | AB97: PT. TIGAKA DISTRINDO PERKASA CIKARANG | AC97: Handy Inarto | AD97: 104 | AE97: 0 | AF97: 966 | AG97: TCNP | AH97: TRA COL NAT POWDER | AJ97: . | AK97: T | AL97: Non-Affiliate | AM97: Distributor | AN97: =VLOOKUP(I97,Sheet1!A:D,4,) -> A320400 | AP97: Invoice dikasih sore jam balik kerja jam 17:46. Invoice tgl 24/2/25.MB terima di tanggal 28/2/25.
AN98: =VLOOKUP(I98,Sheet1!A:D,4,) -> #N/A | AP98: Invoice dikasih sore jam balik kerja jam 17:46. Invoice tgl 24/2/25.MB terima di tanggal 28/2/25.
AN99: =VLOOKUP(I99,Sheet1!A:D,4,) -> #N/A
AN100: =VLOOKUP(I100,Sheet1!A:D,4,) -> #N/A
AN101: =VLOOKUP(I101,Sheet1!A:D,4,) -> #N/A
AN102: =VLOOKUP(I102,Sheet1!A:D,4,) -> #N/A
AN103: =VLOOKUP(I103,Sheet1!A:D,4,) -> #N/A
AN104: =VLOOKUP(I104,Sheet1!A:D,4,) -> #N/A
...

Sheet OGAWA
A5: PT. Sensient Technologies Indonesia
A6: Date - Period | B6: StatusType | C6: Order Type | D6: Invoice | E6: Customer Order | F6: Order | G6: Ship Date | H6: Customer Group | I6: Item Number | J6: Item Description | K6: Input Quantity | L6: Input UOM | M6: Total KG | N6: Unit Price | O6: Amount | P6: Amount - Sales and orders Only | Q6: Foreign per unit | R6: Foreign Amount | S6: Currency | T6: StandardCost | U6: StandardCost- Sales and orders Only | V6: Gross Margin | W6: Gross Margin % | X6: Margin - Sales and orders Only | Y6: IncoTerms | Z6: IncoTerms Description | AA6: Ship To | AB6: Ship To Name | AC6: Sales Region Desc | AD6: Sales Region | AE6: Delivery Days | AF6: GL Category | AG6: Cat6 | AH6: Cat 6 Desc | AI6: Cat7 | AJ6: Cat 7 Desc | AK6: SaleType | AL6: AffiliateType | AM6: CustomerType | AN6: HS-Code | AP6: Note Finance MB
A7: 45658 | B7: Invoiced | C7: SO | D7: 25707940 | E7: 24106480 | F7: 025710 | G7: 45660 | H7: PT. OGAWA INDONESIA | I7: 1206750 | J7: LIME EXTRACT SNO C2122 | K7: 1 | L7: KG | M7: 1 | N7: 64242861 | O7: 64242861 | P7: 64242861 | Q7: 0 | R7: 0 | S7: IDR | T7: 34741658 | U7: 34741658 | V7: 29501203 | W7: 0.45921371 | X7: 29501203 | Y7: DEL | Z7: Delivered | AA7: 15447 | AB7: PT. OGAWA INDONESIA | AC7: ELLY HENDRA | AD7: 35 | AE7: 0 | AF7: 208 | AH7: . | AJ7: . | AK7: T | AL7: Non-Affiliate | AM7: Domestic | AN7: =VLOOKUP(I7,Sheet1!A:D,4,FALSE) -> A210600 | AP7: Invoice dikasih jam 09:30. invoice tanggal 3/1/25. MB terima di tanggal 23/1/25.
A8: 45809 | B8: Invoiced | C8: SO | D8: 25708263 | E8: 25106679 | F8: 026949 | G8: 45812 | H8: PT. OGAWA INDONESIA | I8: 1206750 | J8: LIME EXTRACT SNO C2122 | K8: 0.4 | L8: KG | M8: 0.4 | N8: 91411199 | O8: 36564480 | P8: 36564480 | Q8: 0 | R8: 0 | S8: IDR | T8: 13932796 | U8: 13932796 | V8: 22631684 | W8: 0.61895271 | X8: 22631684 | Y8: DEL | Z8: Delivered | AA8: 15447 | AB8: PT. OGAWA INDONESIA | AC8: AGNESYA ADIFILIA | AD8: 94 | AE8: 0 | AF8: 208 | AH8: . | AJ8: . | AK8: T | AL8: Non-Affiliate | AM8: Domestic | AN8: =VLOOKUP(I8,Sheet1!A:D,4,FALSE) -> A210600 | AP8: Invoice dikasih jam 14:00. invoice tgl 3/6/25. Finance abis Clossing,mB terima di tgl 9/6/25.
A9: 45901 | B9: Invoiced | C9: SO | D9: 25708561 | E9: 25106874 | F9: 028122 | G9: 45923 | H9: PT. OGAWA INDONESIA | I9: 1008421740 | J9: TERPENELESS LEMON EXTRACT 0.9 | K9: 1.8 | L9: KG | M9: 1.8 | N9: 25408000 | O9: 45734400 | P9: 45734400 | Q9: 0 | R9: 0 | S9: IDR | T9: 22772653 | U9: 22772653 | V9: 22961747 | W9: 0.50206732 | X9: 22961747 | Y9: DEL | Z9: Delivered | AA9: 15447 | AB9: PT. OGAWA INDONESIA | AC9: AGNESYA ADIFILIA | AD9: 94 | AE9: 0 | AF9: P208 | AH9: . | AJ9: . | AK9: T | AL9: Non-Affiliate | AM9: Domestic | AN9: =VLOOKUP(I9,Sheet1!A:D,4,FALSE) -> A210600 | AP9: Invoice dikasih siang pas jam makan siang. Invoice tgl 20,23,24/09/2025. MB terima ditanggal 26/9/25.
AN10: =VLOOKUP(I10,Sheet1!A:D,4,FALSE) -> #N/A
AN11: =VLOOKUP(I11,Sheet1!A:D,4,FALSE) -> #N/A
AN12: =VLOOKUP(I12,Sheet1!A:D,4,FALSE) -> #N/A
AN13: =VLOOKUP(I13,Sheet1!A:D,4,FALSE) -> #N/A
AN14: =VLOOKUP(I14,Sheet1!A:D,4,FALSE) -> #N/A
AN15: =VLOOKUP(I15,Sheet1!A:D,4,FALSE) -> #N/A
AN16: =VLOOKUP(I16,Sheet1!A:D,4,FALSE) -> #N/A
AN17: =VLOOKUP(I17,Sheet1!A:D,4,FALSE) -> #N/A
AN18: =VLOOKUP(I18,Sheet1!A:D,4,FALSE) -> #N/A
AN19: =VLOOKUP(I19,Sheet1!A:D,4,FALSE) -> #N/A
AN20: =VLOOKUP(I20,Sheet1!A:D,4,FALSE) -> #N/A
AN21: =VLOOKUP(I21,Sheet1!A:D,4,FALSE) -> #N/A
... AN233: =VLOOKUP(I233,Sheet1!A:D,4,FALSE) -> #N/A

Sheet GMC
A5: PT. Sensient Technologies Indonesia
A6: Date - Period | B6: StatusType | C6: Order Type | D6: Invoice | E6: Customer Order | F6: Order | G6: Ship Date | H6: Customer Group | I6: Item Number | J6: Item Description | K6: Input Quantity | L6: Input UOM | M6: Total KG | N6: Unit Price | O6: Amount | P6: Amount - Sales and orders Only | Q6: Foreign per unit | R6: Foreign Amount | S6: Currency | T6: StandardCost | U6: StandardCost- Sales and orders Only | V6: Gross Margin | W6: Gross Margin % | X6: Margin - Sales and orders Only | Y6: IncoTerms | Z6: IncoTerms Description | AA6: Ship To | AB6: Ship To Name | AC6: Sales Region Desc | AD6: Sales Region | AE6: Delivery Days | AF6: GL Category | AG6: Cat6 | AH6: Cat 6 Desc | AI6: Cat7 | AJ6: Cat 7 Desc | AK6: SaleType | AL6: AffiliateType | AM6: CustomerType | AN6: HS-Code | AP6: Note Finance MB
A7: 45658 | B7: Invoiced | C7: SO | D7: 25707900 | E7: 24106537 | F7: POPD/GMC/24120465 | G7: 45659 | H7: PT. GRAND MULTI CHEMICALS JAKARTA | I7: IDF2004 | J7: DB XF1591 10KG | K7: 40 | L7: KG | M7: 40 | N7: 226225 | O7: 9049000 | P7: 9049000 | Q7: 0 | R7: 0 | S7: IDR | T7: 5684526.9 | U7: 5684526.9 | V7: 3364473.1 | W7: 0.37180607 | X7: 3364473.1 | Y7: DEL | Z7: Delivered | AA7: 15161 | AB7: PT. GRAND MULTI CHEMICALS TANGERANG | AC7: ELLY HENDRA | AD7: 35 | AE7: 0 | AF7: 202 | AH7: . | AJ7: . | AK7: M | AL7: Non-Affiliate | AM7: Distributor | AN7: =VLOOKUP(I7,Sheet1!A:D,4,FALSE) -> A210600 | AP7: Invoice di kasih Tanggal 15/01/25.baru bisa karena Tax Cortex n di seetting sama IT. Invoice tgl 2/1/25.MB terima di tanggal 15/01/25 jam 16:48
A8: 45658 | B8: Invoiced | C8: SO | D8: 25707901 | E8: 24106294 | F8: POPD/GMC/24070273 | G8: 45659 | H8: PT. GRAND MULTI CHEMICALS JAKARTA | I8: IDF2017 | J8: DB N2945 (FML10) 10KG | K8: 900 | L8: KG | M8: 900 | N8: 310898.82 | O8: 279808938 | P8: 279808938 | Q8: 0 | R8: 0 | S8: IDR | T8: 1.4457609e+08 | U8: 1.4457609e+08 | V8: 1.3523285e+08 | W8: 0.48330425 | X8: 1.3523285e+08 | Y8: DEL | Z8: Delivered | AA8: 15161 | AB8: PT. GRAND MULTI CHEMICALS TANGERANG | AC8: ELLY HENDRA | AD8: 35 | AE8: 0 | AF8: 202 | AH8: . | AJ8: . | AK8: M | AL8: Non-Affiliate | AM8: Distributor | AN8: =VLOOKUP(I8,Sheet1!A:D,4,FALSE) -> A210600 | AP8: Invoice di kasih Tanggal 15/01/25.baru bisa karena Tax Cortex n di seetting sama IT. Invoice tgl 2/1/25.MB terima di tanggal 15/01/25 jam 16:48
A9: 45658 | B9: Invoiced | C9: SO | D9: 25707902 | E9: 24106469 | F9: POPD/GMC/24110404 | G9: 45665 | H9: PT. GRAND MULTI CHEMICALS JAKARTA | I9: IDF2016 | J9: DB XF1745 10KG | K9: 760 | L9: KG | M9: 760 | N9: 309447 | O9: 235179720 | P9: 235179720 | Q9: 0 | R9: 0 | S9: IDR | T9: 1.1276695e+08 | U9: 1.1276695e+08 | V9: 1.2241277e+08 | W9: 0.52050733 | X9: 1.2241277e+08 | Y9: DEL | Z9: Delivered | AA9: 15161 | AB9: PT. GRAND MULTI CHEMICALS TANGERANG | AC9: ELLY HENDRA | AD9: 35 | AE9: 0 | AF9: 202 | AH9: . | AJ9: . | AK9: M | AL9: Non-Affiliate | AM9: Distributor | AN9: =VLOOKUP(I9,Sheet1!A:D,4,FALSE) -> A210600 | AP9: Invoice di kasih Tanggal 15/01/25.baru bisa karena Tax Cortex n di seetting sama IT. Invoice tgl 2/1/25.MB terima di tanggal 15/01/25 jam 16:48
A10: 45658 | B10: Invoiced | C10: SO | D10: 25707903 | E10: 24106487 | F10: POPD/GMC/24120418 | G10: 45665 | H10: PT. GRAND MULTI CHEMICALS JAKARTA | I10: IDF2005 | J10: DB XF1951 10KG | K10: 430 | L10: KG | M10: 430 | N10: 255491.39 | O10: 1.098613e+08 | P10: 1.098613e+08 | Q10: 0 | R10: 0 | S10: IDR | T10: 58649689 | U10: 58649689 | V10: 51211608 | W10: 0.46614786 | X10: 51211608 | Y10: DEL | Z10: Delivered | AA10: 15161 | AB10: PT. GRAND MULTI CHEMICALS TANGERANG | AC10: ELLY HENDRA | AD10: 35 | AE10: 0 | AF10: 202 | AH10: . | AJ10: . | AK10: M | AL10: Non-Affiliate | AM10: Distributor | AN10: =VLOOKUP(I10,Sheet1!A:D,4,FALSE) -> A210600 | AP10: Invoice di kasih Tanggal 15/01/25.baru bisa karena Tax Cortex n di seetting sama IT. Invoice tgl 2/1/25.MB terima di tanggal 15/01/25 jam 16:48
A11: 45658 | B11: Invoiced | C11: SO | D11: 25707904 | E11: 24106491 | F11: POPD/GMC/24120432 | G11: 45665 | H11: PT. GRAND MULTI CHEMICALS JAKARTA | I11: 9624950020 | J11: DAIRYBOOST BUTTER FLVR 20KG *A | K11: 20 | L11: KG | M11: 20 | N11: 913599.23 | O11: 18271985 | P11: 18271985 | Q11: 0 | R11: 0 | S11: IDR | T11: 11596533 | U11: 11596533 | V11: 6675451.8 | W11: 0.36533808 | X11: 6675451.8 | Y11: DEL | Z11: Delivered | AA11: 15161 | AB11: PT. GRAND MULTI CHEMICALS TANGERANG | AC11: ELLY HENDRA | AD11: 35 | AE11: 0 | AF11: 208 | AH11: . | AJ11: . | AK11: T | AL11: Non-Affiliate | AM11: Distributor | AN11: =VLOOKUP(I11,Sheet1!A:D,4,FALSE) -> A210600 | AP11: Invoice di kasih Tanggal 15/01/25.baru bisa karena Tax Cortex n di seetting sama IT. Invoice tgl 2/1/25.MB terima di tanggal 15/01/25 jam 16:48
A12: 45658 | B12: Invoiced | C12: SO | D12: 25707905 | E12: 24106490 | F12: POPD/GMC/24120431 | G12: 45665 | H12: PT. GRAND MULTI CHEMICALS JAKARTA-AA | I12: 9637050025 | J12: SWEETEASE 3G FLAV N11839 25KG | K12: 100 | L12: KG | M12: 100 | N12: 490110 | O12: 49011000 | P12: 49011000 | Q12: 0 | R12: 0 | S12: IDR | T12: 32069577 | U12: 32069577 | V12: 16941423 | W12: 0.34566572 | X12: 16941423 | Z12: . | AA12: 2306511 | AB12: PT. GRAND MULTI CHEMICALS TANGERANG-AA | AC12: AGNESYA ADIFILIA | AD12: 94 | AE12: 0 | AF12: 101 | AH12: . | AJ12: . | AK12: T | AL12: Non-Affiliate | AM12: Distributor | AN12: =VLOOKUP(I12,Sheet1!A:D,4,FALSE) -> A210600 | AP12: Invoice di kasih tanggal 17/1/25. invoice tanggal 8 & 14/01/25.MB terima di tanggal 17/1/25. Cortexnya masih belum bisa.
A13: 45658 | B13: Invoiced | C13: SO | D13: 25707906 | E13: 25106543 | F13: POPD/GMC/25010008 | G13: 45665 | H13: PT. GRAND MULTI CHEMICALS JAKARTA-AA | I13: 96393200.25 | J13: LVR024 | K13: 25 | L13: KG | M13: 25 | N13: 483097 | O13: 12077425 | P13: 12077425 | Q13: 0 | R13: 0 | S13: IDR | T13: 9715618.2 | U13: 9715618.2 | V13: 2361806.8 | W13: 0.1955555 | X13: 2361806.8 | Z13: . | AA13: 2306511 | AB13: PT. GRAND MULTI CHEMICALS TANGERANG-AA | AC13: AGNESYA ADIFILIA | AD13: 94 | AE13: 0 | AF13: 208 | AH13: . | AJ13: . | AK13: T | AL13: Non-Affiliate | AM13: Distributor | AN13: =VLOOKUP(I13,Sheet1!A:D,4,FALSE) -> A210600 | AP13: Invoice di kasih tanggal 17/1/25. invoice tanggal 8 & 14/01/25.MB terima di tanggal 17/1/25. Cortexnya masih belum bisa.
A14: 45658 | B14: Invoiced | C14: SO | D14: 25707907 | E14: 24106494 | F14: POPD/GMC/24120437 | G14: 45671 | H14: PT. GRAND MULTI CHEMICALS JAKARTA-AA | I14: IF2576 | J14: SPEARMINT FLAVOUR | K14: 50 | L14: KG | M14: 50 | N14: 842434.92 | O14: 42121746 | P14: 42121746 | Q14: 0 | R14: 0 | S14: IDR | T14: 24011384 | U14: 24011384 | V14: 18110362 | W14: 0.42995279 | X14: 18110362 | Z14: . | AA14: 2306511 | AB14: PT. GRAND MULTI CHEMICALS TANGERANG-AA | AC14: AGNESYA ADIFILIA | AD14: 94 | AE14: 0 | AF14: 208 | AH14: . | AJ14: . | AK14: T | AL14: Non-Affiliate | AM14: Distributor | AN14: =VLOOKUP(I14,Sheet1!A:D,4,FALSE) -> A210600 | AP14: Invoice di kasih tanggal 17/1/25. invoice tanggal 8 & 14/01/25.MB terima di tanggal 17/1/25. Cortexnya masih belum bisa.
A15: 45689 | B15: Invoiced | C15: SO | D15: 25707979 | E15: 25106570 | F15: POPD/GMC/25010028 | G15: 45691 | H15: PT. GRAND MULTI CHEMICALS JAKARTA | I15: IDF2003 | J15: DB XF1589 10KG | K15: 300 | L15: KG | M15: 300 | N15: 304251.29 | O15: 91275387 | P15: 91275387 | Q15: 0 | R15: 0 | S15: IDR | T15: 48849983 | U15: 48849983 | V15: 42425404 | W15: 0.46480662 | X15: 42425404 | Y15: DEL | Z15: Delivered | AA15: 15161 | AB15: PT. GRAND MULTI CHEMICALS TANGERANG | AC15: ELLY HENDRA | AD15: 35 | AE15: 0 | AF15: 202 | AH15: . | AJ15: . | AK15: M | AL15: Non-Affiliate | AM15: Distributor | AN15: =VLOOKUP(I15,Sheet1!A:D,4,FALSE) -> A210600 | AP15: Invoice dikasih sore jam 15:30.Invoice tanggal 03/02/2025,MB terima di tanggal 10/2/25.
A16: 45689 | B16: Invoiced | C16: SO | D16: 25707980 | E16: 24106464 | F16: POPD/GMC/24110399 | G16: 45691 | H16: PT. GRAND MULTI CHEMICALS JAKARTA | I16: IDF5028 | J16: HONEY FLAVOR | K16: 500 | L16: KG | M16: 500 | N16: 288744.48 | O16: 144372240 | P16: 144372240 | Q16: 0 | R16: 0 | S16: IDR | T16: 1.1579444e+08 | U16: 1.1579444e+08 | V16: 28577802 | W16: 0.19794527 | X16: 28577802 | Y16: DEL | Z16: Delivered | AA16: 15161 | AB16: PT. GRAND MULTI CHEMICALS TANGERANG | AC16: ELLY HENDRA | AD16: 35 | AE16: 0 | AF16: 102 | AH16: . | AJ16: . | AK16: M | AL16: Non-Affiliate | AM16: Distributor | AN16: =VLOOKUP(I16,Sheet1!A:D,4,FALSE) -> A210600 | AP16: Invoice dikasih sore jam 15:30.Invoice tanggal 03/02/2025,MB terima di tanggal 10/2/25.
A17: 45689 | B17: Invoiced | C17: SO | D17: 25707981 | E17: 24106487 | F17: POPD/GMC/24120418 | G17: 45691 | H17: PT. GRAND MULTI CHEMICALS JAKARTA | I17: IDF2005 | J17: DB XF1951 10KG | K17: 250 | L17: KG | M17: 250 | N17: 255491.39 | O17: 63872848 | P17: 63872848 | Q17: 0 | R17: 0 | S17: IDR | T17: 34098657 | U17: 34098657 | V17: 29774191 | W17: 0.46614786 | X17: 29774191 | Y17: DEL | Z17: Delivered | AA17: 15161 | AB17: PT. GRAND MULTI CHEMICALS TANGERANG | AC17: ELLY HENDRA | AD17: 35 | AE17: 0 | AF17: 202 | AH17: . | AJ17: . | AK17: M | AL17: Non-Affiliate | AM17: Distributor | AN17: =VLOOKUP(I17,Sheet1!A:D,4,FALSE) -> A210600 | AP17: Invoice dikasih sore jam 15:30.Invoice tanggal 03/02/2025,MB terima di tanggal 10/2/25.
A18: 45689 | B18: Invoiced | C18: SO | D18: 25707982 | E18: 24106537 | F18: POPD/GMC/24120465 | G18: 45691 | H18: PT. GRAND MULTI CHEMICALS JAKARTA | I18: IDF2004 | J18: DB XF1591 10KG | K18: 960 | L18: KG | M18: 960 | N18: 226225 | O18: 217176000 | P18: 217176000 | Q18: 0 | R18: 0 | S18: IDR | T18: 1.3642865e+08 | U18: 1.3642865e+08 | V18: 80747355 | W18: 0.37180607 | X18: 80747355 | Y18: DEL | Z18: Delivered | AA18: 15161 | AB18: PT. GRAND MULTI CHEMICALS TANGERANG | AC18: ELLY HENDRA | AD18: 35 | AE18: 0 | AF18: 202 | AH18: . | AJ18: . | AK18: M | AL18: Non-Affiliate | AM18: Distributor | AN18: =VLOOKUP(I18,Sheet1!A:D,4,FALSE) -> A210600 | AP18: Invoice dikasih sore jam 15:30.Invoice tanggal 03/02/2025,MB terima di tanggal 10/2/25.
A19: 45689 | B19: Invoiced | C19: SO | D19: 25707983 | E19: 25106572 | F19: POPD/GMC/25010030 | G19: 45691 | H19: PT. GRAND MULTI CHEMICALS JAKARTA | I19: IDF2016 | J19: DB XF1745 10KG | K19: 150 | L19: KG | M19: 150 | N19: 322054.08 | O19: 48308112 | P19: 48308112 | Q19: 0 | R19: 0 | S19: IDR | T19: 22501330 | U19: 22501330 | V19: 25806782 | W19: 0.53421218 | X19: 25806782 | Y19: DEL | Z19: Delivered | AA19: 15161 | AB19: PT. GRAND MULTI CHEMICALS TANGERANG | AC19: ELLY HENDRA | AD19: 35 | AE19: 0 | AF19: 202 | AH19: . | AJ19: . | AK19: M | AL19: Non-Affiliate | AM19: Distributor | AN19: =VLOOKUP(I19,Sheet1!A:D,4,FALSE) -> A210600 | AP19: Invoice dikasih sore jam 15:30.Invoice tanggal 03/02/2025,MB terima di tanggal 10/2/25.
A20: 45689 | B20: Invoiced | C20: SO | D20: 25707987 | E20: 25106569 | F20: POPD/GMC/25010027 | G20: 45691 | H20: PT. GRAND MULTI CHEMICALS JAKARTA-AA | I20: 9637050025 | J20: SWEETEASE 3G FLAV N11839 25KG | K20: 50 | L20: KG | M20: 50 | N20: 505920 | O20: 25296000 | P20: 25296000 | Q20: 0 | R20: 0 | S20: IDR | T20: 16028611 | U20: 16028611 | V20: 9267389.1 | W20: 0.36635789 | X20: 9267389.1 | Z20: . | AA20: 2306511 | AB20: PT. GRAND MULTI CHEMICALS TANGERANG-AA | AC20: AGNESYA ADIFILIA | AD20: 94 | AE20: 0 | AF20: 101 | AH20: . | AJ20: . | AK20: T | AL20: Non-Affiliate | AM20: Distributor | AN20: =VLOOKUP(I20,Sheet1!A:D,4,FALSE) -> A210600 | AP20: Invoice dikasih sore jam 15:30.Invoice tanggal 03/02/2025,MB terima di tanggal 10/2/25.
A21: 45689 | B21: Invoiced | C21: SO | D21: 25707990 | E21: 24106534 | F21: POPD/GMC/24120456 | G21: 45695 | H21: PT. GRAND MULTI CHEMICALS JAKARTA-HI | I21: IF4851 | J21: PEACH FLAVOUR OS | K21: 5 | L21: KG | M21: 5 | N21: 1344896 | O21: 6724480 | P21: 6724480 | Q21: 0 | R21: 0 | S21: IDR | T21: 397383.6 | U21: 397383.6 | V21: 6327096.4 | W21: 0.94090493 | X21: 6327096.4 | Z21: . | AA21: 2306510 | AB21: PT. GRAND MULTI CHEMICALS TANGERANG-HI | AC21: Handy Inarto | AD21: 104 | AE21: 0 | AF21: 208 | AH21: . | AJ21: . | AK21: T | AL21: Non-Affiliate | AM21: Distributor | AN21: =VLOOKUP(I21,Sheet1!A:D,4,FALSE) -> A210600 | AP21: Invoice di kasih Jam 15:00, invoice tanggal 6/2/25. MB terima di tanggal 11/2/25
A22: 45689 | B22: Invoiced | C22: SO | D22: 25708015 | E22: 25106545 | F22: POPD/GMC/25010010 | G22: 45705 | H22: PT. GRAND MULTI CHEMICALS JAKARTA-AA | I22: IF2001 | J22: CHEDDAR CHEESE FLAVOUR | K22: 100 | L22: KG | M22: 100 | N22: 384604.43 | O22: 38460443 | P22: 38460443 | Q22: 0 | R22: 0 | S22: IDR | T22: 31119506 | U22: 31119506 | V22: 7340937 | W22: 0.1908698 | X22: 7340937 | Z22: . | AA22: 2306511 | AB22: PT. GRAND MULTI CHEMICALS TANGERANG-AA | AC22: AGNESYA ADIFILIA | AD22: 94 | AE22: 0 | AF22: 208 | AH22: . | AJ22: . | AK22: T | AL22: Non-Affiliate | AM22: Distributor | AN22: =VLOOKUP(I22,Sheet1!A:D,4,FALSE) -> A210600 | AP22: Invoice dikasih pas Mau Makan Siang, Invoice tgl 17,12,19,.MB terima Di tanggal 25/2/25. jam 12:25
A23: 45689 | B23: Invoiced | C23: SO | D23: 25708022 | E23: 25106616 | F23: POPD/GMC/25020072 | G23: 45712 | H23: PT. GRAND MULTI CHEMICALS JAKARTA-HI | I23: 9645360025 | J23: SWEET FLAVOR MSW 001 | K23: 50 | L23: KG | M23: 50 | N23: 901217.31 | O23: 45060866 | P23: 45060866 | Q23: 0 | R23: 0 | S23: IDR | T23: 31084931 | U23: 31084931 | V23: 13975934 | W23: 0.31015681 | X23: 13975934 | Z23: . | AA23: 2306510 | AB23: PT. GRAND MULTI CHEMICALS TANGERANG-HI | AC23: Handy Inarto | AD23: 104 | AE23: 0 | AF23: 102 | AH23: . | AJ23: . | AK23: T | AL23: Non-Affiliate | AM23: Distributor | AN23: =VLOOKUP(I23,Sheet1!A:D,4,FALSE) -> A210600 | AP23: Invoice dikasih sore tanggal 26/2/25. Invoice tanggal 19,24/2/25. MB terima di tanggal 26/2/25 jam 15:45
A24: 45689 | B24: Invoiced | C24: SO | D24: 25708023 | E24: 25106578 | F24: POPD/GMC/25010036 | G24: 45712 | H24: PT. GRAND MULTI CHEMICALS JAKARTA | I24: 9642640025 | J24: LZ 0414 | K24: 25 | L24: KG | M24: 25 | N24: 518045.16 | O24: 12951129 | P24: 12951129 | Q24: 0 | R24: 0 | S24: IDR | T24: 11581712 | U24: 11581712 | V24: 1369417 | W24: 0.10573727 | X24: 1369417 | Y24: DEL | Z24: Delivered | AA24: 15161 | AB24: PT. GRAND MULTI CHEMICALS TANGERANG | AC24: AGNESYA ADIFILIA | AD24: 94 | AE24: 0 | AF24: 101 | AH24: . | AJ24: . | AK24: T | AL24: Non-Affiliate | AM24: Distributor | AN24: =VLOOKUP(I24,Sheet1!A:D,4,FALSE) -> A210600 | AP24: Invoice dikasih sore tanggal 26/2/25. Invoice tanggal 19,24/2/25. MB terima di tanggal 26/2/25 jam 15:45
A25: 45689 | B25: Invoiced | C25: SO | D25: 25708027 | E25: 25106590 | F25: POPD/GMC/25010045 | G25: 45712 | H25: PT. GRAND MULTI CHEMICALS JAKARTA-AA | I25: 9637050025 | J25: SWEETEASE 3G FLAV N11839 25KG | K25: 50 | L25: KG | M25: 50 | N25: 505920 | O25: 25296000 | P25: 25296000 | Q25: 0 | R25: 0 | S25: IDR | T25: 16028611 | U25: 16028611 | V25: 9267389.1 | W25: 0.36635789 | X25: 9267389.1 | Z25: . | AA25: 2306511 | AB25: PT. GRAND MULTI CHEMICALS TANGERANG-AA | AC25: AGNESYA ADIFILIA | AD25: 94 | AE25: 0 | AF25: 101 | AH25: . | AJ25: . | AK25: T | AL25: Non-Affiliate | AM25: Distributor | AN25: =VLOOKUP(I25,Sheet1!A:D,4,FALSE) -> A210600 | AP25: Invoice dikasih sore tanggal 26/2/25. Invoice tanggal 19,24/2/25. MB terima di tanggal 26/2/25 jam 15:45
A26: 45717 | B26: Invoiced | C26: SO | D26: 25708037 | E26: 24106294 | F26: POPD/GMC/24070273 | G26: 45719 | H26: PT. GRAND MULTI CHEMICALS JAKARTA | I26: IDF2017 | J26: DB N2945 (FML10) 10KG | K26: 1000 | L26: KG | M26: 1000 | N26: 310898.82 | O26: 310898820 | P26: 310898820 | Q26: 0 | R26: 0 | S26: IDR | T26: 1.595273e+08 | U26: 1.595273e+08 | V26: 1.5137152e+08 | W26: 0.48688355 | X26: 1.5137152e+08 | Y26: DEL | Z26: Delivered | AA26: 15161 | AB26: PT. GRAND MULTI CHEMICALS TANGERANG | AC26: AGNESYA ADIFILIA | AD26: 94 | AE26: 0 | AF26: 202 | AH26: . | AJ26: . | AK26: M | AL26: Non-Affiliate | AM26: Distributor | AN26: =VLOOKUP(I26,Sheet1!A:D,4,FALSE) -> A210600 | AP26: Invoice dikasih Pagi jam 09:38 tanggal 7/3/25. Invoice tgl 03/3/25.MB terima ditanggal 07/3/25,abis Clossing Finance
A27: 45717 | B27: Invoiced | C27: SO | D27: 25708039 | E27: 25106579 | F27: POPD/GMC/25010037 | G27: 45719 | H27: PT. GRAND MULTI CHEMICALS JAKARTA | I27: 951090B003 | J27: CINNABON CARAMEL TOPPING @ | K27: 247.5 | L27: KG | M27: 247.5 | N27: 318924.9 | O27: 78933913 | P27: 78933913 | Q27: 0 | R27: 0 | S27: IDR | T27: 45294230 | U27: 45294230 | V27: 33639683 | W27: 0.42617528 | X27: 33639683 | Y27: DEL | Z27: Delivered | AA27: 15161 | AB27: PT. GRAND MULTI CHEMICALS TANGERANG | AC27: AGNESYA ADIFILIA | AD27: 94 | AE27: 0 | AF27: 308 | AG27: MKBR | AH27: MAN KET BROWN BASED | AJ27: . | AK27: T | AL27: Non-Affiliate | AM27: Distributor | AN27: =VLOOKUP(I27,Sheet1!A:D,4,FALSE) -> A210600 | AP27: Invoice dikasih Pagi jam 09:38 tanggal 7/3/25. Invoice tgl 03/3/25.MB terima ditanggal 07/3/25,abis Clossing Finance
A28: 45717 | B28: Invoiced | C28: SO | D28: 25708083 | E28: 25106571 | F28: POPD/GMC/25010029 | G28: 45734 | H28: PT. GRAND MULTI CHEMICALS JAKARTA | I28: IDF2005 | J28: DB XF1951 10KG | K28: 860 | L28: KG | M28: 860 | N28: 264315.3 | O28: 227311158 | P28: 227311158 | Q28: 0 | R28: 0 | S28: IDR | T28: 1.1809503e+08 | U28: 1.1809503e+08 | V28: 1.0921613e+08 | W28: 0.48046974 | X28: 1.0921613e+08 | Y28: DEL | Z28: Delivered | AA28: 15161 | AB28: PT. GRAND MULTI CHEMICALS TANGERANG | AC28: AGNESYA ADIFILIA | AD28: 94 | AE28: 0 | AF28: 202 | AH28: . | AJ28: . | AK28: M | AL28: Non-Affiliate | AM28: Distributor | AN28: =VLOOKUP(I28,Sheet1!A:D,4,FALSE) -> A210600 | AP28: Invoice di kasih sore jam pulang kerja.Invoice tgl 15/3/25. MB terima ditanggal 21/3/25. pagi
A29: 45717 | B29: Invoiced | C29: SO | D29: 25708084 | E29: 25106635 | F29: POPD/GMC/25030088 | G29: 45734 | H29: PT. GRAND MULTI CHEMICALS JAKARTA-AA | I29: 9637050025 | J29: SWEETEASE 3G FLAV N11839 25KG | K29: 50 | L29: KG | M29: 50 | N29: 512244 | O29: 25612200 | P29: 25612200 | Q29: 0 | R29: 0 | S29: IDR | T29: 17666414 | U29: 17666414 | V29: 7945786.4 | W29: 0.31023443 | X29: 7945786.4 | Z29: . | AA29: 2306511 | AB29: PT. GRAND MULTI CHEMICALS TANGERANG-AA | AC29: AGNESYA ADIFILIA | AD29: 94 | AE29: 0 | AF29: 101 | AH29: . | AJ29: . | AK29: T | AL29: Non-Affiliate | AM29: Distributor | AN29: =VLOOKUP(I29,Sheet1!A:D,4,FALSE) -> A210600 | AP29: Invoice di kasih sore jam pulang kerja.Invoice tgl 15/3/25. MB terima ditanggal 21/3/25. pagi
A30: 45717 | B30: Invoiced | C30: SO | D30: 25708086 | E30: 25106572 | F30: POPD/GMC/25010030 | G30: 45736 | H30: PT. GRAND MULTI CHEMICALS JAKARTA | I30: IDF2016 | J30: DB XF1745 10KG | K30: 850 | L30: KG | M30: 850 | N30: 322054.08 | O30: 273745968 | P30: 273745968 | Q30: 0 | R30: 0 | S30: IDR | T30: 1.2734945e+08 | U30: 1.2734945e+08 | V30: 1.4639652e+08 | W30: 0.53478969 | X30: 1.4639652e+08 | Y30: DEL | Z30: Delivered | AA30: 15161 | AB30: PT. GRAND MULTI CHEMICALS TANGERANG | AC30: AGNESYA ADIFILIA | AD30: 94 | AE30: 0 | AF30: 202 | AH30: . | AJ30: . | AK30: M | AL30: Non-Affiliate | AM30: Distributor | AN30: =VLOOKUP(I30,Sheet1!A:D,4,FALSE) -> A210600 | AP30: Invoice dikasih sore jam balik kerja 21/3/25 jam 17:30. Invaoice tgl 20/3/25. MB terima di tanggal 24/3/25 pagi
A31: 45717 | B31: Invoiced | C31: SO | D31: 25708087 | E31: 25106636 | F31: POPD/GMC/25030089 | G31: 45736 | H31: PT. GRAND MULTI CHEMICALS JAKARTA-HI | I31: 9645360025 | J31: SWEET FLAVOR MSW 001 | K31: 50 | L31: KG | M31: 50 | N31: 901217.31 | O31: 45060866 | P31: 45060866 | Q31: 0 | R31: 0 | S31: IDR | T31: 31072585 | U31: 31072585 | V31: 13988280 | W31: 0.3104308 | X31: 13988280 | Z31: . | AA31: 2306510 | AB31: PT. GRAND MULTI CHEMICALS TANGERANG-HI | AC31: Handy Inarto | AD31: 104 | AE31: 0 | AF31: 102 | AH31: . | AJ31: . | AK31: T | AL31: Non-Affiliate | AM31: Distributor | AN31: =VLOOKUP(I31,Sheet1!A:D,4,FALSE) -> A210600 | AP31: Invoice dikasih sore jam balik kerja 21/3/25 jam 17:30. Invaoice tgl 20/3/25. MB terima di tanggal 24/3/25 pagi
A32: 45717 | B32: Invoiced | C32: SO | D32: 25708088 | E32: 25106649 | F32: POPD/GMC/25030107 | G32: 45736 | H32: PT. GRAND MULTI CHEMICALS JAKARTA-HI | I32: 9643730025 | J32: SMOOTH FLAVOR MST 002 | K32: 5 | L32: KG | M32: 5 | N32: 860483.4 | O32: 4302417 | P32: 4302417 | Q32: 0 | R32: 0 | S32: IDR | T32: 3131134.3 | U32: 3131134.3 | V32: 1171282.7 | W32: 0.2722383 | X32: 1171282.7 | Z32: . | AA32: 2306510 | AB32: PT. GRAND MULTI CHEMICALS TANGERANG-HI | AC32: Handy Inarto | AD32: 104 | AE32: 0 | AF32: 101 | AH32: . | AJ32: . | AK32: T | AL32: Non-Affiliate | AM32: Distributor | AN32: =VLOOKUP(I32,Sheet1!A:D,4,FALSE) -> A210600 | AP32: Invoice dikasih sore jam balik kerja 21/3/25 jam 17:30. Invaoice tgl 20/3/25. MB terima di tanggal 24/3/25 pagi
A33: 45717 | B33: Invoiced | C33: SO | D33: 25708089 | E33: 25106650 | F33: POPD/GMC/25030106 | G33: 45736 | H33: PT. GRAND MULTI CHEMICALS JAKARTA-HI | I33: 9645360025 | J33: SWEET FLAVOR MSW 001 | K33: 5 | L33: KG | M33: 5 | N33: 901217.31 | O33: 4506086.5 | P33: 4506086.5 | Q33: 0 | R33: 0 | S33: IDR | T33: 3107258.5 | U33: 3107258.5 | V33: 1398828.1 | W33: 0.3104308 | X33: 1398828.1 | Z33: . | AA33: 2306510 | AB33: PT. GRAND MULTI CHEMICALS TANGERANG-HI | AC33: Handy Inarto | AD33: 104 | AE33: 0 | AF33: 102 | AH33: . | AJ33: . | AK33: T | AL33: Non-Affiliate | AM33: Distributor | AN33: =VLOOKUP(I33,Sheet1!A:D,4,FALSE) -> A210600 | AP33: Invoice dikasih sore jam balik kerja 21/3/25 jam 17:30. Invaoice tgl 20/3/25. MB terima di tanggal 24/3/25 pagi
A34: 45717 | B34: Invoiced | C34: SO | D34: 25708090 | E34: 24106539 | F34: POPD/GMC/24120469 | G34: 45740 | H34: PT. GRAND MULTI CHEMICALS JAKARTA | I34: 1109656820 | J34: CHEESEMATE 3036 | K34: 1600 | L34: KG | M34: 1600 | N34: 193951.97 | O34: 310323152 | P34: 310323152 | Q34: 0 | R34: 0 | S34: IDR | T34: 2.0708358e+08 | U34: 2.0708358e+08 | V34: 1.0323957e+08 | W34: 0.33268408 | X34: 1.0323957e+08 | Y34: DEL | Z34: Delivered | AA34: 15161 | AB34: PT. GRAND MULTI CHEMICALS TANGERANG | AC34: AGNESYA ADIFILIA | AD34: 94 | AE34: 0 | AF34: 973 | AG34: TSYB | AH34: TRA SAV YEAST BLEND CONC. | AJ34: . | AK34: T | AL34: Non-Affiliate | AM34: Distributor | AN34: =VLOOKUP(I34,Sheet1!A:D,4,FALSE) -> A210600 | AP34: Invoice dikasih Sore jam 16:00, Invoice tgl 25,21/03/2025. MB terima di tanggal 25/3/25. pagi
A35: 45717 | B35: Invoiced | C35: SO | D35: 25708091 | E35: 24106541 | F35: POPD/GMC/24120470 | G35: 45740 | H35: PT. GRAND MULTI CHEMICALS JAKARTA | I35: 1103880820 | J35: FSS-060301-SN | K35: 7000 | L35: KG | M35: 7000 | N35: 173227.91 | O35: 1212595370 | P35: 1212595370 | Q35: 0 | R35: 0 | S35: IDR | T35: 9.6803727e+08 | U35: 9.6803727e+08 | V35: 2.445581e+08 | W35: 0.20168154 | X35: 2.445581e+08 | Y35: DEL | Z35: Delivered | AA35: 15161 | AB35: PT. GRAND MULTI CHEMICALS TANGERANG | AC35: AGNESYA ADIFILIA | AD35: 94 | AE35: 0 | AF35: 201 | AG35: TSYE | AH35: TRA SAV YEAST EXTRACT | AJ35: . | AK35: T | AL35: Non-Affiliate | AM35: Distributor | AN35: =VLOOKUP(I35,Sheet1!A:D,4,FALSE) -> A210600 | AP35: Invoice dikasih Sore jam 16:00, Invoice tgl 25,21/03/2025. MB terima di tanggal 25/3/25. pagi
A36: 45748 | B36: Invoiced | C36: SO | D36: 25708125 | E36: 24106488 | F36: POPD/GMC/24120419 | G36: 45762 | H36: PT. GRAND MULTI CHEMICALS JAKARTA | I36: C15P.029-0020 | J36: BEETROOT P | K36: 680 | L36: KG | M36: 680 | N36: 120073.04 | O36: 81649667 | P36: 81649667 | Q36: 0 | R36: 0 | S36: IDR | T36: 64729923 | U36: 64729923 | V36: 16919744 | W36: 0.20722367 | X36: 16919744 | Y36: DEL | Z36: Delivered | AA36: 15161 | AB36: PT. GRAND MULTI CHEMICALS TANGERANG | AC36: AGNESYA ADIFILIA | AD36: 94 | AE36: 0 | AF36: 960 | AH36: . | AJ36: . | AK36: T | AL36: Non-Affiliate | AM36: Distributor | AN36: =VLOOKUP(I36,Sheet1!A:D,4,FALSE) -> A320400 | AP36: Invoice di kasih jam 11:30 tanggal 17/4/25.Invoice tanggal 14,1516.MB terima ditanggal 17/4/25.
A37: 45748 | B37: Invoiced | C37: SO | D37: 25708133 | E37: 24106487 | F37: POPD/GMC/24120418 | G37: 45762 | H37: PT. GRAND MULTI CHEMICALS JAKARTA | I37: IDF2005 | J37: DB XF1951 10KG | K37: 250 | L37: KG | M37: 250 | N37: 255491.39 | O37: 63872848 | P37: 63872848 | Q37: 0 | R37: 0 | S37: IDR | T37: 33365855 | U37: 33365855 | V37: 30506992 | W37: 0.47762067 | X37: 30506992 | Y37: DEL | Z37: Delivered | AA37: 15161 | AB37: PT. GRAND MULTI CHEMICALS TANGERANG | AC37: AGNESYA ADIFILIA | AD37: 94 | AE37: 0 | AF37: 202 | AH37: . | AJ37: . | AK37: M | AL37: Non-Affiliate | AM37: Distributor | AN37: =VLOOKUP(I37,Sheet1!A:D,4,FALSE) -> A210600 | AP37: Invoice di kasih jam 11:30 tanggal 17/4/25.Invoice tanggal 14,1516.MB terima ditanggal 17/4/25.
A38: 45748 | B38: Invoiced | C38: SO | D38: 25708134 | E38: 25106571 | F38: POPD/GMC/25010029 | G38: 45762 | H38: PT. GRAND MULTI CHEMICALS JAKARTA | I38: IDF2005 | J38: DB XF1951 10KG | K38: 140 | L38: KG | M38: 140 | N38: 264315.3 | O38: 37004142 | P38: 37004142 | Q38: 0 | R38: 0 | S38: IDR | T38: 18684879 | U38: 18684879 | V38: 18319263 | W38: 0.4950598 | X38: 18319263 | Y38: DEL | Z38: Delivered | AA38: 15161 | AB38: PT. GRAND MULTI CHEMICALS TANGERANG | AC38: AGNESYA ADIFILIA | AD38: 94 | AE38: 0 | AF38: 202 | AH38: . | AJ38: . | AK38: M | AL38: Non-Affiliate | AM38: Distributor | AN38: =VLOOKUP(I38,Sheet1!A:D,4,FALSE) -> A210600 | AP38: Invoice di kasih jam 11:30 tanggal 17/4/25.Invoice tanggal 14,1516.MB terima ditanggal 17/4/25.
A39: 45748 | B39: Invoiced | C39: SO | D39: 25708138 | E39: 25106642 | F39: POPD/GMC/25030098 | G39: 45762 | H39: PT. GRAND MULTI CHEMICALS JAKARTA | I39: IDF2005 | J39: DB XF1951 10KG | K39: 110 | L39: KG | M39: 110 | N39: 269465.3 | O39: 29641183 | P39: 29641183 | Q39: 0 | R39: 0 | S39: IDR | T39: 14680976 | U39: 14680976 | V39: 14960207 | W39: 0.50471017 | X39: 14960207 | Y39: DEL | Z39: Delivered | AA39: 15161 | AB39: PT. GRAND MULTI CHEMICALS TANGERANG | AC39: AGNESYA ADIFILIA | AD39: 94 | AE39: 0 | AF39: 202 | AH39: . | AJ39: . | AK39: M | AL39: Non-Affiliate | AM39: Distributor | AN39: =VLOOKUP(I39,Sheet1!A:D,4,FALSE) -> A210600 | AP39: Invoice dikasih sore jam 16:30 Invoice tgl 15,16/04/25. MB terima tanggal 21/4/25 sore itu juga.
A40: 45748 | B40: Invoiced | C40: SO | D40: 25708139 | E40: 25106647 | F40: POPD/GMC/25030103 | G40: 45762 | H40: PT. GRAND MULTI CHEMICALS JAKARTA | I40: IDF2004 | J40: DB XF1591 10KG | K40: 500 | L40: KG | M40: 500 | N40: 238562 | O40: 119281000 | P40: 119281000 | Q40: 0 | R40: 0 | S40: IDR | T40: 70092306 | U40: 70092306 | V40: 49188694 | W40: 0.41237661 | X40: 49188694 | Y40: DEL | Z40: Delivered | AA40: 15161 | AB40: PT. GRAND MULTI CHEMICALS TANGERANG | AC40: AGNESYA ADIFILIA | AD40: 94 | AE40: 0 | AF40: 202 | AH40: . | AJ40: . | AK40: M | AL40: Non-Affiliate | AM40: Distributor | AN40: =VLOOKUP(I40,Sheet1!A:D,4,FALSE) -> A210600 | AP40: Invoice dikasih sore jam 16:30 Invoice tgl 15,16/04/25. MB terima tanggal 21/4/25 sore itu juga.
A41: 45748 | B41: Invoiced | C41: SO | D41: 25708154 | E41: 25106646 | F41: POPD/GMC/25030102 | G41: 45771 | H41: PT. GRAND MULTI CHEMICALS JAKARTA-AA | I41: IF2576 | J41: SPEARMINT FLAVOUR | K41: 100 | L41: KG | M41: 100 | N41: 717350 | O41: 71735000 | P41: 71735000 | Q41: 0 | R41: 0 | S41: IDR | T41: 49459183 | U41: 49459183 | V41: 22275817 | W41: 0.31052926 | X41: 22275817 | Z41: . | AA41: 2306511 | AB41: PT. GRAND MULTI CHEMICALS TANGERANG-AA | AC41: AGNESYA ADIFILIA | AD41: 94 | AE41: 0 | AF41: 208 | AH41: . | AJ41: . | AK41: T | AL41: Non-Affiliate | AM41: Distributor | AN41: =VLOOKUP(I41,Sheet1!A:D,4,FALSE) -> A210600 | AP41: Invoice Dikasih Sore jam pulang kerja jam 17:30. Invoice tanggal 24,28/4/25. MB terima ditanggal 30/4/25. Sore jam 18:45
A42: 45778 | B42: Invoiced | C42: SO | D42: 25708173 | E42: 25106630 | F42: POPD/GMC/25030085 | G42: 45779 | H42: PT. GRAND MULTI CHEMICALS JAKARTA | I42: 964129 | J42: DB BUTTER FLV N14142 *A | K42: 200 | L42: KG | M42: 200 | N42: 857939.59 | O42: 171587918 | P42: 171587918 | Q42: 0 | R42: 0 | S42: IDR | T42: 98721473 | U42: 98721473 | V42: 72866445 | W42: 0.42465953 | X42: 72866445 | Y42: DEL | Z42: Delivered | AA42: 15161 | AB42: PT. GRAND MULTI CHEMICALS TANGERANG | AC42: AGNESYA ADIFILIA | AD42: 94 | AE42: 0 | AF42: 203 | AH42: . | AJ42: . | AK42: T | AL42: Non-Affiliate | AM42: Distributor | AN42: =VLOOKUP(I42,Sheet1!A:D,4,FALSE) -> A210600 | AP42: Invoice di kasih sore jam pulang kerja tgl 8/5/25,invoice tgl 2/05/2025 Finance abis clossing.MB terima di tanggal 09/5/25.
A43: 45778 | B43: Invoiced | C43: SO | D43: 25708174 | E43: 25106680 | F43: POPD/GMC/25040135 | G43: 45779 | H43: PT. GRAND MULTI CHEMICALS JAKARTA-HI | I43: 9645360025 | J43: SWEET FLAVOR MSW 001 | K43: 125 | L43: KG | M43: 125 | N43: 901217.31 | O43: 1.1265216e+08 | P43: 1.1265216e+08 | Q43: 0 | R43: 0 | S43: IDR | T43: 46420941 | U43: 46420941 | V43: 66231223 | W43: 0.58792677 | X43: 66231223 | Z43: . | AA43: 2306510 | AB43: PT. GRAND MULTI CHEMICALS TANGERANG-HI | AC43: Handy Inarto | AD43: 104 | AE43: 0 | AF43: 102 | AH43: . | AJ43: . | AK43: T | AL43: Non-Affiliate | AM43: Distributor | AN43: =VLOOKUP(I43,Sheet1!A:D,4,FALSE) -> A210600 | AP43: Invoice di kasih sore jam pulang kerja tgl 8/5/25,invoice tgl 2/05/2025 Finance abis clossing.MB terima di tanggal 09/5/25.
A44: 45778 | B44: Invoiced | C44: SO | D44: 25708175 | E44: 25106682 | F44: POPD/GMC/25040137 | G44: 45779 | H44: PT. GRAND MULTI CHEMICALS JAKARTA-HI | I44: 9643730025 | J44: SMOOTH FLAVOR MST 002 | K44: 50 | L44: KG | M44: 50 | N44: 861206 | O44: 43060300 | P44: 43060300 | Q44: 0 | R44: 0 | S44: IDR | T44: 31395490 | U44: 31395490 | V44: 11664810 | W44: 0.27089476 | X44: 11664810 | Z44: . | AA44: 2306510 | AB44: PT. GRAND MULTI CHEMICALS TANGERANG-HI | AC44: Handy Inarto | AD44: 104 | AE44: 0 | AF44: 101 | AH44: . | AJ44: . | AK44: T | AL44: Non-Affiliate | AM44: Distributor | AN44: =VLOOKUP(I44,Sheet1!A:D,4,FALSE) -> A210600 | AP44: Invoice di kasih sore jam pulang kerja tgl 8/5/25,invoice tgl 2/05/2025 Finance abis clossing.MB terima di tanggal 09/5/25.
A45: 45778 | B45: Invoiced | C45: SO | D45: 25708176 | E45: 24106341 | F45: POPD/GMC/24080292 | G45: 45779 | H45: PT. GRAND MULTI CHEMICALS JAKARTA | I45: 1103880820 | J45: FSS-060301-SN | K45: 20 | L45: KG | M45: 20 | N45: 178014.15 | O45: 3560283 | P45: 3560283 | Q45: 0 | R45: 0 | S45: IDR | T45: 2935059.9 | U45: 2935059.9 | V45: 625223.11 | W45: 0.17561051 | X45: 625223.11 | Y45: DEL | Z45: Delivered | AA45: 15161 | AB45: PT. GRAND MULTI CHEMICALS TANGERANG | AC45: AGNESYA ADIFILIA | AD45: 94 | AE45: 0 | AF45: 201 | AG45: TSYE | AH45: TRA SAV YEAST EXTRACT | AJ45: . | AK45: T | AL45: Non-Affiliate | AM45: Distributor | AN45: =VLOOKUP(I45,Sheet1!A:D,4,FALSE) -> A210600 | AP45: Invoice di kasih sore jam pulang kerja tgl 8/5/25,invoice tgl 2/05/2025 Finance abis clossing.MB terima di tanggal 09/5/25.
A46: 45778 | B46: Invoiced | C46: SO | D46: 25708177 | E46: 25106573 | F46: POPD/GMC/25010031 | G46: 45779 | H46: PT. GRAND MULTI CHEMICALS JAKARTA | I46: 1103880820 | J46: FSS-060301-SN | K46: 4000 | L46: KG | M46: 4000 | N46: 175622.12 | O46: 702488480 | P46: 702488480 | Q46: 0 | R46: 0 | S46: IDR | T46: 587011978 | U46: 587011978 | V46: 115476502 | W46: 0.16438206 | X46: 115476502 | Y46: DEL | Z46: Delivered | AA46: 15161 | AB46: PT. GRAND MULTI CHEMICALS TANGERANG | AC46: AGNESYA ADIFILIA | AD46: 94 | AE46: 0 | AF46: 201 | AG46: TSYE | AH46: TRA SAV YEAST EXTRACT | AJ46: . | AK46: T | AL46: Non-Affiliate | AM46: Distributor | AN46: =VLOOKUP(I46,Sheet1!A:D,4,FALSE) -> A210600 | AP46: Invoice di kasih sore jam pulang kerja tgl 8/5/25,invoice tgl 2/05/2025 Finance abis clossing.MB terima di tanggal 09/5/25.
A47: 45778 | B47: Invoiced | C47: SO | D47: 25708178 | E47: 25106642 | F47: POPD/GMC/25030098 | G47: 45779 | H47: PT. GRAND MULTI CHEMICALS JAKARTA | I47: IDF2005 | J47: DB XF1951 10KG | K47: 620 | L47: KG | M47: 620 | N47: 269465.3 | O47: 167068486 | P47: 167068486 | Q47: 0 | R47: 0 | S47: IDR | T47: 82747321 | U47: 82747321 | V47: 84321165 | W47: 0.50471017 | X47: 84321165 | Y47: DEL | Z47: Delivered | AA47: 15161 | AB47: PT. GRAND MULTI CHEMICALS TANGERANG | AC47: AGNESYA ADIFILIA | AD47: 94 | AE47: 0 | AF47: 202 | AH47: . | AJ47: . | AK47: M | AL47: Non-Affiliate | AM47: Distributor | AN47: =VLOOKUP(I47,Sheet1!A:D,4,FALSE) -> A210600 | AP47: Invoice di kasih sore jam pulang kerja tgl 8/5/25,invoice tgl 2/05/2025 Finance abis clossing.MB terima di tanggal 09/5/25.
A48: 45778 | B48: Invoiced | C48: SO | D48: 25708179 | E48: 25106681 | F48: POPD/GMC/25040136 | G48: 45779 | H48: PT. GRAND MULTI CHEMICALS JAKARTA-AA | I48: 9637050025 | J48: SWEETEASE 3G FLAV N11839 25KG | K48: 50 | L48: KG | M48: 50 | N48: 518568 | O48: 25928400 | P48: 25928400 | Q48: 0 | R48: 0 | S48: IDR | T48: 17986464 | U48: 17986464 | V48: 7941936.3 | W48: 0.3063026 | X48: 7941936.3 | Z48: . | AA48: 2306511 | AB48: PT. GRAND MULTI CHEMICALS TANGERANG-AA | AC48: AGNESYA ADIFILIA | AD48: 94 | AE48: 0 | AF48: 101 | AH48: . | AJ48: . | AK48: T | AL48: Non-Affiliate | AM48: Distributor | AN48: =VLOOKUP(I48,Sheet1!A:D,4,FALSE) -> A210600 | AP48: Invoice di kasih sore jam pulang kerja tgl 8/5/25,invoice tgl 2/05/2025 Finance abis clossing.MB terima di tanggal 09/5/25.
A49: 45778 | B49: Invoiced | C49: SO | D49: 25708207 | E49: 25106640 | F49: POPD/GMC/25030095 | G49: 45791 | H49: PT. GRAND MULTI CHEMICALS JAKARTA-HI | I49: IF4851 | J49: PEACH FLAVOUR OS | K49: 25 | L49: KG | M49: 25 | N49: 1875118 | O49: 46877950 | P49: 46877950 | Q49: 0 | R49: 0 | S49: IDR | T49: 12826407 | U49: 12826407 | V49: 34051543 | W49: 0.7263872 | X49: 34051543 | Z49: . | AA49: 2306510 | AB49: PT. GRAND MULTI CHEMICALS TANGERANG-HI | AC49: Handy Inarto | AD49: 104 | AE49: 0 | AF49: 208 | AH49: . | AJ49: . | AK49: T | AL49: Non-Affiliate | AM49: Distributor | AN49: =VLOOKUP(I49,Sheet1!A:D,4,FALSE) -> A210600 | AP49: Invoice dikasih jam 17:26. Invoice tgl 14,15/5/25. MB terima di hari yang sama.
A50: 45778 | B50: Invoiced | C50: SO | D50: 25708222 | E50: 25106713 | F50: POPD/GMC/25050166 | G50: 45794 | H50: PT. GRAND MULTI CHEMICALS JAKARTA-HI | I50: 9645360025 | J50: SWEET FLAVOR MSW 001 | K50: 200 | L50: KG | M50: 200 | N50: 926548 | O50: 185309600 | P50: 185309600 | Q50: 0 | R50: 0 | S50: IDR | T50: 74273505 | U50: 74273505 | V50: 1.1103609e+08 | W50: 0.59919235 | X50: 1.1103609e+08 | Z50: . | AA50: 2306510 | AB50: PT. GRAND MULTI CHEMICALS TANGERANG-HI | AC50: Handy Inarto | AD50: 104 | AE50: 0 | AF50: 102 | AH50: . | AJ50: . | AK50: T | AL50: Non-Affiliate | AM50: Distributor | AN50: =VLOOKUP(I50,Sheet1!A:D,4,FALSE) -> A210600 | AP50: Invoice dikasih sore jam 17:30. invoice tgl 16,17/05/2025. MB terima pagi tgl 22/05/2025.
A51: 45778 | B51: Invoiced | C51: SO | D51: 25708223 | E51: 25106673 | F51: POPD/GMC/25040122 | G51: 45794 | H51: PT. GRAND MULTI CHEMICALS JAKARTA-HI | I51: 9645410020 | J51: MILK FLV DB N16484 *A* | K51: 300 | L51: KG | M51: 300 | N51: 680431.05 | O51: 204129315 | P51: 204129315 | Q51: 0 | R51: 0 | S51: IDR | T51: 152352057 | U51: 152352057 | V51: 51777258 | W51: 0.2536493 | X51: 51777258 | Z51: . | AA51: 2306510 | AB51: PT. GRAND MULTI CHEMICALS TANGERANG-HI | AC51: Handy Inarto | AD51: 104 | AE51: 0 | AF51: 399 | AH51: . | AJ51: . | AK51: T | AL51: Non-Affiliate | AM51: Distributor | AN51: =VLOOKUP(I51,Sheet1!A:D,4,FALSE) -> #N/A | AP51: Invoice dikasih sore jam 17:30. invoice tgl 16,17/05/2025. MB terima pagi tgl 22/05/2025.
A52: 45778 | B52: Invoiced | C52: SO | D52: 25708224 | E52: 25106680 | F52: POPD/GMC/25040135 | G52: 45794 | H52: PT. GRAND MULTI CHEMICALS JAKARTA-HI | I52: 9645360025 | J52: SWEET FLAVOR MSW 001 | K52: 100 | L52: KG | M52: 100 | N52: 901217.31 | O52: 90121731 | P52: 90121731 | Q52: 0 | R52: 0 | S52: IDR | T52: 37136753 | U52: 37136753 | V52: 52984978 | W52: 0.58792677 | X52: 52984978 | Z52: . | AA52: 2306510 | AB52: PT. GRAND MULTI CHEMICALS TANGERANG-HI | AC52: Handy Inarto | AD52: 104 | AE52: 0 | AF52: 102 | AH52: . | AJ52: . | AK52: T | AL52: Non-Affiliate | AM52: Distributor | AN52: =VLOOKUP(I52,Sheet1!A:D,4,FALSE) -> A210600 | AP52: Invoice dikasih sore jam 17:30. invoice tgl 16,17/05/2025. MB terima pagi tgl 22/05/2025.
A53: 45778 | B53: Invoiced | C53: SO | D53: 25708225 | E53: 25106682 | F53: POPD/GMC/25040137 | G53: 45794 | H53: PT. GRAND MULTI CHEMICALS JAKARTA-HI | I53: 9643730025 | J53: SMOOTH FLAVOR MST 002 | K53: 50 | L53: KG | M53: 50 | N53: 861206 | O53: 43060300 | P53: 43060300 | Q53: 0 | R53: 0 | S53: IDR | T53: 31395490 | U53: 31395490 | V53: 11664810 | W53: 0.27089476 | X53: 11664810 | Z53: . | AA53: 2306510 | AB53: PT. GRAND MULTI CHEMICALS TANGERANG-HI | AC53: Handy Inarto | AD53: 104 | AE53: 0 | AF53: 101 | AH53: . | AJ53: . | AK53: T | AL53: Non-Affiliate | AM53: Distributor | AN53: =VLOOKUP(I53,Sheet1!A:D,4,FALSE) -> A210600 | AP53: Invoice dikasih sore jam 17:30. invoice tgl 16,17/05/2025. MB terima pagi tgl 22/05/2025.
A54: 45809 | B54: Invoiced | C54: SO | D54: 25708283 | E54: 25106642 | F54: POPD/GMC/25030098 | G54: 45819 | H54: PT. GRAND MULTI CHEMICALS JAKARTA | I54: IDF2005 | J54: DB XF1951 10KG | K54: 270 | L54: KG | M54: 270 | N54: 269465.3 | O54: 72755631 | P54: 72755631 | Q54: 0 | R54: 0 | S54: IDR | T54: 36665683 | U54: 36665683 | V54: 36089948 | W54: 0.49604337 | X54: 36089948 | Y54: DEL | Z54: Delivered | AA54: 15161 | AB54: PT. GRAND MULTI CHEMICALS TANGERANG | AC54: AGNESYA ADIFILIA | AD54: 94 | AE54: 0 | AF54: 202 | AH54: . | AJ54: . | AK54: M | AL54: Non-Affiliate | AM54: Distributor | AN54: =VLOOKUP(I54,Sheet1!A:D,4,FALSE) -> A210600 | AP54: Invoice dikasih jam 17:50 Jam pulang kerja. Invoice tgl 11,12/06/2025.MB terima di tanggal 13/6/25 Sore itu juga.
A55: 45809 | B55: Invoiced | C55: SO | D55: 25708284 | E55: 25106718 | F55: POPD/GMC/25050171 | G55: 45819 | H55: PT. GRAND MULTI CHEMICALS JAKARTA-AA | I55: IF4149 | J55: CAPPUCCINO FLAVOUR | K55: 150 | L55: KG | M55: 150 | N55: 510327 | O55: 76549050 | P55: 76549050 | Q55: 0 | R55: 0 | S55: IDR | T55: 28967102 | U55: 28967102 | V55: 47581948 | W55: 0.6215877 | X55: 47581948 | Z55: . | AA55: 2306511 | AB55: PT. GRAND MULTI CHEMICALS TANGERANG-AA | AC55: AGNESYA ADIFILIA | AD55: 94 | AE55: 0 | AF55: 208 | AH55: . | AJ55: . | AK55: T | AL55: Non-Affiliate | AM55: Distributor | AN55: =VLOOKUP(I55,Sheet1!A:D,4,FALSE) -> A210600 | AP55: Invoice dikasih jam 17:50 Jam pulang kerja. Invoice tgl 11,12/06/2025.MB terima di tanggal 13/6/25 Sore itu juga.
A56: 45809 | B56: Invoiced | C56: SO | D56: 25708285 | E56: 25106647 | F56: POPD/GMC/25030103 | G56: 45819 | H56: PT. GRAND MULTI CHEMICALS JAKARTA | I56: IDF2004 | J56: DB XF1591 10KG | K56: 500 | L56: KG | M56: 500 | N56: 238562 | O56: 119281000 | P56: 119281000 | Q56: 0 | R56: 0 | S56: IDR | T56: 70201452 | U56: 70201452 | V56: 49079548 | W56: 0.41146157 | X56: 49079548 | Y56: DEL | Z56: Delivered | AA56: 15161 | AB56: PT. GRAND MULTI CHEMICALS TANGERANG | AC56: AGNESYA ADIFILIA | AD56: 94 | AE56: 0 | AF56: 202 | AH56: . | AJ56: . | AK56: M | AL56: Non-Affiliate | AM56: Distributor | AN56: =VLOOKUP(I56,Sheet1!A:D,4,FALSE) -> A210600 | AP56: Invoice dikasih jam 17:50 Jam pulang kerja. Invoice tgl 11,12/06/2025.MB terima di tanggal 13/6/25 Sore itu juga.
A57: 45809 | B57: Invoiced | C57: SO | D57: 25708286 | E57: 25106764 | F57: POPD/GMC/25050204 | G57: 45819 | H57: PT. GRAND MULTI CHEMICALS JAKARTA | I57: IDF2016 | J57: DB XF1745 10KG | K57: 500 | L57: KG | M57: 500 | N57: 337887.36 | O57: 168943680 | P57: 168943680 | Q57: 0 | R57: 0 | S57: IDR | T57: 74204253 | U57: 74204253 | V57: 94739427 | W57: 0.56077521 | X57: 94739427 | Y57: DEL | Z57: Delivered | AA57: 15161 | AB57: PT. GRAND MULTI CHEMICALS TANGERANG | AC57: AGNESYA ADIFILIA | AD57: 94 | AE57: 0 | AF57: 202 | AH57: . | AJ57: . | AK57: M | AL57: Non-Affiliate | AM57: Distributor | AN57: =VLOOKUP(I57,Sheet1!A:D,4,FALSE) -> A210600 | AP57: Invoice dikasih jam 17:50 Jam pulang kerja. Invoice tgl 11,12/06/2025.MB terima di tanggal 13/6/25 Sore itu juga.
A58: 45809 | B58: Invoiced | C58: SO | D58: 25708289 | E58: 25106719 | F58: POPD/GMC/25050172 | G58: 45820 | H58: PT. GRAND MULTI CHEMICALS JAKARTA-AA | I58: IF4149 | J58: CAPPUCCINO FLAVOUR | K58: 750 | L58: KG | M58: 750 | N58: 349980 | O58: 262485000 | P58: 262485000 | Q58: 0 | R58: 0 | S58: IDR | T58: 1.4483551e+08 | U58: 1.4483551e+08 | V58: 1.1764949e+08 | W58: 0.44821415 | X58: 1.1764949e+08 | Z58: . | AA58: 2306511 | AB58: PT. GRAND MULTI CHEMICALS TANGERANG-AA | AC58: AGNESYA ADIFILIA | AD58: 94 | AE58: 0 | AF58: 208 | AH58: . | AJ58: . | AK58: T | AL58: Non-Affiliate | AM58: Distributor | AN58: =VLOOKUP(I58,Sheet1!A:D,4,FALSE) -> A210600 | AP58: Invoice dikasih jam 15:00.Invoice tgl 12,13,16/06/25.MB terima di tanggal 18/6/25. jam 15:25
A59: 45809 | B59: Invoiced | C59: SO | D59: 25708295 | E59: 25106713 | F59: POPD/GMC/25050166 | G59: 45824 | H59: PT. GRAND MULTI CHEMICALS JAKARTA-HI | I59: 9645360025 | J59: SWEET FLAVOR MSW 001 | K59: 50 | L59: KG | M59: 50 | N59: 926548 | O59: 46327400 | P59: 46327400 | Q59: 0 | R59: 0 | S59: IDR | T59: 19106248 | U59: 19106248 | V59: 27221152 | W59: 0.58758211 | X59: 27221152 | Z59: . | AA59: 2306510 | AB59: PT. GRAND MULTI CHEMICALS TANGERANG-HI | AC59: Handy Inarto | AD59: 104 | AE59: 0 | AF59: 102 | AH59: . | AJ59: . | AK59: T | AL59: Non-Affiliate | AM59: Distributor | AN59: =VLOOKUP(I59,Sheet1!A:D,4,FALSE) -> A210600 | AP59: Invoice dikasih jam 15:00.Invoice tgl 12,13,16/06/25.MB terima di tanggal 18/6/25. jam 15:25
A60: 45809 | B60: Invoiced | C60: SO | D60: 25708296 | E60: 25106736 | F60: POPD/GMC/25050181 | G60: 45824 | H60: PT. GRAND MULTI CHEMICALS JAKARTA-AA | I60: 9637050025 | J60: SWEETEASE 3G FLAV N11839 25KG | K60: 50 | L60: KG | M60: 50 | N60: 518568 | O60: 25928400 | P60: 25928400 | Q60: 0 | R60: 0 | S60: IDR | T60: 17986464 | U60: 17986464 | V60: 7941936.3 | W60: 0.3063026 | X60: 7941936.3 | Z60: . | AA60: 2306511 | AB60: PT. GRAND MULTI CHEMICALS TANGERANG-AA | AC60: AGNESYA ADIFILIA | AD60: 94 | AE60: 0 | AF60: 101 | AH60: . | AJ60: . | AK60: T | AL60: Non-Affiliate | AM60: Distributor | AN60: =VLOOKUP(I60,Sheet1!A:D,4,FALSE) -> A210600 | AP60: Invoice dikasih jam 15:00.Invoice tgl 12,13,16/06/25.MB terima di tanggal 18/6/25. jam 15:25
A61: 45809 | B61: Invoiced | C61: SO | D61: 25708297 | E61: 25106788 | F61: POPD/GMC/25060216 | G61: 45824 | H61: PT. GRAND MULTI CHEMICALS JAKARTA | I61: IDF5028 | J61: HONEY FLAVOR | K61: 520 | L61: KG | M61: 520 | N61: 304561.5 | O61: 158371980 | P61: 158371980 | Q61: 0 | R61: 0 | S61: IDR | T61: 1.2042748e+08 | U61: 1.2042748e+08 | V61: 37944502 | W61: 0.23959101 | X61: 37944502 | Y61: DEL | Z61: Delivered | AA61: 15161 | AB61: PT. GRAND MULTI CHEMICALS TANGERANG | AC61: AGNESYA ADIFILIA | AD61: 94 | AE61: 0 | AF61: 102 | AH61: . | AJ61: . | AK61: M | AL61: Non-Affiliate | AM61: Distributor | AN61: =VLOOKUP(I61,Sheet1!A:D,4,FALSE) -> A210600 | AP61: Invoice dikasih jam 15:00.Invoice tgl 12,13,16/06/25.MB terima di tanggal 18/6/25. jam 15:25
A62: 45809 | B62: Invoiced | C62: SO | D62: 25708299 | E62: 25106750 | F62: POPD/GMC/25050185 | G62: 45824 | H62: PT. GRAND MULTI CHEMICALS JAKARTA | I62: AA000486.015 | J62: CONDENSED MILK FLAVOR | K62: 60 | L62: KG | M62: 60 | N62: 759652 | O62: 45579120 | P62: 45579120 | Q62: 0 | R62: 0 | S62: IDR | T62: 21599141 | U62: 21599141 | V62: 23979979 | W62: 0.52611763 | X62: 23979979 | Y62: DEL | Z62: Delivered | AA62: 15161 | AB62: PT. GRAND MULTI CHEMICALS TANGERANG | AC62: AGNESYA ADIFILIA | AD62: 94 | AE62: 0 | AF62: 208 | AH62: . | AJ62: . | AK62: T | AL62: Non-Affiliate | AM62: Distributor | AN62: =VLOOKUP(I62,Sheet1!A:D,4,FALSE) -> A210600 | AP62: Invoice dikasih jam 15:00.Invoice tgl 12,13,16/06/25.MB terima di tanggal 18/6/25. jam 15:25
A63: 45839 | B63: Invoiced | C63: SO | D63: 25708340 | E63: 25106764 | F63: POPD/GMC/25050204 | G63: 45840 | H63: PT. GRAND MULTI CHEMICALS JAKARTA | I63: IDF2016 | J63: DB XF1745 10KG | K63: 390 | L63: KG | M63: 390 | N63: 337887.36 | O63: 1.3177607e+08 | P63: 1.3177607e+08 | Q63: 0 | R63: 0 | S63: IDR | T63: 57880787 | U63: 57880787 | V63: 73895283 | W63: 0.56076405 | X63: 73895283 | Y63: DEL | Z63: Delivered | AA63: 15161 | AB63: PT. GRAND MULTI CHEMICALS TANGERANG | AC63: AGNESYA ADIFILIA | AD63: 94 | AE63: 0 | AF63: 202 | AH63: . | AJ63: . | AK63: M | AL63: Non-Affiliate | AM63: Distributor | AN63: =VLOOKUP(I63,Sheet1!A:D,4,FALSE) -> A210600 | AP63: Invoice di kasih abis makan siang jam 14:35. Invoice tgl 02,03/7/25. MB terima di tanggal 9/7/25.
A64: 45839 | B64: Invoiced | C64: SO | D64: 25708341 | E64: 25106772 | F64: POPD/GMC/25050206 | G64: 45840 | H64: PT. GRAND MULTI CHEMICALS JAKARTA-HI | I64: IF4851 | J64: PEACH FLAVOUR OS | K64: 50 | L64: KG | M64: 50 | N64: 1299697 | O64: 64984850 | P64: 64984850 | Q64: 0 | R64: 0 | S64: IDR | T64: 68471644 | U64: 68471644 | V64: -3486794 | W64: -0.05365549 | X64: -3486794 | Z64: . | AA64: 2306510 | AB64: PT. GRAND MULTI CHEMICALS TANGERANG-HI | AC64: Handy Inarto | AD64: 104 | AE64: 0 | AF64: 208 | AH64: . | AJ64: . | AK64: T | AL64: Non-Affiliate | AM64: Distributor | AN64: =VLOOKUP(I64,Sheet1!A:D,4,FALSE) -> A210600 | AP64: Invoice di kasih abis makan siang jam 14:35. Invoice tgl 02,03/7/25. MB terima di tanggal 9/7/25.
A65: 45839 | B65: Invoiced | C65: SO | D65: 25708342 | E65: 25106786 | F65: POPD/GMC/25060217 | G65: 45840 | H65: PT. GRAND MULTI CHEMICALS JAKARTA | I65: IDF2005 | J65: DB XF1951 10KG | K65: 500 | L65: KG | M65: 500 | N65: 270575.4 | O65: 135287700 | P65: 135287700 | Q65: 0 | R65: 0 | S65: IDR | T65: 67901422 | U65: 67901422 | V65: 67386278 | W65: 0.49809611 | X65: 67386278 | Y65: DEL | Z65: Delivered | AA65: 15161 | AB65: PT. GRAND MULTI CHEMICALS TANGERANG | AC65: AGNESYA ADIFILIA | AD65: 94 | AE65: 0 | AF65: 202 | AH65: . | AJ65: . | AK65: M | AL65: Non-Affiliate | AM65: Distributor | AN65: =VLOOKUP(I65,Sheet1!A:D,4,FALSE) -> A210600 | AP65: Invoice di kasih abis makan siang jam 14:35. Invoice tgl 02,03/7/25. MB terima di tanggal 9/7/25.
A66: 45839 | B66: Invoiced | C66: SO | D66: 25708343 | E66: 25106800 | F66: POPD/GMC/25060238 | G66: 45840 | H66: PT. GRAND MULTI CHEMICALS JAKARTA-AA | I66: 9637050025 | J66: SWEETEASE 3G FLAV N11839 25KG | K66: 50 | L66: KG | M66: 50 | N66: 515406 | O66: 25770300 | P66: 25770300 | Q66: 0 | R66: 0 | S66: IDR | T66: 18509395 | U66: 18509395 | V66: 7260905 | W66: 0.28175477 | X66: 7260905 | Z66: . | AA66: 2306511 | AB66: PT. GRAND MULTI CHEMICALS TANGERANG-AA | AC66: AGNESYA ADIFILIA | AD66: 94 | AE66: 0 | AF66: 101 | AH66: . | AJ66: . | AK66: T | AL66: Non-Affiliate | AM66: Distributor | AN66: =VLOOKUP(I66,Sheet1!A:D,4,FALSE) -> A210600 | AP66: Invoice di kasih abis makan siang jam 14:35. Invoice tgl 02,03/7/25. MB terima di tanggal 9/7/25.
A67: 45839 | B67: Invoiced | C67: SO | D67: 25708346 | E67: 25106789 | F67: POPD/GMC/25060219 | G67: 45846 | H67: PT. GRAND MULTI CHEMICALS JAKARTA | I67: 951090B003 | J67: CINNABON CARAMEL TOPPING @ | K67: 247.5 | L67: KG | M67: 247.5 | N67: 318924.9 | O67: 78933913 | P67: 78933913 | Q67: 0 | R67: 0 | S67: IDR | T67: 45585201 | U67: 45585201 | V67: 33348712 | W67: 0.42248902 | X67: 33348712 | Y67: DEL | Z67: Delivered | AA67: 15161 | AB67: PT. GRAND MULTI CHEMICALS TANGERANG | AC67: AGNESYA ADIFILIA | AD67: 94 | AE67: 0 | AF67: 308 | AG67: MKBR | AH67: MAN KET BROWN BASED | AJ67: . | AK67: T | AL67: Non-Affiliate | AM67: Distributor | AN67: =VLOOKUP(I67,Sheet1!A:D,4,FALSE) -> A210600 | AP67: Invoice di kasih abis makan siang jam 14:35. Invoice tgl 07/7/25. MB terima di tanggal 10/7/25.
A68: 45839 | B68: Invoiced | C68: SO | D68: 25708348 | E68: 25106794 | F68: POPD/GMC/25060227 | G68: 45845 | H68: PT. GRAND MULTI CHEMICALS JAKARTA-AA | I68: 96393200.25 | J68: LVR024 | K68: 50 | L68: KG | M68: 50 | N68: 582534 | O68: 29126700 | P68: 29126700 | Q68: 0 | R68: 0 | S68: IDR | T68: 19691859 | U68: 19691859 | V68: 9434840.7 | W68: 0.32392412 | X68: 9434840.7 | Z68: . | AA68: 2306511 | AB68: PT. GRAND MULTI CHEMICALS TANGERANG-AA | AC68: AGNESYA ADIFILIA | AD68: 94 | AE68: 0 | AF68: 208 | AH68: . | AJ68: . | AK68: T | AL68: Non-Affiliate | AM68: Distributor | AN68: =VLOOKUP(I68,Sheet1!A:D,4,FALSE) -> A210600 | AP68: Invoice di kasih abis makan siang jam 14:35. Invoice tgl 07/7/25. MB terima di tanggal 10/7/25.
A69: 45839 | B69: Invoiced | C69: SO | D69: 25708349 | E69: 25106797 | F69: POPD/GMC/25060231 | G69: 45845 | H69: PT. GRAND MULTI CHEMICALS JAKARTA-HI | I69: 9643730025 | J69: SMOOTH FLAVOR MST 002 | K69: 50 | L69: KG | M69: 50 | N69: 855426 | O69: 42771300 | P69: 42771300 | Q69: 0 | R69: 0 | S69: IDR | T69: 19683889 | U69: 19683889 | V69: 23087411 | W69: 0.53978745 | X69: 23087411 | Z69: . | AA69: 2306510 | AB69: PT. GRAND MULTI CHEMICALS TANGERANG-HI | AC69: Handy Inarto | AD69: 104 | AE69: 0 | AF69: 101 | AH69: . | AJ69: . | AK69: T | AL69: Non-Affiliate | AM69: Distributor | AN69: =VLOOKUP(I69,Sheet1!A:D,4,FALSE) -> A210600 | AP69: Invoice di kasih abis makan siang jam 14:35. Invoice tgl 07/7/25. MB terima di tanggal 10/7/25.
A70: 45839 | B70: Invoiced | C70: SO | D70: 25708350 | E70: 25106811 | F70: POPD/GMC/25060245 | G70: 45845 | H70: PT. GRAND MULTI CHEMICALS JAKARTA | I70: 967081 | J70: DAIRYBOOST PARMESAN CHEESE *A | K70: 20 | L70: KG | M70: 20 | N70: 1089525.7 | O70: 21790514 | P70: 21790514 | Q70: 0 | R70: 0 | S70: IDR | T70: 11094330 | U70: 11094330 | V70: 10696184 | W70: 0.49086425 | X70: 10696184 | Y70: DEL | Z70: Delivered | AA70: 15161 | AB70: PT. GRAND MULTI CHEMICALS TANGERANG | AC70: AGNESYA ADIFILIA | AD70: 94 | AE70: 0 | AF70: 399 | AH70: . | AJ70: . | AK70: T | AL70: Non-Affiliate | AM70: Distributor | AN70: =VLOOKUP(I70,Sheet1!A:D,4,FALSE) -> A210600 | AP70: Invoice di kasih abis makan siang jam 14:35. Invoice tgl 07/7/25. MB terima di tanggal 10/7/25.
A71: 45839 | B71: Invoiced | C71: SO | D71: 25708351 | E71: 25106832 | F71: POPD/GMC/25070255 | G71: 45845 | H71: PT. GRAND MULTI CHEMICALS JAKARTA-AA | I71: 9639790020 | J71: DB MILK FLV N13888 *A | K71: 40 | L71: KG | M71: 40 | N71: 502274 | O71: 20090960 | P71: 20090960 | Q71: 0 | R71: 0 | S71: IDR | T71: 15904728 | U71: 15904728 | V71: 4186231.6 | W71: 0.20836394 | X71: 4186231.6 | Z71: . | AA71: 2306511 | AB71: PT. GRAND MULTI CHEMICALS TANGERANG-AA | AC71: AGNESYA ADIFILIA | AD71: 94 | AE71: 0 | AF71: 208 | AH71: . | AJ71: . | AK71: T | AL71: Non-Affiliate | AM71: Distributor | AN71: =VLOOKUP(I71,Sheet1!A:D,4,FALSE) -> A210600 | AP71: Invoice di kasih abis makan siang jam 14:35. Invoice tgl 07/7/25. MB terima di tanggal 10/7/25.
A72: 45839 | B72: Invoiced | C72: SO | D72: 25708352 | E72: 25106787 | F72: POPD/GMC/25060218 | G72: 45840 | H72: PT. GRAND MULTI CHEMICALS JAKARTA | I72: IDF2017 | J72: DB N2945 (FML10) 10KG | K72: 160 | L72: KG | M72: 160 | N72: 315561.84 | O72: 50489894 | P72: 50489894 | Q72: 0 | R72: 0 | S72: IDR | T72: 25144939 | U72: 25144939 | V72: 25344955 | W72: 0.50198076 | X72: 25344955 | Y72: DEL | Z72: Delivered | AA72: 15161 | AB72: PT. GRAND MULTI CHEMICALS TANGERANG | AC72: AGNESYA ADIFILIA | AD72: 94 | AE72: 0 | AF72: 202 | AH72: . | AJ72: . | AK72: M | AL72: Non-Affiliate | AM72: Distributor | AN72: =VLOOKUP(I72,Sheet1!A:D,4,FALSE) -> A210600 | AP72: Invoice di kasih abis makan siang jam 14:35. Invoice tgl 02,07/7/25. MB terima di tanggal 11/7/25.
A73: 45839 | B73: Invoiced | C73: SO | D73: 25708353 | E73: 25106796 | F73: POPD/GMC/25060230 | G73: 45845 | H73: PT. GRAND MULTI CHEMICALS JAKARTA-HI | I73: 9645360025 | J73: SWEET FLAVOR MSW 001 | K73: 50 | L73: KG | M73: 50 | N73: 896903 | O73: 44845150 | P73: 44845150 | Q73: 0 | R73: 0 | S73: IDR | T73: 19106248 | U73: 19106248 | V73: 25738902 | W73: 0.57395062 | X73: 25738902 | Z73: . | AA73: 2306510 | AB73: PT. GRAND MULTI CHEMICALS TANGERANG-HI | AC73: Handy Inarto | AD73: 104 | AE73: 0 | AF73: 102 | AH73: . | AJ73: . | AK73: T | AL73: Non-Affiliate | AM73: Distributor | AN73: =VLOOKUP(I73,Sheet1!A:D,4,FALSE) -> A210600 | AP73: Invoice di kasih abis makan siang jam 14:35. Invoice tgl 02,07/7/25. MB terima di tanggal 11/7/25.
A74: 45839 | B74: Invoiced | C74: SO | D74: 25708354 | E74: 25106798 | F74: POPD/GMC/25060228 | G74: 45849 | H74: PT. GRAND MULTI CHEMICALS JAKARTA | I74: 1103880820 | J74: FSS-060301-SN | K74: 5000 | L74: KG | M74: 5000 | N74: 179781.59 | O74: 898907950 | P74: 898907950 | Q74: 0 | R74: 0 | S74: IDR | T74: 7.3376497e+08 | U74: 7.3376497e+08 | V74: 1.6514298e+08 | W74: 0.18371512 | X74: 1.6514298e+08 | Y74: DEL | Z74: Delivered | AA74: 15161 | AB74: PT. GRAND MULTI CHEMICALS TANGERANG | AC74: AGNESYA ADIFILIA | AD74: 94 | AE74: 0 | AF74: 201 | AG74: TSYE | AH74: TRA SAV YEAST EXTRACT | AJ74: . | AK74: T | AL74: Non-Affiliate | AM74: Distributor | AN74: =VLOOKUP(I74,Sheet1!A:D,4,FALSE) -> A210600 | AP74: Invoice di kasihsudah jam pulang 17:39. Invoice tgl 11/7/25. MB terima di tanggal 14/7/25.
A75: 45839 | B75: Invoiced | C75: SO | D75: 25708355 | E75: 25106799 | F75: POPD/GMC/25060229 | G75: 45849 | H75: PT. GRAND MULTI CHEMICALS JAKARTA | I75: 1103880820 | J75: FSS-060301-SN | K75: 5340 | L75: KG | M75: 5340 | N75: 179781.59 | O75: 9.6003369e+08 | P75: 9.6003369e+08 | Q75: 0 | R75: 0 | S75: IDR | T75: 7.8366099e+08 | U75: 7.8366099e+08 | V75: 1.763727e+08 | W75: 0.18371512 | X75: 1.763727e+08 | Y75: DEL | Z75: Delivered | AA75: 15161 | AB75: PT. GRAND MULTI CHEMICALS TANGERANG | AC75: AGNESYA ADIFILIA | AD75: 94 | AE75: 0 | AF75: 201 | AG75: TSYE | AH75: TRA SAV YEAST EXTRACT | AJ75: . | AK75: T | AL75: Non-Affiliate | AM75: Distributor | AN75: =VLOOKUP(I75,Sheet1!A:D,4,FALSE) -> A210600 | AP75: Invoice di kasihsudah jam pulang 17:39. Invoice tgl 11/7/25. MB terima di tanggal 14/7/25.
A76: 45839 | B76: Invoiced | C76: SO | D76: 25708359 | E76: 25106851 | F76: POPD/GMC/25050206 | G76: 45840 | H76: PT. GRAND MULTI CHEMICALS JAKARTA-HI | I76: IF4851 | J76: PEACH FLAVOUR OS | K76: 50 | L76: KG | M76: 50 | N76: 1299697 | O76: 64984850 | P76: 64984850 | Q76: 0 | R76: 0 | S76: IDR | T76: 51438765 | U76: 51438765 | V76: 13546085 | W76: 0.20844989 | X76: 13546085 | Z76: . | AA76: 2306510 | AB76: PT. GRAND MULTI CHEMICALS TANGERANG-HI | AC76: Handy Inarto | AD76: 104 | AE76: 0 | AF76: 208 | AH76: . | AJ76: . | AK76: T | AL76: Non-Affiliate | AM76: Distributor | AN76: =VLOOKUP(I76,Sheet1!A:D,4,FALSE) -> A210600 | AP76: Invoice dikasih sore jam pulang kerja.Invoice tgl 14&17/07/2025. MB terima di tanggal 18/7/25. abis magrib
A77: 45839 | B77: Invoiced | C77: SO | D77: 25708360 | E77: 25106760 | F77: POPD/GMC/25050193 | G77: 45855 | H77: PT. GRAND MULTI CHEMICALS JAKARTA-AA | I77: IF4149 | J77: CAPPUCCINO FLAVOUR | K77: 300 | L77: KG | M77: 300 | N77: 344224 | O77: 103267200 | P77: 103267200 | Q77: 0 | R77: 0 | S77: IDR | T77: 58639897 | U77: 58639897 | V77: 44627303 | W77: 0.43215371 | X77: 44627303 | Z77: . | AA77: 2306511 | AB77: PT. GRAND MULTI CHEMICALS TANGERANG-AA | AC77: AGNESYA ADIFILIA | AD77: 94 | AE77: 0 | AF77: 208 | AH77: . | AJ77: . | AK77: T | AL77: Non-Affiliate | AM77: Distributor | AN77: =VLOOKUP(I77,Sheet1!A:D,4,FALSE) -> A210600 | AP77: Invoice dikasih sore jam pulang kerja.Invoice tgl 14&17/07/2025. MB terima di tanggal 18/7/25. abis magrib
A78: 45839 | B78: Invoiced | C78: SO | D78: 25708372 | E78: 25106818 | F78: POPD/GMC/25060251 | G78: 45860 | H78: PT. GRAND MULTI CHEMICALS JAKARTA-AA | I78: 9637050025 | J78: SWEETEASE 3G FLAV N11839 25KG | K78: 50 | L78: KG | M78: 50 | N78: 515406 | O78: 25770300 | P78: 25770300 | Q78: 0 | R78: 0 | S78: IDR | T78: 18509395 | U78: 18509395 | V78: 7260905 | W78: 0.28175477 | X78: 7260905 | Z78: . | AA78: 2306511 | AB78: PT. GRAND MULTI CHEMICALS TANGERANG-AA | AC78: AGNESYA ADIFILIA | AD78: 94 | AE78: 0 | AF78: 101 | AH78: . | AJ78: . | AK78: T | AL78: Non-Affiliate | AM78: Distributor | AN78: =VLOOKUP(I78,Sheet1!A:D,4,FALSE) -> A210600 | AP78: Invoice dikasih pas mau makan siang. Invoice tgl 22/7/25 dan CN 1. MB terima di tgl 29/7/25. karena 25&28 MB cuti.
A79: 45839 | B79: Invoiced | C79: SO | D79: 25708373 | E79: 25106837 | F79: POPD/GMC/25070263 | G79: 45860 | H79: PT. GRAND MULTI CHEMICALS JAKARTA-AA | I79: 9637050025 | J79: SWEETEASE 3G FLAV N11839 25KG | K79: 50 | L79: KG | M79: 50 | N79: 512244 | O79: 25612200 | P79: 25612200 | Q79: 0 | R79: 0 | S79: IDR | T79: 18509395 | U79: 18509395 | V79: 7102805 | W79: 0.27732116 | X79: 7102805 | Z79: . | AA79: 2306511 | AB79: PT. GRAND MULTI CHEMICALS TANGERANG-AA | AC79: AGNESYA ADIFILIA | AD79: 94 | AE79: 0 | AF79: 101 | AH79: . | AJ79: . | AK79: T | AL79: Non-Affiliate | AM79: Distributor | AN79: =VLOOKUP(I79,Sheet1!A:D,4,FALSE) -> A210600 | AP79: Invoice dikasih pas mau makan siang. Invoice tgl 22/7/25 dan CN 1. MB terima di tgl 29/7/25. karena 25&28 MB cuti.
A80: 45839 | B80: Invoiced | C80: SO | D80: 25708388 | E80: 25106787 | F80: POPD/GMC/25060218 | G80: 45863 | H80: PT. GRAND MULTI CHEMICALS JAKARTA | I80: IDF2017 | J80: DB N2945 (FML10) 10KG | K80: 840 | L80: KG | M80: 840 | N80: 315561.84 | O80: 2.6507195e+08 | P80: 2.6507195e+08 | Q80: 0 | R80: 0 | S80: IDR | T80: 1.3201093e+08 | U80: 1.3201093e+08 | V80: 1.3306102e+08 | W80: 0.50198076 | X80: 1.3306102e+08 | Y80: DEL | Z80: Delivered | AA80: 15161 | AB80: PT. GRAND MULTI CHEMICALS TANGERANG | AC80: AGNESYA ADIFILIA | AD80: 94 | AE80: 0 | AF80: 202 | AH80: . | AJ80: . | AK80: M | AL80: Non-Affiliate | AM80: Distributor | AN80: =VLOOKUP(I80,Sheet1!A:D,4,FALSE) -> A210600 | AP80: Invoice dikasih pas mau makan siang. Invoice tgl 22/7/25 dan CN 1. MB terima di tgl 29/7/25. karena 25&28 MB cuti.
A81: 45839 | B81: Invoiced | C81: SO | D81: 25708389 | E81: 25106764 | F81: POPD/GMC/25050204 | G81: 45863 | H81: PT. GRAND MULTI CHEMICALS JAKARTA | I81: IDF2016 | J81: DB XF1745 10KG | K81: 110 | L81: KG | M81: 110 | N81: 337887.36 | O81: 37167610 | P81: 37167610 | Q81: 0 | R81: 0 | S81: IDR | T81: 16325350 | U81: 16325350 | V81: 20842259 | W81: 0.56076405 | X81: 20842259 | Y81: DEL | Z81: Delivered | AA81: 15161 | AB81: PT. GRAND MULTI CHEMICALS TANGERANG | AC81: AGNESYA ADIFILIA | AD81: 94 | AE81: 0 | AF81: 202 | AH81: . | AJ81: . | AK81: M | AL81: Non-Affiliate | AM81: Distributor | AN81: =VLOOKUP(I81,Sheet1!A:D,4,FALSE) -> A210600 | AP81: Invoice dikasih pas mau makan siang. Invoice tgl 22/7/25 dan CN 1. MB terima di tgl 29/7/25. karena 25&28 MB cuti.
A82: 45839 | B82: Invoiced | C82: SO | D82: 25708391 | E82: 25106787 | F82: POPD/GMC/25060218 | G82: 45868 | H82: PT. GRAND MULTI CHEMICALS JAKARTA | I82: IDF2017 | J82: DB N2945 (FML10) 10KG | K82: 300 | L82: KG | M82: 300 | N82: 315561.84 | O82: 94668552 | P82: 94668552 | Q82: 0 | R82: 0 | S82: IDR | T82: 47146761 | U82: 47146761 | V82: 47521791 | W82: 0.50198076 | X82: 47521791 | Y82: DEL | Z82: Delivered | AA82: 15161 | AB82: PT. GRAND MULTI CHEMICALS TANGERANG | AC82: AGNESYA ADIFILIA | AD82: 94 | AE82: 0 | AF82: 202 | AH82: . | AJ82: . | AK82: M | AL82: Non-Affiliate | AM82: Distributor | AN82: =VLOOKUP(I82,Sheet1!A:D,4,FALSE) -> A210600 | AP82: Invoice dikasih pas makan siang, Invoice tgl 23,30/07/2025. MB terima di tanggal 31/7/25. abis makan siang
A83: 45839 | B83: Invoiced | C83: SO | D83: 25708392 | E83: 25106788 | F83: POPD/GMC/25060216 | G83: 45868 | H83: PT. GRAND MULTI CHEMICALS JAKARTA | I83: IDF5028 | J83: HONEY FLAVOR | K83: 280 | L83: KG | M83: 280 | N83: 304561.5 | O83: 85277220 | P83: 85277220 | Q83: 0 | R83: 0 | S83: IDR | T83: 64845565 | U83: 64845565 | V83: 20431655 | W83: 0.23959101 | X83: 20431655 | Y83: DEL | Z83: Delivered | AA83: 15161 | AB83: PT. GRAND MULTI CHEMICALS TANGERANG | AC83: AGNESYA ADIFILIA | AD83: 94 | AE83: 0 | AF83: 102 | AH83: . | AJ83: . | AK83: M | AL83: Non-Affiliate | AM83: Distributor | AN83: =VLOOKUP(I83,Sheet1!A:D,4,FALSE) -> A210600 | AP83: Invoice dikasih pas makan siang, Invoice tgl 23,30/07/2025. MB terima di tanggal 31/7/25. abis makan siang
A84: 45870 | B84: Invoiced | C84: SO | D84: 25708423 | E84: 25106819 | F84: POPD/GMC/25060252 | G84: 45870 | H84: PT. GRAND MULTI CHEMICALS JAKARTA-AA | I84: AA000682015 | J84: YEAST BLEND 15KG | K84: 525 | L84: KG | M84: 525 | N84: 349547.95 | O84: 1.8351267e+08 | P84: 1.8351267e+08 | Q84: 0 | R84: 0 | S84: IDR | T84: 1.4590567e+08 | U84: 1.4590567e+08 | V84: 37606999 | W84: 0.20492862 | X84: 37606999 | Z84: . | AA84: 2306511 | AB84: PT. GRAND MULTI CHEMICALS TANGERANG-AA | AC84: AGNESYA ADIFILIA | AD84: 94 | AE84: 0 | AF84: 975 | AH84: . | AJ84: . | AK84: T | AL84: Non-Affiliate | AM84: Distributor | AN84: =VLOOKUP(I84,Sheet1!A:D,4,FALSE) -> A210600 | AP84: Invoice di kasih sore jam balik kantor. Invoice tgl 01,04,06/08/2025. Mb terima di tanggal 13/8/25.
A85: 45870 | B85: Invoiced | C85: SO | D85: 25708433 | E85: 25106786 | F85: POPD/GMC/25060217 | G85: 45883 | H85: PT. GRAND MULTI CHEMICALS JAKARTA | I85: IDF2005 | J85: DB XF1951 10KG | K85: 500 | L85: KG | M85: 500 | N85: 270575.4 | O85: 135287700 | P85: 135287700 | Q85: 0 | R85: 0 | S85: IDR | T85: 67892800 | U85: 67892800 | V85: 67394900 | W85: 0.49815984 | X85: 67394900 | Y85: DEL | Z85: Delivered | AA85: 15161 | AB85: PT. GRAND MULTI CHEMICALS TANGERANG | AC85: AGNESYA ADIFILIA | AD85: 94 | AE85: 0 | AF85: 202 | AH85: . | AJ85: . | AK85: M | AL85: Non-Affiliate | AM85: Distributor | AN85: =VLOOKUP(I85,Sheet1!A:D,4,FALSE) -> A210600 | AP85: Invoice di kasih jam pulang kerja tgl 15/8/25. Invoice tgl 13,14/08/2025. MB terima di tanggal 19/8/25.
A86: 45870 | B86: Invoiced | C86: SO | D86: 25708434 | E86: 25106787 | F86: POPD/GMC/25060218 | G86: 45883 | H86: PT. GRAND MULTI CHEMICALS JAKARTA | I86: IDF2017 | J86: DB N2945 (FML10) 10KG | K86: 700 | L86: KG | M86: 700 | N86: 315561.84 | O86: 220893288 | P86: 220893288 | Q86: 0 | R86: 0 | S86: IDR | T86: 1.0999704e+08 | U86: 1.0999704e+08 | V86: 1.1089625e+08 | W86: 0.5020354 | X86: 1.1089625e+08 | Y86: DEL | Z86: Delivered | AA86: 15161 | AB86: PT. GRAND MULTI CHEMICALS TANGERANG | AC86: AGNESYA ADIFILIA | AD86: 94 | AE86: 0 | AF86: 202 | AH86: . | AJ86: . | AK86: M | AL86: Non-Affiliate | AM86: Distributor | AN86: =VLOOKUP(I86,Sheet1!A:D,4,FALSE) -> A210600 | AP86: Invoice di kasih jam pulang kerja tgl 15/8/25. Invoice tgl 13,14/08/2025. MB terima di tanggal 19/8/25.
A87: 45870 | B87: Invoiced | C87: SO | D87: 25708435 | E87: 25106790 | F87: POPD/GMC/25060220 | G87: 45883 | H87: PT. GRAND MULTI CHEMICALS JAKARTA | I87: IDF2004 | J87: DB XF1591 10KG | K87: 500 | L87: KG | M87: 500 | N87: 239544.6 | O87: 119772300 | P87: 119772300 | Q87: 0 | R87: 0 | S87: IDR | T87: 70194714 | U87: 70194714 | V87: 49577586 | W87: 0.41393198 | X87: 49577586 | Y87: DEL | Z87: Delivered | AA87: 15161 | AB87: PT. GRAND MULTI CHEMICALS TANGERANG | AC87: AGNESYA ADIFILIA | AD87: 94 | AE87: 0 | AF87: 202 | AH87: . | AJ87: . | AK87: M | AL87: Non-Affiliate | AM87: Distributor | AN87: =VLOOKUP(I87,Sheet1!A:D,4,FALSE) -> A210600 | AP87: Invoice di kasih jam pulang kerja tgl 15/8/25. Invoice tgl 13,14/08/2025. MB terima di tanggal 19/8/25.
A88: 45870 | B88: Invoiced | C88: SO | D88: 25708436 | E88: 25106871 | F88: POPD/GMC/25080307 | G88: 45883 | H88: PT. GRAND MULTI CHEMICALS JAKARTA | I88: IDF2003 | J88: DB XF1589 10KG | K88: 150 | L88: KG | M88: 150 | N88: 308952 | O88: 46342800 | P88: 46342800 | Q88: 0 | R88: 0 | S88: IDR | T88: 24424928 | U88: 24424928 | V88: 21917872 | W88: 0.47295097 | X88: 21917872 | Y88: DEL | Z88: Delivered | AA88: 15161 | AB88: PT. GRAND MULTI CHEMICALS TANGERANG | AC88: AGNESYA ADIFILIA | AD88: 94 | AE88: 0 | AF88: 202 | AH88: . | AJ88: . | AK88: M | AL88: Non-Affiliate | AM88: Distributor | AN88: =VLOOKUP(I88,Sheet1!A:D,4,FALSE) -> A210600 | AP88: Invoice di kasih jam pulang kerja tgl 15/8/25. Invoice tgl 13,14/08/2025. MB terima di tanggal 19/8/25.
A89: 45870 | B89: Invoiced | C89: SO | D89: 25708437 | E89: 25106872 | F89: POPD/GMC/25080308 | G89: 45883 | H89: PT. GRAND MULTI CHEMICALS JAKARTA | I89: IDF2016 | J89: DB XF1745 10KG | K89: 500 | L89: KG | M89: 500 | N89: 327030 | O89: 163515000 | P89: 163515000 | Q89: 0 | R89: 0 | S89: IDR | T89: 74197515 | U89: 74197515 | V89: 89317485 | W89: 0.5462342 | X89: 89317485 | Y89: DEL | Z89: Delivered | AA89: 15161 | AB89: PT. GRAND MULTI CHEMICALS TANGERANG | AC89: AGNESYA ADIFILIA | AD89: 94 | AE89: 0 | AF89: 202 | AH89: . | AJ89: . | AK89: M | AL89: Non-Affiliate | AM89: Distributor | AN89: =VLOOKUP(I89,Sheet1!A:D,4,FALSE) -> A210600 | AP89: Invoice di kasih jam pulang kerja tgl 15/8/25. Invoice tgl 13,14/08/2025. MB terima di tanggal 19/8/25.
A90: 45870 | B90: Invoiced | C90: SO | D90: 25708456 | E90: 25106852 | F90: POPD/GMC/25070275 | G90: 45889 | H90: PT. GRAND MULTI CHEMICALS JAKARTA-AA | I90: 9637050025 | J90: SWEETEASE 3G FLAV N11839 25KG | K90: 50 | L90: KG | M90: 50 | N90: 512244 | O90: 25612200 | P90: 25612200 | Q90: 0 | R90: 0 | S90: IDR | T90: 18550959 | U90: 18550959 | V90: 7061241.2 | W90: 0.27569835 | X90: 7061241.2 | Z90: . | AA90: 2306511 | AB90: PT. GRAND MULTI CHEMICALS TANGERANG-AA | AC90: AGNESYA ADIFILIA | AD90: 94 | AE90: 0 | AF90: 101 | AH90: . | AJ90: . | AK90: T | AL90: Non-Affiliate | AM90: Distributor | AN90: =VLOOKUP(I90,Sheet1!A:D,4,FALSE) -> A210600 | AP90: Invoice di kasih pagi jam 10:00. Invoice tgl 20,22/08/2025. MB terima di tanggal 26/8/25 juga.
A91: 45870 | B91: Invoiced | C91: SO | D91: 25708457 | E91: 25106865 | F91: POPD/GMC/25070292 | G91: 45889 | H91: PT. GRAND MULTI CHEMICALS JAKARTA-AA | I91: 9637050025 | J91: SWEETEASE 3G FLAV N11839 25KG | K91: 100 | L91: KG | M91: 100 | N91: 512244 | O91: 51224400 | P91: 51224400 | Q91: 0 | R91: 0 | S91: IDR | T91: 37101918 | U91: 37101918 | V91: 14122482 | W91: 0.27569835 | X91: 14122482 | Z91: . | AA91: 2306511 | AB91: PT. GRAND MULTI CHEMICALS TANGERANG-AA | AC91: AGNESYA ADIFILIA | AD91: 94 | AE91: 0 | AF91: 101 | AH91: . | AJ91: . | AK91: T | AL91: Non-Affiliate | AM91: Distributor | AN91: =VLOOKUP(I91,Sheet1!A:D,4,FALSE) -> A210600 | AP91: Invoice di kasih pagi jam 10:00. Invoice tgl 20,22/08/2025. MB terima di tanggal 26/8/25 juga.
A92: 45870 | B92: Invoiced | C92: SO | D92: 25708458 | E92: 25106889 | F92: POPD/GMC/25080327 | G92: 45889 | H92: PT. GRAND MULTI CHEMICALS JAKARTA-AA | I92: 9637050025 | J92: SWEETEASE 3G FLAV N11839 25KG | K92: 50 | L92: KG | M92: 50 | N92: 510663 | O92: 25533150 | P92: 25533150 | Q92: 0 | R92: 0 | S92: IDR | T92: 18550959 | U92: 18550959 | V92: 6982191.2 | W92: 0.27345593 | X92: 6982191.2 | Z92: . | AA92: 2306511 | AB92: PT. GRAND MULTI CHEMICALS TANGERANG-AA | AC92: AGNESYA ADIFILIA | AD92: 94 | AE92: 0 | AF92: 101 | AH92: . | AJ92: . | AK92: T | AL92: Non-Affiliate | AM92: Distributor | AN92: =VLOOKUP(I92,Sheet1!A:D,4,FALSE) -> A210600 | AP92: Invoice di kasih pagi jam 10:00. Invoice tgl 20,22/08/2025. MB terima di tanggal 26/8/25 juga.
A93: 45870 | B93: Invoiced | C93: SO | D93: 25708459 | E93: 25106715 | F93: POPD/GMC/25050168 | G93: 45889 | H93: PT. GRAND MULTI CHEMICALS JAKARTA-AA | I93: 9631080010 | J93: CHOCOLATE FLAVOUR SD N7314 | K93: 360 | L93: KG | M93: 360 | N93: 586500 | O93: 211140000 | P93: 211140000 | Q93: 0 | R93: 0 | S93: IDR | T93: 1.382679e+08 | U93: 1.382679e+08 | V93: 72872104 | W93: 0.34513642 | X93: 72872104 | Z93: . | AA93: 2306511 | AB93: PT. GRAND MULTI CHEMICALS TANGERANG-AA | AC93: AGNESYA ADIFILIA | AD93: 94 | AE93: 0 | AF93: 208 | AH93: . | AJ93: . | AK93: T | AL93: Non-Affiliate | AM93: Distributor | AN93: =VLOOKUP(I93,Sheet1!A:D,4,FALSE) -> A210600 | AP93: Invoice di kasih pagi jam 10:00. Invoice tgl 20,22/08/2025. MB terima di tanggal 26/8/25 juga.
A94: 45870 | B94: Invoiced | C94: SO | D94: 25708460 | E94: 25106717 | F94: POPD/GMC/25050170 | G94: 45889 | H94: PT. GRAND MULTI CHEMICALS JAKARTA-AA | I94: 9630310005 | J94: COFFEE FLAVOUR N4592 5KG | K94: 350 | L94: KG | M94: 350 | N94: 575299 | O94: 201354650 | P94: 201354650 | Q94: 0 | R94: 0 | S94: IDR | T94: 1.2275972e+08 | U94: 1.2275972e+08 | V94: 78594928 | W94: 0.39033083 | X94: 78594928 | Z94: . | AA94: 2306511 | AB94: PT. GRAND MULTI CHEMICALS TANGERANG-AA | AC94: AGNESYA ADIFILIA | AD94: 94 | AE94: 0 | AF94: 208 | AH94: . | AJ94: . | AK94: T | AL94: Non-Affiliate | AM94: Distributor | AN94: =VLOOKUP(I94,Sheet1!A:D,4,FALSE) -> A210600 | AP94: Invoice di kasih pagi jam 10:00. Invoice tgl 20,22/08/2025. MB terima di tanggal 26/8/25 juga.
A95: 45870 | B95: Invoiced | C95: SO | D95: 25708461 | E95: 25106721 | F95: POPD/GMC/25050174 | G95: 45889 | H95: PT. GRAND MULTI CHEMICALS JAKARTA-AA | I95: 9638940010 | J95: COFFEE FLV SD N7526 | K95: 220 | L95: KG | M95: 220 | N95: 857107 | O95: 188563540 | P95: 188563540 | Q95: 0 | R95: 0 | S95: IDR | T95: 1.2824891e+08 | U95: 1.2824891e+08 | V95: 60314633 | W95: 0.31986371 | X95: 60314633 | Z95: . | AA95: 2306511 | AB95: PT. GRAND MULTI CHEMICALS TANGERANG-AA | AC95: AGNESYA ADIFILIA | AD95: 94 | AE95: 0 | AF95: 102 | AH95: . | AJ95: . | AK95: T | AL95: Non-Affiliate | AM95: Distributor | AN95: =VLOOKUP(I95,Sheet1!A:D,4,FALSE) -> A210600 | AP95: Invoice di kasih pagi jam 10:00. Invoice tgl 20,22/08/2025. MB terima di tanggal 26/8/25 juga.
A96: 45870 | B96: Invoiced | C96: SO | D96: 25708462 | E96: 25106758 | F96: POPD/GMC/25050191 | G96: 45889 | H96: PT. GRAND MULTI CHEMICALS JAKARTA-AA | I96: 9638940010 | J96: COFFEE FLV SD N7526 | K96: 80 | L96: KG | M96: 80 | N96: 843012 | O96: 67440960 | P96: 67440960 | Q96: 0 | R96: 0 | S96: IDR | T96: 46635966 | U96: 46635966 | V96: 20804994 | W96: 0.30849196 | X96: 20804994 | Z96: . | AA96: 2306511 | AB96: PT. GRAND MULTI CHEMICALS TANGERANG-AA | AC96: AGNESYA ADIFILIA | AD96: 94 | AE96: 0 | AF96: 102 | AH96: . | AJ96: . | AK96: T | AL96: Non-Affiliate | AM96: Distributor | AN96: =VLOOKUP(I96,Sheet1!A:D,4,FALSE) -> A210600 | AP96: Invoice di kasih pagi jam 10:00. Invoice tgl 20,22/08/2025. MB terima di tanggal 26/8/25 juga.
A97: 45870 | B97: Invoiced | C97: SO | D97: 25708463 | E97: 25106759 | F97: POPD/GMC/25050192 | G97: 45889 | H97: PT. GRAND MULTI CHEMICALS JAKARTA-AA | I97: 9630310005 | J97: COFFEE FLAVOUR N4592 5KG | K97: 130 | L97: KG | M97: 130 | N97: 565839 | O97: 73559070 | P97: 73559070 | Q97: 0 | R97: 0 | S97: IDR | T97: 45596468 | U97: 45596468 | V97: 27962602 | W97: 0.38013806 | X97: 27962602 | Z97: . | AA97: 2306511 | AB97: PT. GRAND MULTI CHEMICALS TANGERANG-AA | AC97: AGNESYA ADIFILIA | AD97: 94 | AE97: 0 | AF97: 208 | AH97: . | AJ97: . | AK97: T | AL97: Non-Affiliate | AM97: Distributor | AN97: =VLOOKUP(I97,Sheet1!A:D,4,FALSE) -> A210600 | AP97: Invoice di kasih pagi jam 10:00. Invoice tgl 20,22/08/2025. MB terima di tanggal 26/8/25 juga.
A98: 45870 | B98: Invoiced | C98: SO | D98: 25708464 | E98: 25106761 | F98: POPD/GMC/25050194 | G98: 45889 | H98: PT. GRAND MULTI CHEMICALS JAKARTA-AA | I98: 9631080010 | J98: CHOCOLATE FLAVOUR SD N7314 | K98: 130 | L98: KG | M98: 130 | N98: 576856 | O98: 74991280 | P98: 74991280 | Q98: 0 | R98: 0 | S98: IDR | T98: 49930074 | U98: 49930074 | V98: 25061206 | W98: 0.33418827 | X98: 25061206 | Z98: . | AA98: 2306511 | AB98: PT. GRAND MULTI CHEMICALS TANGERANG-AA | AC98: AGNESYA ADIFILIA | AD98: 94 | AE98: 0 | AF98: 208 | AH98: . | AJ98: . | AK98: T | AL98: Non-Affiliate | AM98: Distributor | AN98: =VLOOKUP(I98,Sheet1!A:D,4,FALSE) -> A210600 | AP98: Invoice di kasih pagi jam 10:00. Invoice tgl 20,22/08/2025. MB terima di tanggal 26/8/25 juga.
A99: 45870 | B99: Invoiced | C99: SO | D99: 25708465 | E99: 25106787 | F99: POPD/GMC/25060218 | G99: 45891 | H99: PT. GRAND MULTI CHEMICALS JAKARTA | I99: IDF2017 | J99: DB N2945 (FML10) 10KG | K99: 570 | L99: KG | M99: 570 | N99: 315561.84 | O99: 1.7987025e+08 | P99: 1.7987025e+08 | Q99: 0 | R99: 0 | S99: IDR | T99: 89569016 | U99: 89569016 | V99: 90301232 | W99: 0.5020354 | X99: 90301232 | Y99: DEL | Z99: Delivered | AA99: 15161 | AB99: PT. GRAND MULTI CHEMICALS TANGERANG | AC99: AGNESYA ADIFILIA | AD99: 94 | AE99: 0 | AF99: 202 | AH99: . | AJ99: . | AK99: M | AL99: Non-Affiliate | AM99: Distributor | AN99: =VLOOKUP(I99,Sheet1!A:D,4,FALSE) -> A210600 | AP99: Invoice di kasih pagi jam 10:00. Invoice tgl 20,22/08/2025. MB terima di tanggal 26/8/25 juga.
A100: 45870 | B100: Invoiced | C100: SO | D100: 25708466 | E100: 25106790 | F100: POPD/GMC/25060220 | G100: 45891 | H100: PT. GRAND MULTI CHEMICALS JAKARTA | I100: IDF2004 | J100: DB XF1591 10KG | K100: 240 | L100: KG | M100: 240 | N100: 239544.6 | O100: 57490704 | P100: 57490704 | Q100: 0 | R100: 0 | S100: IDR | T100: 33693463 | U100: 33693463 | V100: 23797241 | W100: 0.41393198 | X100: 23797241 | Y100: DEL | Z100: Delivered | AA100: 15161 | AB100: PT. GRAND MULTI CHEMICALS TANGERANG | AC100: AGNESYA ADIFILIA | AD100: 94 | AE100: 0 | AF100: 202 | AH100: . | AJ100: . | AK100: M | AL100: Non-Affiliate | AM100: Distributor | AN100: =VLOOKUP(I100,Sheet1!A:D,4,FALSE) -> A210600 | AP100: Invoice di kasih pagi jam 10:00. Invoice tgl 20,22/08/2025. MB terima di tanggal 26/8/25 juga.
A101: 45870 | B101: Invoiced | C101: SO | D101: 25708467 | E101: 25106872 | F101: POPD/GMC/25080308 | G101: 45891 | H101: PT. GRAND MULTI CHEMICALS JAKARTA | I101: IDF2016 | J101: DB XF1745 10KG | K101: 270 | L101: KG | M101: 270 | N101: 327030 | O101: 88298100 | P101: 88298100 | Q101: 0 | R101: 0 | S101: IDR | T101: 40066658 | U101: 40066658 | V101: 48231442 | W101: 0.5462342 | X101: 48231442 | Y101: DEL | Z101: Delivered | AA101: 15161 | AB101: PT. GRAND MULTI CHEMICALS TANGERANG | AC101: AGNESYA ADIFILIA | AD101: 94 | AE101: 0 | AF101: 202 | AH101: . | AJ101: . | AK101: M | AL101: Non-Affiliate | AM101: Distributor | AN101: =VLOOKUP(I101,Sheet1!A:D,4,FALSE) -> A210600 | AP101: Invoice di kasih pagi jam 10:00. Invoice tgl 20,22/08/2025. MB terima di tanggal 26/8/25 juga.
A102: 45870 | B102: Invoiced | C102: SO | D102: 25708478 | E102: 25106787 | F102: POPD/GMC/25060218 | G102: 45896 | H102: PT. GRAND MULTI CHEMICALS JAKARTA | I102: IDF2017 | J102: DB N2945 (FML10) 10KG | K102: 430 | L102: KG | M102: 430 | N102: 315561.84 | O102: 1.3569159e+08 | P102: 1.3569159e+08 | Q102: 0 | R102: 0 | S102: IDR | T102: 67569609 | U102: 67569609 | V102: 68121982 | W102: 0.5020354 | X102: 68121982 | Y102: DEL | Z102: Delivered | AA102: 15161 | AB102: PT. GRAND MULTI CHEMICALS TANGERANG | AC102: AGNESYA ADIFILIA | AD102: 94 | AE102: 0 | AF102: 202 | AH102: . | AJ102: . | AK102: M | AL102: Non-Affiliate | AM102: Distributor | AN102: =VLOOKUP(I102,Sheet1!A:D,4,FALSE) -> A210600 | AP102: Invoice dikasih sore jam 16:00. Invoice tgl 27/8/25.MB terima di tanggal 29/8/25. ( sore les Inggris
A103: 45870 | B103: Invoiced | C103: SO | D103: 25708479 | E103: 25106790 | F103: POPD/GMC/25060220 | G103: 45896 | H103: PT. GRAND MULTI CHEMICALS JAKARTA | I103: IDF2004 | J103: DB XF1591 10KG | K103: 260 | L103: KG | M103: 260 | N103: 239544.6 | O103: 62281596 | P103: 62281596 | Q103: 0 | R103: 0 | S103: IDR | T103: 36501251 | U103: 36501251 | V103: 25780345 | W103: 0.41393198 | X103: 25780345 | Y103: DEL | Z103: Delivered | AA103: 15161 | AB103: PT. GRAND MULTI CHEMICALS TANGERANG | AC103: AGNESYA ADIFILIA | AD103: 94 | AE103: 0 | AF103: 202 | AH103: . | AJ103: . | AK103: M | AL103: Non-Affiliate | AM103: Distributor | AN103: =VLOOKUP(I103,Sheet1!A:D,4,FALSE) -> A210600 | AP103: Invoice dikasih sore jam 16:00. Invoice tgl 27/8/25.MB terima di tanggal 29/8/25. ( sore les Inggris
A104: 45870 | B104: Invoiced | C104: SO | D104: 25708480 | E104: 25106871 | F104: POPD/GMC/25080307 | G104: 45896 | H104: PT. GRAND MULTI CHEMICALS JAKARTA | I104: IDF2003 | J104: DB XF1589 10KG | K104: 150 | L104: KG | M104: 150 | N104: 308952 | O104: 46342800 | P104: 46342800 | Q104: 0 | R104: 0 | S104: IDR | T104: 24424928 | U104: 24424928 | V104: 21917872 | W104: 0.47295097 | X104: 21917872 | Y104: DEL | Z104: Delivered | AA104: 15161 | AB104: PT. GRAND MULTI CHEMICALS TANGERANG | AC104: AGNESYA ADIFILIA | AD104: 94 | AE104: 0 | AF104: 202 | AH104: . | AJ104: . | AK104: M | AL104: Non-Affiliate | AM104: Distributor | AN104: =VLOOKUP(I104,Sheet1!A:D,4,FALSE) -> A210600 | AP104: Invoice dikasih sore jam 16:00. Invoice tgl 27/8/25.MB terima di tanggal 29/8/25. ( sore les Inggris
...

Sheet COCA-COLA
A5: PT. Sensient Technologies Indonesia
A6: Date - Period | B6: StatusType | C6: Order Type | D6: Invoice | E6: Customer Order | F6: Order | G6: Ship Date | H6: Customer Group | I6: Item Number | J6: Item Description | K6: Input Quantity | L6: Input UOM | M6: Total KG | N6: Unit Price | O6: Amount | P6: Amount - Sales and orders Only | Q6: Foreign per unit | R6: Foreign Amount | S6: Currency | T6: StandardCost | U6: StandardCost- Sales and orders Only | V6: Gross Margin | W6: Gross Margin % | X6: Margin - Sales and orders Only | Y6: IncoTerms | Z6: IncoTerms Description | AA6: Ship To | AB6: Ship To Name | AC6: Sales Region Desc | AD6: Sales Region | AE6: Delivery Days | AF6: GL Category | AG6: Cat6 | AH6: Cat 6 Desc | AI6: Cat7 | AJ6: Cat 7 Desc | AK6: SaleType | AL6: AffiliateType | AM6: CustomerType | AN6: HS-Code | AP6: Note Finance MB
A7: 45689 | B7: Invoiced | C7: SO | D7: 25707963 | E7: 24106349 | F7: 4100190669 | G7: 45689 | H7: PT. COCA COLA INDONESIA JAKARTA | I7: M98110C20 | J7: RED NO 5 E 122 EXTRUKLEEN | K7: 1840 | L7: KG | M7: 1840 | N7: 453556 | O7: 834543040 | P7: 834543040 | Q7: 0 | R7: 0 | S7: IDR | T7: 6.4166672e+08 | U7: 6.4166672e+08 | V7: 1.9287632e+08 | W7: 0.23111608 | X7: 1.9287632e+08 | Z7: . | AA7: 15454 | AB7: PT. COCA COLA INDONESIA BOGOR | AC7: ELLY HENDRA | AD7: 35 | AE7: 0 | AF7: 966 | AH7: . | AJ7: . | AK7: T | AL7: Non-Affiliate | AM7: Multinational | AN7: =VLOOKUP(I7,Sheet1!A:D,4,FALSE) -> A320400 | AP7: Invoice di kasih tanggal 7/02/25. Finance abis clossing. MB terima di tanggal 7/2/25 jam 18:19
A8: 45689 | B8: Invoiced | C8: SO | D8: 25707964 | E8: 24106349 | F8: 4100190669 | G8: 45691 | H8: PT. COCA COLA INDONESIA JAKARTA | I8: M98110C20 | J8: RED NO 5 E 122 EXTRUKLEEN | K8: 100 | L8: KG | M8: 100 | N8: 453556 | O8: 45355600 | P8: 45355600 | Q8: 0 | R8: 0 | S8: IDR | T8: 34873191 | U8: 34873191 | V8: 10482409 | W8: 0.23111608 | X8: 10482409 | Z8: . | AA8: 15454 | AB8: PT. COCA COLA INDONESIA BOGOR | AC8: ELLY HENDRA | AD8: 35 | AE8: 0 | AF8: 966 | AH8: . | AJ8: . | AK8: T | AL8: Non-Affiliate | AM8: Multinational | AN8: =VLOOKUP(I8,Sheet1!A:D,4,FALSE) -> A320400 | AP8: Invoice di kasih tanggal 7/02/25. Finance abis clossing. MB terima di tanggal 7/2/25 jam 18:19
A9: 45689 | B9: Invoiced | C9: SO | D9: 25707965 | E9: 24106348 | F9: 4100190668 | G9: 45691 | H9: PT. COCA COLA INDONESIA JAKARTA | I9: M98110C20 | J9: RED NO 5 E 122 EXTRUKLEEN | K9: 1700 | L9: KG | M9: 1700 | N9: 442865 | O9: 752870500 | P9: 752870500 | Q9: 0 | R9: 0 | S9: IDR | T9: 5.9284425e+08 | U9: 5.9284425e+08 | V9: 1.6002625e+08 | W9: 0.21255481 | X9: 1.6002625e+08 | Z9: . | AA9: 15454 | AB9: PT. COCA COLA INDONESIA BOGOR | AC9: ELLY HENDRA | AD9: 35 | AE9: 0 | AF9: 966 | AH9: . | AJ9: . | AK9: T | AL9: Non-Affiliate | AM9: Multinational | AN9: =VLOOKUP(I9,Sheet1!A:D,4,FALSE) -> A320400 | AP9: Invoice di kasih tanggal 7/02/25. Finance abis clossing. MB terima di tanggal 7/2/25 jam 18:19
A10: 45717 | B10: Invoiced | C10: SO | D10: 25708038 | E10: 24106350 | F10: 4100190670 | G10: 45719 | H10: PT. COCA COLA INDONESIA JAKARTA | I10: M98110C20 | J10: RED NO 5 E 122 EXTRUKLEEN | K10: 1460 | L10: KG | M10: 1460 | N10: 453556 | O10: 662191760 | P10: 662191760 | Q10: 0 | R10: 0 | S10: IDR | T10: 509148594 | U10: 509148594 | V10: 153043166 | W10: 0.23111608 | X10: 153043166 | Z10: . | AA10: 15454 | AB10: PT. COCA COLA INDONESIA BOGOR | AC10: AGNESYA ADIFILIA | AD10: 94 | AE10: 0 | AF10: 966 | AH10: . | AJ10: . | AK10: T | AL10: Non-Affiliate | AM10: Multinational | AN10: =VLOOKUP(I10,Sheet1!A:D,4,FALSE) -> A320400 | AP10: Invoice dikasih Pagi jam 09:38 tanggal 7/3/25. Invoice tgl 03/3/25.MB terima ditanggal 07/3/25,abis Clossing Finance
A11: 45748 | B11: Invoiced | C11: SO | D11: 25708137 | E11: 25106574 | F11: 4100290287 | G11: 45763 | H11: PT. COCA COLA INDONESIA JAKARTA | I11: M98110C20 | J11: RED NO 5 E 122 EXTRUKLEEN | K11: 1360 | L11: KG | M11: 1360 | N11: 472700 | O11: 642872000 | P11: 642872000 | Q11: 0 | R11: 0 | S11: IDR | T11: 4.742754e+08 | U11: 4.742754e+08 | V11: 1.685966e+08 | W11: 0.26225532 | X11: 1.685966e+08 | Z11: . | AA11: 15454 | AB11: PT. COCA COLA INDONESIA BOGOR | AC11: AGNESYA ADIFILIA | AD11: 94 | AE11: 0 | AF11: 966 | AH11: . | AJ11: . | AK11: T | AL11: Non-Affiliate | AM11: Multinational | AN11: =VLOOKUP(I11,Sheet1!A:D,4,FALSE) -> A320400 | AP11: Invoice di kasih jam 11:30 tanggal 17/4/25.Invoice tanggal 14,1516.MB terima ditanggal 17/4/25.
A12: 45870 | B12: Invoiced | C12: SO | D12: 25708428 | E12: 25106707 | F12: 4100369945 | G12: 45883 | H12: PT. COCA COLA INDONESIA JAKARTA | I12: M98110C20 | J12: RED NO 5 E 122 EXTRUKLEEN | K12: 760 | L12: KG | M12: 760 | N12: 487925 | O12: 370823000 | P12: 370823000 | Q12: 0 | R12: 0 | S12: IDR | T12: 2.7922441e+08 | U12: 2.7922441e+08 | V12: 91598589 | W12: 0.24701432 | X12: 91598589 | Z12: . | AA12: 15454 | AB12: PT. COCA COLA INDONESIA BOGOR | AC12: AGNESYA ADIFILIA | AD12: 94 | AE12: 0 | AF12: 966 | AH12: . | AJ12: . | AK12: T | AL12: Non-Affiliate | AM12: Multinational | AN12: =VLOOKUP(I12,Sheet1!A:D,4,FALSE) -> A320400 | AP12: Invoice di kasih jam pulang kerja tgl 15/8/25. Invoice tgl 13,14/08/2025. MB terima di tanggal 19/8/25.
A13: 45901 | B13: Invoiced | C13: SO | D13: 25708584 | E13: 25106770 | F13: 4100388189 | G13: 45926 | H13: PT. COCA COLA INDONESIA JAKARTA | I13: M98110C20 | J13: RED NO 5 E 122 EXTRUKLEEN | K13: 1600 | L13: KG | M13: 1600 | N13: 473715 | O13: 757944000 | P13: 757944000 | Q13: 0 | R13: 0 | S13: IDR | T13: 5.8784086e+08 | U13: 5.8784086e+08 | V13: 1.7010314e+08 | W13: 0.22442705 | X13: 1.7010314e+08 | Z13: . | AA13: 15454 | AB13: PT. COCA COLA INDONESIA BOGOR | AC13: AGNESYA ADIFILIA | AD13: 94 | AE13: 0 | AF13: 966 | AH13: . | AJ13: . | AK13: T | AL13: Non-Affiliate | AM13: Multinational | AN13: =VLOOKUP(I13,Sheet1!A:D,4,FALSE) -> A320400
AN14: =VLOOKUP(I14,Sheet1!A:D,4,FALSE) -> #N/A
AN15: =VLOOKUP(I15,Sheet1!A:D,4,FALSE) -> #N/A
AN16: =VLOOKUP(I16,Sheet1!A:D,4,FALSE) -> #N/A
AN17: =VLOOKUP(I17,Sheet1!A:D,4,FALSE) -> #N/A
AN18: =VLOOKUP(I18,Sheet1!A:D,4,FALSE) -> #N/A
AN19: =VLOOKUP(I19,Sheet1!A:D,4,FALSE) -> #N/A
AN20: =VLOOKUP(I20,Sheet1!A:D,4,FALSE) -> #N/A
AN21: =VLOOKUP(I21,Sheet1!A:D,4,FALSE) -> #N/A
AN22: =VLOOKUP(I22,Sheet1!A:D,4,FALSE) -> #N/A
AN23: =VLOOKUP(I23,Sheet1!A:D,4,FALSE) -> #N/A
AN24: =VLOOKUP(I24,Sheet1!A:D,4,FALSE) -> #N/A
AN25: =VLOOKUP(I25,Sheet1!A:D,4,FALSE) -> #N/A
... AN147: =VLOOKUP(I147,Sheet1!A:D,4,FALSE) -> #N/A

Sheet KIANTAKA
A5: PT. Sensient Technologies Indonesia
A6: Date - Period | B6: StatusType | C6: Order Type | D6: Invoice | E6: Customer Order | F6: Order | G6: Ship Date | H6: Customer Group | I6: Item Number | J6: Item Description | K6: Input Quantity | L6: Input UOM | M6: Total KG | N6: Unit Price | O6: Amount | P6: Amount - Sales and orders Only | Q6: Foreign per unit | R6: Foreign Amount | S6: Currency | T6: StandardCost | U6: StandardCost- Sales and orders Only | V6: Gross Margin | W6: Gross Margin % | X6: Margin - Sales and orders Only | Y6: IncoTerms | Z6: IncoTerms Description | AA6: Ship To | AB6: Ship To Name | AC6: Sales Region Desc | AD6: Sales Region | AE6: Delivery Days | AF6: GL Category | AG6: Cat6 | AH6: Cat 6 Desc | AI6: Cat7 | AJ6: Cat 7 Desc | AK6: SaleType | AL6: AffiliateType | AM6: CustomerType | AN6: HS-Code | AP6: Catatan MB
A7: 45658 | B7: Invoiced | C7: SO | D7: 25707928 | E7: 24106398 | F7: B2410011 | G7: 45664 | H7: PT KIANTAKA RASA | I7: 11100094 | J7: CARMINE LAKE HIGH TINTING 50% | K7: 500 | L7: KG | M7: 500 | N7: 4390400 | O7: 2195200000 | P7: 2195200000 | Q7: 0 | R7: 0 | S7: IDR | T7: 1931416705 | U7: 1931416705 | V7: 263783295 | W7: 0.12016367 | X7: 263783295 | Z7: . | AA7: 2308618 | AB7: PT KIANTAKA RASA | AC7: AGNESYA ADIFILIA | AD7: 94 | AE7: 0 | AF7: 966 | AH7: . | AJ7: . | AK7: T | AL7: Non-Affiliate | AM7: Domestic | AN7: =VLOOKUP(I7,Sheet1!A:D,4,FALSE) -> A320400 | AP7: Invoice di kasih pagi jam 09:30. Invoice tanggal 17/1/25.MB terima di tanggal 22/1/25.
A8: 45748 | B8: Invoiced | C8: SO | D8: 25708124 | E8: 25106610 | F8: B2502016 | G8: 45761 | H8: PT KIANTAKA RASA | I8: 11100602 | J8: PINK CARMINE LAKE 50% | K8: 5 | L8: KG | M8: 5 | N8: 6810387 | O8: 34051935 | P8: 34051935 | Q8: 0 | R8: 0 | S8: IDR | T8: 30673872 | U8: 30673872 | V8: 3378063.1 | W8: 0.099203266 | X8: 3378063.1 | Z8: . | AA8: 2308618 | AB8: PT KIANTAKA RASA | AC8: AGNESYA ADIFILIA | AD8: 94 | AE8: 0 | AF8: 966 | AH8: . | AJ8: . | AK8: T | AL8: Non-Affiliate | AM8: Domestic | AN8: =VLOOKUP(I8,Sheet1!A:D,4,FALSE) -> A320400 | AP8: Invoice di kasih jam 11:30 tanggal 17/4/25.Invoice tanggal 14,1516.MB terima ditanggal 17/4/25.
A9: 45809 | B9: Invoiced | C9: SO | D9: 25708288 | E9: 25106778 | F9: B2506003 | G9: 45824 | H9: PT KIANTAKA RASA | I9: 043771020 | J9: YELLOW MICROFINE | K9: 100 | L9: KG | M9: 100 | N9: 2069067 | O9: 206906700 | P9: 206906700 | Q9: 0 | R9: 0 | S9: IDR | T9: 1.4539999e+08 | U9: 1.4539999e+08 | V9: 61506708 | W9: 0.29726784 | X9: 61506708 | Z9: . | AA9: 2308618 | AB9: PT KIANTAKA RASA | AC9: AGNESYA ADIFILIA | AD9: 94 | AE9: 0 | AF9: 966 | AH9: . | AJ9: . | AK9: T | AL9: Non-Affiliate | AM9: Domestic | AN9: =VLOOKUP(I9,Sheet1!A:D,4,FALSE) -> A320400 | AP9: Invoice dikasih jam pulang kerja.invoice tgl 16 /6/25. MB terima di tanggal 17/6/25.
A10: 45839 | B10: Invoiced | C10: SO | D10: 25708328 | E10: 25106778 | F10: B2506003 | G10: 45839 | H10: PT KIANTAKA RASA | I10: 043771020 | J10: YELLOW MICROFINE | K10: 100 | L10: KG | M10: 100 | N10: 2069067 | O10: 206906700 | P10: 206906700 | Q10: 0 | R10: 0 | S10: IDR | T10: 1.4539999e+08 | U10: 1.4539999e+08 | V10: 61506708 | W10: 0.29726784 | X10: 61506708 | Z10: . | AA10: 2308618 | AB10: PT KIANTAKA RASA | AC10: AGNESYA ADIFILIA | AD10: 94 | AE10: 0 | AF10: 966 | AH10: . | AJ10: . | AK10: T | AL10: Non-Affiliate | AM10: Domestic | AN10: =VLOOKUP(I10,Sheet1!A:D,4,FALSE) -> A320400 | AP10: Invoice dikasih jam 16:38. Sore, Invoice tgl 1,2,3.Finance abis clossing. MB terima di tgl 4/7/25.
A11: 45901 | B11: Invoiced | C11: SO | D11: 25708542 | E11: 25106875 | F11: B2508005 | G11: 45918 | H11: PT KIANTAKA RASA | I11: 043771020 | J11: YELLOW MICROFINE | K11: 100 | L11: KG | M11: 100 | N11: 2094078 | O11: 209407800 | P11: 209407800 | Q11: 0 | R11: 0 | S11: IDR | T11: 1.4326706e+08 | U11: 1.4326706e+08 | V11: 66140736 | W11: 0.31584657 | X11: 66140736 | Z11: . | AA11: 2308618 | AB11: PT KIANTAKA RASA | AC11: AGNESYA ADIFILIA | AD11: 94 | AE11: 0 | AF11: 966 | AH11: . | AJ11: . | AK11: T | AL11: Non-Affiliate | AM11: Domestic | AN11: =VLOOKUP(I11,Sheet1!A:D,4,FALSE) -> A320400 | AP11: invoice dikasih jam 14:50 tgl 24/9/25, invoice tgl 12,18,19,20,22.MB terima di tanggal 24/9/25.
A12: 45901 | B12: Invoiced | C12: SO | D12: 25708582 | E12: 25106823 | F12: B2506018 | G12: 45926 | H12: PT KIANTAKA RASA | I12: 11100094 | J12: CARMINE LAKE HIGH TINTING 50% | K12: 260 | L12: KG | M12: 260 | N12: 7550205 | O12: 1963053300 | P12: 1963053300 | Q12: 0 | R12: 0 | S12: IDR | T12: 1.5909775e+09 | U12: 1.5909775e+09 | V12: 3.720758e+08 | W12: 0.18953933 | X12: 3.720758e+08 | Z12: . | AA12: 2308618 | AB12: PT KIANTAKA RASA | AC12: AGNESYA ADIFILIA | AD12: 94 | AE12: 0 | AF12: 966 | AH12: . | AJ12: . | AK12: T | AL12: Non-Affiliate | AM12: Domestic | AN12: =VLOOKUP(I12,Sheet1!A:D,4,FALSE) -> A320400
AN13: =VLOOKUP(I13,Sheet1!A:D,4,FALSE) -> #N/A
AN14: =VLOOKUP(I14,Sheet1!A:D,4,FALSE) -> #N/A
AN15: =VLOOKUP(I15,Sheet1!A:D,4,FALSE) -> #N/A
AN16: =VLOOKUP(I16,Sheet1!A:D,4,FALSE) -> #N/A
AN17: =VLOOKUP(I17,Sheet1!A:D,4,FALSE) -> #N/A
AN18: =VLOOKUP(I18,Sheet1!A:D,4,FALSE) -> #N/A
AN19: =VLOOKUP(I19,Sheet1!A:D,4,FALSE) -> #N/A
AN20: =VLOOKUP(I20,Sheet1!A:D,4,FALSE) -> #N/A
AN21: =VLOOKUP(I21,Sheet1!A:D,4,FALSE) -> #N/A
AN22: =VLOOKUP(I22,Sheet1!A:D,4,FALSE) -> #N/A
AN23: =VLOOKUP(I23,Sheet1!A:D,4,FALSE) -> #N/A
AN24: =VLOOKUP(I24,Sheet1!A:D,4,FALSE) -> #N/A
... AN211: =VLOOKUP(I211,Sheet1!A:D,4,FALSE) -> #N/A

Sheet PEPSICO
A5: PT. Sensient Technologies Indonesia
A6: Date - Period | B6: StatusType | C6: Order Type | D6: Invoice | E6: Customer Order | F6: Order | G6: Ship Date | H6: Customer Group | I6: Item Number | J6: Item Description | K6: Input Quantity | L6: Input UOM | M6: Total KG | N6: Unit Price | O6: Amount | P6: Amount - Sales and orders Only | Q6: Foreign per unit | R6: Foreign Amount | S6: Currency | T6: StandardCost | U6: StandardCost- Sales and orders Only | V6: Gross Margin | W6: Gross Margin % | X6: Margin - Sales and orders Only | Y6: IncoTerms | Z6: IncoTerms Description | AA6: Ship To | AB6: Ship To Name | AC6: Sales Region Desc | AD6: Sales Region | AE6: Delivery Days | AF6: GL Category | AG6: Cat6 | AH6: Cat 6 Desc | AI6: Cat7 | AJ6: Cat 7 Desc | AK6: SaleType | AL6: AffiliateType | AM6: CustomerType | AN6: HS-Code
A7: 45901 | B7: Invoiced | C7: SO | D7: 25708556 | E7: 25106961 | F7: 4514751715 | G7: 45918 | H7: PT PEPSICO INDONESIA FOODS AND BEVERAGES | I7: 503750.010 | J7: MIDNIGHT BLACK P-WD 10KG | K7: 10 | L7: KG | M7: 10 | N7: 1299280 | O7: 12992800 | P7: 12992800 | Q7: 0 | R7: 0 | S7: IDR | T7: 5091083.4 | U7: 5091083.4 | V7: 7901716.6 | W7: 0.60816118 | X7: 7901716.6 | Z7: . | AA7: 2309894 | AB7: PT PEPSICO INDONESIA FOODS AND BEVERAGES | AC7: AGNESYA ADIFILIA | AD7: 94 | AE7: 0 | AF7: 966 | AG7: TCNP | AH7: TRA COL NAT POWDER | AJ7: . | AK7: T | AL7: Non-Affiliate | AM7: Domestic | AN7: =VLOOKUP(I7,Sheet1!A:D,4,FALSE) -> A320400 | AP7: invoice dikasih jam 14:50 tgl 24/9/25, invoice tgl 12,18,19,20,22.MB terima di tanggal 24/9/25.
AN8: =VLOOKUP(I8,Sheet1!A:D,4,FALSE) -> #N/A
AN9: =VLOOKUP(I9,Sheet1!A:D,4,FALSE) -> #N/A
AN10: =VLOOKUP(I10,Sheet1!A:D,4,FALSE) -> #N/A
AN11: =VLOOKUP(I11,Sheet1!A:D,4,FALSE) -> #N/A
AN12: =VLOOKUP(I12,Sheet1!A:D,4,FALSE) -> #N/A
AN13: =VLOOKUP(I13,Sheet1!A:D,4,FALSE) -> #N/A
AN14: =VLOOKUP(I14,Sheet1!A:D,4,FALSE) -> #N/A
AN15: =VLOOKUP(I15,Sheet1!A:D,4,FALSE) -> #N/A
AN16: =VLOOKUP(I16,Sheet1!A:D,4,FALSE) -> #N/A
AN17: =VLOOKUP(I17,Sheet1!A:D,4,FALSE) -> #N/A
AN18: =VLOOKUP(I18,Sheet1!A:D,4,FALSE) -> #N/A
AN19: =VLOOKUP(I19,Sheet1!A:D,4,FALSE) -> #N/A
... AN570: =VLOOKUP(I570,Sheet1!A:D,4,FALSE) -> #N/A
AP571: Invoice dikasih Pagi jam 09:38 tanggal 7/3/25. Invoice tgl 03/3/25.MB terima ditanggal 07/3/25,abis Clossing Finance
AP572: Invoice dikasih Pagi jam 09:38 tanggal 7/3/25. Invoice tgl 03/3/25.MB terima ditanggal 07/3/25,abis Clossing Finance
AP573: Invoice di kasih pagi jam 09:30. Invoice tanggal 03/03/2025. MB terima di tanggal 10/3/25. finance abis clossing
AP574: Invoice di kasih pagi jam 09:30. Invoice tanggal 03/03/2025. MB terima di tanggal 10/3/25. finance abis clossing
AP575: Invoice di kasih pagi jam 09:30. Invoice tanggal 03/03/2025. MB terima di tanggal 10/3/25. finance abis clossing
AP576: Invoice di kasih pagi jam 09:30. Invoice tanggal 03/03/2025. MB terima di tanggal 10/3/25. finance abis clossing
AP577: Invoice di kasih pagi jam 09:30. Invoice tanggal 03/03/2025. MB terima di tanggal 10/3/25. finance abis clossing
AP578: Invoice di kasih pagi jam 09:30. Invoice tanggal 03/03/2025. MB terima di tanggal 10/3/25. finance abis clossing
AP579: Invoice di kasih pagi jam 09:30. Invoice tanggal 03/03/2025. MB terima di tanggal 10/3/25. finance abis clossing
AP580: Invoice di kasih pagi jam 09:30. Invoice tanggal 03/03/2025. MB terima di tanggal 10/3/25. finance abis clossing
AP581: Invoice di kasih pagi jam 09:30. Invoice tanggal 03/03/2025. MB terima di tanggal 10/3/25. finance abis clossing
AP582: Invoice di kasih pagi jam 09:30. Invoice tanggal 03/03/2025. MB terima di tanggal 10/3/25. finance abis clossing
... AP936: Invoice di kasih jam pulang kerja jam 18:45.invoice tgl 16/9/25. MB terima di tanggal 19/9/25.

Sheet Nutrifood
A5: PT. Sensient Technologies Indonesia
A6: Date - Period | B6: StatusType | C6: Order Type | D6: Invoice | E6: Customer Order | F6: Order | G6: Ship Date | H6: Customer Group | I6: Item Number | J6: Item Description | K6: Input Quantity | L6: Input UOM | M6: Total KG | N6: Unit Price | O6: Amount | P6: Amount - Sales and orders Only | Q6: Foreign per unit | R6: Foreign Amount | S6: Currency | T6: StandardCost | U6: StandardCost- Sales and orders Only | V6: Gross Margin | W6: Gross Margin % | X6: Margin - Sales and orders Only | Y6: IncoTerms | Z6: IncoTerms Description | AA6: Ship To | AB6: Ship To Name | AC6: Sales Region Desc | AD6: Sales Region | AE6: Delivery Days | AF6: GL Category | AG6: Cat6 | AH6: Cat 6 Desc | AI6: Cat7 | AJ6: Cat 7 Desc | AK6: SaleType | AL6: AffiliateType | AM6: CustomerType | AN6: HS-Code | AO6: Adress | AP6: Ship To Adress | AR6: Catatan MB
A7: 45658 | B7: Invoiced | C7: SO | D7: 25707931 | E7: 24106432 | F7: 225984 | G7: 45674 | H7: NUTRIFOOD | I7: C86040O20 | J7: EUROCERT SUNSET YELLOW BG | K7: 100 | L7: KG | M7: 100 | N7: 194624.96 | O7: 19462496 | P7: 19462496 | Q7: 0 | R7: 0 | S7: IDR | T7: 11764568 | U7: 11764568 | V7: 7697927.5 | W7: 0.39552622 | X7: 7697927.5 | Z7: . | AA7: 2308688 | AB7: PT. NUTRIFOOD INDONESIA BOGOR | AC7: AGNESYA ADIFILIA | AD7: 94 | AE7: 0 | AF7: 960 | AH7: . | AJ7: . | AK7: T | AL7: Non-Affiliate | AM7: Domestic | AN7: =VLOOKUP(I7,Sheet1!A:D,4,FALSE) -> A320400 | AP7: Ciawi Pusat | AR7: Invoice di kasih pagi jam 09:30. Invoice tanggal 17/1/25.MB terima di tanggal 22/1/25.
A8: 45658 | B8: Invoiced | C8: SO | D8: 25707932 | E8: 24106320 | F8: 225432 | G8: 45674 | H8: NUTRIFOOD | I8: 056011001 | J8: FD&C BLUE NO 1 POWDER 1KG | K8: 8 | L8: KG | M8: 8 | N8: 947800.59 | O8: 7582404.7 | P8: 7582404.7 | Q8: 0 | R8: 0 | S8: IDR | T8: 5361377.2 | U8: 5361377.2 | V8: 2221027.5 | W8: 0.29291862 | X8: 2221027.5 | Z8: . | AA8: 15440 | AB8: PT. NUTRIFOOD INDONESIA MM2100 | AC8: AGNESYA ADIFILIA | AD8: 94 | AE8: 0 | AF8: 961 | AG8: TCSP | AH8: TRA COL SYN DYE POWDER | AJ8: . | AK8: T | AL8: Non-Affiliate | AM8: Domestic | AN8: =VLOOKUP(I8,Sheet1!A:D,4,FALSE) -> A320400 | AP8: Cibitung | AR8: Invoice di kasih pagi jam 09:30. Invoice tanggal 17/1/25.MB terima di tanggal 22/1/25.
A9: 45658 | B9: Invoiced | C9: SO | D9: 25707933 | E9: 24106321 | F9: 225433 | G9: 45674 | H9: NUTRIFOOD | I9: 056011001 | J9: FD&C BLUE NO 1 POWDER 1KG | K9: 8 | L9: KG | M9: 8 | N9: 947800.59 | O9: 7582404.7 | P9: 7582404.7 | Q9: 0 | R9: 0 | S9: IDR | T9: 5361377.2 | U9: 5361377.2 | V9: 2221027.5 | W9: 0.29291862 | X9: 2221027.5 | Z9: . | AA9: 15440 | AB9: PT. NUTRIFOOD INDONESIA MM2100 | AC9: AGNESYA ADIFILIA | AD9: 94 | AE9: 0 | AF9: 961 | AG9: TCSP | AH9: TRA COL SYN DYE POWDER | AJ9: . | AK9: T | AL9: Non-Affiliate | AM9: Domestic | AN9: =VLOOKUP(I9,Sheet1!A:D,4,FALSE) -> A320400 | AP9: Cibitung | AR9: Invoice di kasih pagi jam 09:30. Invoice tanggal 17/1/25.MB terima di tanggal 22/1/25.
A10: 45658 | B10: Invoiced | C10: SO | D10: 25707934 | E10: 24106323 | F10: 225439 | G10: 45674 | H10: NUTRIFOOD | I10: M70000020 | J10: CARMOISINE 20KG | K10: 40 | L10: KG | M10: 40 | N10: 588514.26 | O10: 23540570 | P10: 23540570 | Q10: 0 | R10: 0 | S10: IDR | T10: 11665296 | U10: 11665296 | V10: 11875274 | W10: 0.50445992 | X10: 11875274 | Z10: . | AA10: 2308688 | AB10: PT. NUTRIFOOD INDONESIA BOGOR | AC10: AGNESYA ADIFILIA | AD10: 94 | AE10: 0 | AF10: 961 | AH10: . | AJ10: . | AK10: T | AL10: Non-Affiliate | AM10: Domestic | AN10: =VLOOKUP(I10,Sheet1!A:D,4,FALSE) -> A320400 | AP10: Ciawi Pusat | AR10: Invoice di kasih pagi jam 09:30. Invoice tanggal 17/1/25.MB terima di tanggal 22/1/25.
A11: 45658 | B11: Invoiced | C11: SO | D11: 25707935 | E11: 24106324 | F11: 225440 | G11: 45674 | H11: NUTRIFOOD | I11: M70000020 | J11: CARMOISINE 20KG | K11: 40 | L11: KG | M11: 40 | N11: 588514.26 | O11: 23540570 | P11: 23540570 | Q11: 0 | R11: 0 | S11: IDR | T11: 11665296 | U11: 11665296 | V11: 11875274 | W11: 0.50445992 | X11: 11875274 | Z11: . | AA11: 15440 | AB11: PT. NUTRIFOOD INDONESIA MM2100 | AC11: AGNESYA ADIFILIA | AD11: 94 | AE11: 0 | AF11: 961 | AH11: . | AJ11: . | AK11: T | AL11: Non-Affiliate | AM11: Domestic | AN11: =VLOOKUP(I11,Sheet1!A:D,4,FALSE) -> A320400 | AP11: Cibitung | AR11: Invoice di kasih pagi jam 09:30. Invoice tanggal 17/1/25.MB terima di tanggal 22/1/25.
A12: 45658 | B12: Invoiced | C12: SO | D12: 25707936 | E12: 24106429 | F12: 228541 | G12: 45674 | H12: NUTRIFOOD | I12: 97CB0361 | J12: SPIRULINA COLOR EXTRACT 1KG | K12: 1 | L12: KG | M12: 1 | N12: 6469057.8 | O12: 6469057.8 | P12: 6469057.8 | Q12: 0 | R12: 0 | S12: IDR | T12: 2701386.5 | U12: 2701386.5 | V12: 3767671.3 | W12: 0.58241422 | X12: 3767671.3 | Z12: . | AA12: 2308689 | AB12: PT. NUTRIFOOD INDONESIA MM2100 | AC12: AGNESYA ADIFILIA | AD12: 94 | AE12: 0 | AF12: 960 | AH12: . | AJ12: . | AK12: T | AL12: Non-Affiliate | AM12: Domestic | AN12: =VLOOKUP(I12,Sheet1!A:D,4,FALSE) -> A320400 | AP12: Cibitung | AR12: Invoice di kasih pagi jam 09:30. Invoice tanggal 17/1/25.MB terima di tanggal 22/1/25.
A13: 45658 | B13: Invoiced | C13: SO | D13: 25707937 | E13: 24106430 | F13: 227514 | G13: 45674 | H13: NUTRIFOOD | I13: 97CB1001.01 | J13: BEET RED 2000 SPWS | K13: 1 | L13: KG | M13: 1 | N13: 10531203 | O13: 10531203 | P13: 10531203 | Q13: 0 | R13: 0 | S13: IDR | T13: 5421277.5 | U13: 5421277.5 | V13: 5109925 | W13: 0.48521762 | X13: 5109925 | Z13: . | AA13: 2308689 | AB13: PT. NUTRIFOOD INDONESIA MM2100 | AC13: AGNESYA ADIFILIA | AD13: 94 | AE13: 0 | AF13: 960 | AH13: . | AJ13: . | AK13: T | AL13: Non-Affiliate | AM13: Domestic | AN13: =VLOOKUP(I13,Sheet1!A:D,4,FALSE) -> A320400 | AP13: Cibitung | AR13: Invoice di kasih pagi jam 09:30. Invoice tanggal 17/1/25.MB terima di tanggal 22/1/25.
A14: 45658 | B14: Invoiced | C14: SO | D14: 25707938 | E14: 24106431 | F14: 225988 | G14: 45674 | H14: NUTRIFOOD | I14: M86030020 | J14: EUROCERT TARTRAZINE BG 311050 | K14: 500 | L14: KG | M14: 500 | N14: 189721.02 | O14: 94860510 | P14: 94860510 | Q14: 0 | R14: 0 | S14: IDR | T14: 56762311 | U14: 56762311 | V14: 38098199 | W14: 0.40162339 | X14: 38098199 | Z14: . | AA14: 2308688 | AB14: PT. NUTRIFOOD INDONESIA BOGOR | AC14: AGNESYA ADIFILIA | AD14: 94 | AE14: 0 | AF14: 961 | AG14: TCSP | AH14: TRA COL SYN DYE POWDER | AJ14: . | AK14: T | AL14: Non-Affiliate | AM14: Domestic | AN14: =VLOOKUP(I14,Sheet1!A:D,4,FALSE) -> A320400 | AP14: Ciawi Pusat | AR14: Invoice di kasih pagi jam 09:30. Invoice tanggal 17/1/25.MB terima di tanggal 22/1/25.
A15: 45658 | B15: Invoiced | C15: SO | D15: 25707939 | E15: 24106461 | F15: 229720 | G15: 45674 | H15: NUTRIFOOD | I15: 97CB0361 | J15: SPIRULINA COLOR EXTRACT 1KG | K15: 1 | L15: KG | M15: 1 | N15: 6469057.8 | O15: 6469057.8 | P15: 6469057.8 | Q15: 0 | R15: 0 | S15: IDR | T15: 2701386.5 | U15: 2701386.5 | V15: 3767671.3 | W15: 0.58241422 | X15: 3767671.3 | Z15: . | AA15: 2308689 | AB15: PT. NUTRIFOOD INDONESIA MM2100 | AC15: AGNESYA ADIFILIA | AD15: 94 | AE15: 0 | AF15: 960 | AH15: . | AJ15: . | AK15: T | AL15: Non-Affiliate | AM15: Domestic | AN15: =VLOOKUP(I15,Sheet1!A:D,4,FALSE) -> A320400 | AP15: Cibitung | AR15: Invoice di kasih pagi jam 09:30. Invoice tanggal 17/1/25.MB terima di tanggal 22/1/25.
A16: 45689 | B16: Invoiced | C16: SO | D16: 25708003 | E16: 24106503 | F16: 227724 | G16: 45701 | H16: NUTRIFOOD | I16: 11100414 | J16: CARMINE WS 5% - 20KG | K16: 100 | L16: KG | M16: 100 | N16: 777548.09 | O16: 77754809 | P16: 77754809 | Q16: 0 | R16: 0 | S16: IDR | T16: 69782350 | U16: 69782350 | V16: 7972458.5 | W16: 0.10253332 | X16: 7972458.5 | Z16: . | AA16: 2308688 | AB16: PT. NUTRIFOOD INDONESIA BOGOR | AC16: AGNESYA ADIFILIA | AD16: 94 | AE16: 0 | AF16: 960 | AH16: . | AJ16: . | AK16: T | AL16: Non-Affiliate | AM16: Domestic | AN16: =VLOOKUP(I16,Sheet1!A:D,4,FALSE) -> A320400 | AP16: Ciawi Pusat | AR16: Invoice dikasih siang abis makan siang tanggal 20/2/25, invoice tanggal 13/2/25. MB terima di tanggal 20/2/25. jam 14:38
A17: 45689 | B17: Invoiced | C17: SO | D17: 25708004 | E17: 24106505 | F17: 227731 | G17: 45701 | H17: NUTRIFOOD | I17: C86040O20 | J17: EUROCERT SUNSET YELLOW BG | K17: 100 | L17: KG | M17: 100 | N17: 200912.73 | O17: 20091273 | P17: 20091273 | Q17: 0 | R17: 0 | S17: IDR | T17: 11764568 | U17: 11764568 | V17: 8326704.5 | W17: 0.41444385 | X17: 8326704.5 | Z17: . | AA17: 2308688 | AB17: PT. NUTRIFOOD INDONESIA BOGOR | AC17: AGNESYA ADIFILIA | AD17: 94 | AE17: 0 | AF17: 960 | AH17: . | AJ17: . | AK17: T | AL17: Non-Affiliate | AM17: Domestic | AN17: =VLOOKUP(I17,Sheet1!A:D,4,FALSE) -> A320400 | AP17: Ciawi Pusat | AR17: Invoice dikasih siang abis makan siang tanggal 20/2/25, invoice tanggal 13/2/25. MB terima di tanggal 20/2/25. jam 14:38
A18: 45689 | B18: Invoiced | C18: SO | D18: 25708005 | E18: 24106508 | F18: 225990 | G18: 45701 | H18: NUTRIFOOD | I18: M86030020 | J18: EUROCERT TARTRAZINE BG 311050 | K18: 500 | L18: KG | M18: 500 | N18: 195850.36 | O18: 97925180 | P18: 97925180 | Q18: 0 | R18: 0 | S18: IDR | T18: 56656054 | U18: 56656054 | V18: 41269126 | W18: 0.42143528 | X18: 41269126 | Z18: . | AA18: 2308688 | AB18: PT. NUTRIFOOD INDONESIA BOGOR | AC18: AGNESYA ADIFILIA | AD18: 94 | AE18: 0 | AF18: 961 | AG18: TCSP | AH18: TRA COL SYN DYE POWDER | AJ18: . | AK18: T | AL18: Non-Affiliate | AM18: Domestic | AN18: =VLOOKUP(I18,Sheet1!A:D,4,FALSE) -> A320400 | AP18: Ciawi Pusat | AR18: Invoice dikasih siang abis makan siang tanggal 20/2/25, invoice tanggal 13/2/25. MB terima di tanggal 20/2/25. jam 14:38
A19: 45689 | B19: Invoiced | C19: SO | D19: 25708006 | E19: 24106509 | F19: 227737 | G19: 45701 | H19: NUTRIFOOD | I19: M86030020 | J19: EUROCERT TARTRAZINE BG 311050 | K19: 500 | L19: KG | M19: 500 | N19: 195850.36 | O19: 97925180 | P19: 97925180 | Q19: 0 | R19: 0 | S19: IDR | T19: 56656054 | U19: 56656054 | V19: 41269126 | W19: 0.42143528 | X19: 41269126 | Z19: . | AA19: 2308688 | AB19: PT. NUTRIFOOD INDONESIA BOGOR | AC19: AGNESYA ADIFILIA | AD19: 94 | AE19: 0 | AF19: 961 | AG19: TCSP | AH19: TRA COL SYN DYE POWDER | AJ19: . | AK19: T | AL19: Non-Affiliate | AM19: Domestic | AN19: =VLOOKUP(I19,Sheet1!A:D,4,FALSE) -> A320400 | AP19: Ciawi Pusat | AR19: Invoice dikasih siang abis makan siang tanggal 20/2/25, invoice tanggal 13/2/25. MB terima di tanggal 20/2/25. jam 14:38
A20: 45689 | B20: Invoiced | C20: SO | D20: 25708007 | E20: 24106512 | F20: 226599 | G20: 45701 | H20: NUTRIFOOD | I20: M70000020 | J20: CARMOISINE 20KG | K20: 40 | L20: KG | M20: 40 | N20: 572680.38 | O20: 22907215 | P20: 22907215 | Q20: 0 | R20: 0 | S20: IDR | T20: 11665296 | U20: 11665296 | V20: 11241919 | W20: 0.49075887 | X20: 11241919 | Z20: . | AA20: 2308688 | AB20: PT. NUTRIFOOD INDONESIA BOGOR | AC20: AGNESYA ADIFILIA | AD20: 94 | AE20: 0 | AF20: 961 | AH20: . | AJ20: . | AK20: T | AL20: Non-Affiliate | AM20: Domestic | AN20: =VLOOKUP(I20,Sheet1!A:D,4,FALSE) -> A320400 | AP20: Ciawi Pusat | AR20: Invoice dikasih siang abis makan siang tanggal 20/2/25, invoice tanggal 13/2/25. MB terima di tanggal 20/2/25. jam 14:38
A21: 45689 | B21: Invoiced | C21: SO | D21: 25708008 | E21: 24106514 | F21: 228542 | G21: 45701 | H21: NUTRIFOOD | I21: 97CB1001.01 | J21: BEET RED 2000 SPWS | K21: 1 | L21: KG | M21: 1 | N21: 10871435 | O21: 10871435 | P21: 10871435 | Q21: 0 | R21: 0 | S21: IDR | T21: 5380686.5 | U21: 5380686.5 | V21: 5490748.8 | W21: 0.505062 | X21: 5490748.8 | Z21: . | AA21: 2308689 | AB21: PT. NUTRIFOOD INDONESIA MM2100 | AC21: AGNESYA ADIFILIA | AD21: 94 | AE21: 0 | AF21: 960 | AH21: . | AJ21: . | AK21: T | AL21: Non-Affiliate | AM21: Domestic | AN21: =VLOOKUP(I21,Sheet1!A:D,4,FALSE) -> A320400 | AP21: Cibitung | AR21: Invoice dikasih siang abis makan siang tanggal 20/2/25, invoice tanggal 13/2/25. MB terima di tanggal 20/2/25. jam 14:38
A22: 45689 | B22: Invoiced | C22: SO | D22: 25708009 | E22: 24106516 | F22: 229721 | G22: 45701 | H22: NUTRIFOOD | I22: 97CB0361 | J22: SPIRULINA COLOR EXTRACT 1KG | K22: 1 | L22: KG | M22: 1 | N22: 6678054.4 | O22: 6678054.4 | P22: 6678054.4 | Q22: 0 | R22: 0 | S22: IDR | T22: 2701386.5 | U22: 2701386.5 | V22: 3976667.9 | W22: 0.595483 | X22: 3976667.9 | Z22: . | AA22: 2308689 | AB22: PT. NUTRIFOOD INDONESIA MM2100 | AC22: AGNESYA ADIFILIA | AD22: 94 | AE22: 0 | AF22: 960 | AH22: . | AJ22: . | AK22: T | AL22: Non-Affiliate | AM22: Domestic | AN22: =VLOOKUP(I22,Sheet1!A:D,4,FALSE) -> A320400 | AP22: Cibitung | AR22: Invoice dikasih siang abis makan siang tanggal 20/2/25, invoice tanggal 13/2/25. MB terima di tanggal 20/2/25. jam 14:38
A23: 45689 | B23: Invoiced | C23: SO | D23: 25708010 | E23: 24106519 | F23: 225986 | G23: 45701 | H23: NUTRIFOOD | I23: C86040O20 | J23: EUROCERT SUNSET YELLOW BG | K23: 100 | L23: KG | M23: 100 | N23: 200912.73 | O23: 20091273 | P23: 20091273 | Q23: 0 | R23: 0 | S23: IDR | T23: 11764568 | U23: 11764568 | V23: 8326704.5 | W23: 0.41444385 | X23: 8326704.5 | Z23: . | AA23: 15440 | AB23: PT. NUTRIFOOD INDONESIA MM2100 | AC23: AGNESYA ADIFILIA | AD23: 94 | AE23: 0 | AF23: 960 | AH23: . | AJ23: . | AK23: T | AL23: Non-Affiliate | AM23: Domestic | AN23: =VLOOKUP(I23,Sheet1!A:D,4,FALSE) -> A320400 | AP23: Cibitung | AR23: Invoice dikasih siang abis makan siang tanggal 20/2/25, invoice tanggal 13/2/25. MB terima di tanggal 20/2/25. jam 14:38
A24: 45689 | B24: Invoiced | C24: SO | D24: 25708011 | E24: 24106520 | F24: 227732 | G24: 45701 | H24: NUTRIFOOD | I24: C86040O20 | J24: EUROCERT SUNSET YELLOW BG | K24: 100 | L24: KG | M24: 100 | N24: 200912.73 | O24: 20091273 | P24: 20091273 | Q24: 0 | R24: 0 | S24: IDR | T24: 11764568 | U24: 11764568 | V24: 8326704.5 | W24: 0.41444385 | X24: 8326704.5 | Z24: . | AA24: 15440 | AB24: PT. NUTRIFOOD INDONESIA MM2100 | AC24: AGNESYA ADIFILIA | AD24: 94 | AE24: 0 | AF24: 960 | AH24: . | AJ24: . | AK24: T | AL24: Non-Affiliate | AM24: Domestic | AN24: =VLOOKUP(I24,Sheet1!A:D,4,FALSE) -> A320400 | AP24: Cibitung | AR24: Invoice dikasih siang abis makan siang tanggal 20/2/25, invoice tanggal 13/2/25. MB terima di tanggal 20/2/25. jam 14:38
A25: 45689 | B25: Invoiced | C25: SO | D25: 25708012 | E25: 24106522 | F25: 227736 | G25: 45701 | H25: NUTRIFOOD | I25: M86030020 | J25: EUROCERT TARTRAZINE BG 311050 | K25: 500 | L25: KG | M25: 500 | N25: 195850.36 | O25: 97925180 | P25: 97925180 | Q25: 0 | R25: 0 | S25: IDR | T25: 56656054 | U25: 56656054 | V25: 41269126 | W25: 0.42143528 | X25: 41269126 | Z25: . | AA25: 15440 | AB25: PT. NUTRIFOOD INDONESIA MM2100 | AC25: AGNESYA ADIFILIA | AD25: 94 | AE25: 0 | AF25: 961 | AG25: TCSP | AH25: TRA COL SYN DYE POWDER | AJ25: . | AK25: T | AL25: Non-Affiliate | AM25: Domestic | AN25: =VLOOKUP(I25,Sheet1!A:D,4,FALSE) -> A320400 | AP25: Cibitung | AR25: Invoice dikasih siang abis makan siang tanggal 20/2/25, invoice tanggal 13/2/25. MB terima di tanggal 20/2/25. jam 14:38
A26: 45689 | B26: Invoiced | C26: SO | D26: 25708013 | E26: 24106523 | F26: 227738 | G26: 45701 | H26: NUTRIFOOD | I26: M86030020 | J26: EUROCERT TARTRAZINE BG 311050 | K26: 500 | L26: KG | M26: 500 | N26: 195850.36 | O26: 97925180 | P26: 97925180 | Q26: 0 | R26: 0 | S26: IDR | T26: 56656054 | U26: 56656054 | V26: 41269126 | W26: 0.42143528 | X26: 41269126 | Z26: . | AA26: 15440 | AB26: PT. NUTRIFOOD INDONESIA MM2100 | AC26: AGNESYA ADIFILIA | AD26: 94 | AE26: 0 | AF26: 961 | AG26: TCSP | AH26: TRA COL SYN DYE POWDER | AJ26: . | AK26: T | AL26: Non-Affiliate | AM26: Domestic | AN26: =VLOOKUP(I26,Sheet1!A:D,4,FALSE) -> A320400 | AP26: Cibitung | AR26: Invoice dikasih siang abis makan siang tanggal 20/2/25, invoice tanggal 13/2/25. MB terima di tanggal 20/2/25. jam 14:38
A27: 45689 | B27: Invoiced | C27: SO | D27: 25708014 | E27: 24106525 | F27: 226598 | G27: 45701 | H27: NUTRIFOOD | I27: M70000020 | J27: CARMOISINE 20KG | K27: 40 | L27: KG | M27: 40 | N27: 572680.38 | O27: 22907215 | P27: 22907215 | Q27: 0 | R27: 0 | S27: IDR | T27: 11665296 | U27: 11665296 | V27: 11241919 | W27: 0.49075887 | X27: 11241919 | Z27: . | AA27: 15440 | AB27: PT. NUTRIFOOD INDONESIA MM2100 | AC27: AGNESYA ADIFILIA | AD27: 94 | AE27: 0 | AF27: 961 | AH27: . | AJ27: . | AK27: T | AL27: Non-Affiliate | AM27: Domestic | AN27: =VLOOKUP(I27,Sheet1!A:D,4,FALSE) -> A320400 | AP27: Cibitung | AR27: Invoice dikasih siang abis makan siang tanggal 20/2/25, invoice tanggal 13/2/25. MB terima di tanggal 20/2/25. jam 14:38
A28: 45689 | B28: Invoiced | C28: SO | D28: 25708026 | E28: 25106587 | F28: 232597 | G28: 45712 | H28: NUTRIFOOD | I28: 03802 | J28: PURPLE SWEET POTATO POWDER | K28: 3 | L28: KG | M28: 3 | N28: 4170023 | O28: 12510069 | P28: 12510069 | Q28: 0 | R28: 0 | S28: IDR | T28: 7052701.5 | U28: 7052701.5 | V28: 5457367.5 | W28: 0.436238 | X28: 5457367.5 | Y28: DEL | Z28: Delivered | AA28: 15191 | AB28: PT. NUTRIFOOD INDONESIA BOGOR | AC28: AGNESYA ADIFILIA | AD28: 94 | AE28: 0 | AF28: 960 | AH28: . | AJ28: . | AK28: T | AL28: Non-Affiliate | AM28: Domestic | AN28: =VLOOKUP(I28,Sheet1!A:D,4,FALSE) -> A320400 | AP28: Ciawi Pusat | AR28: Invoice dikasih sore tanggal 26/2/25. Invoice tanggal 19,24/2/25. MB terima di tanggal 26/2/25 jam 15:45
A29: 45717 | B29: Invoiced | C29: SO | D29: 25708057 | E29: 24106513 | F29: 227922 | G29: 45729 | H29: NUTRIFOOD | I29: M70000020 | J29: CARMOISINE 20KG | K29: 40 | L29: KG | M29: 40 | N29: 572680.38 | O29: 22907215 | P29: 22907215 | Q29: 0 | R29: 0 | S29: IDR | T29: 11665296 | U29: 11665296 | V29: 11241919 | W29: 0.49075887 | X29: 11241919 | Z29: . | AA29: 15440 | AB29: PT. NUTRIFOOD INDONESIA MM2100 | AC29: AGNESYA ADIFILIA | AD29: 94 | AE29: 0 | AF29: 961 | AH29: . | AJ29: . | AK29: T | AL29: Non-Affiliate | AM29: Domestic | AN29: =VLOOKUP(I29,Sheet1!A:D,4,FALSE) -> A320400 | AP29: Cibitung | AR29: Invoice di kasih siang pas mau makan siang. Hari Jumat tanggal 14/3/25. MB terima tanggal 14/3/25. Invoice tgl 13/3/25.
A30: 45717 | B30: Invoiced | C30: SO | D30: 25708058 | E30: 24106515 | F30: 229719 | G30: 45729 | H30: NUTRIFOOD | I30: 97CB1001.01 | J30: BEET RED 2000 SPWS | K30: 1 | L30: KG | M30: 1 | N30: 10871435 | O30: 10871435 | P30: 10871435 | Q30: 0 | R30: 0 | S30: IDR | T30: 5380686.5 | U30: 5380686.5 | V30: 5490748.8 | W30: 0.505062 | X30: 5490748.8 | Z30: . | AA30: 2308689 | AB30: PT. NUTRIFOOD INDONESIA MM2100 | AC30: AGNESYA ADIFILIA | AD30: 94 | AE30: 0 | AF30: 960 | AH30: . | AJ30: . | AK30: T | AL30: Non-Affiliate | AM30: Domestic | AN30: =VLOOKUP(I30,Sheet1!A:D,4,FALSE) -> A320400 | AP30: Cibitung | AR30: Invoice di kasih siang pas mau makan siang. Hari Jumat tanggal 14/3/25. MB terima tanggal 14/3/25. Invoice tgl 13/3/25.
A31: 45717 | B31: Invoiced | C31: SO | D31: 25708059 | E31: 24106517 | F31: 231119 | G31: 45729 | H31: NUTRIFOOD | I31: 97CB0361 | J31: SPIRULINA COLOR EXTRACT 1KG | K31: 1 | L31: KG | M31: 1 | N31: 6678054.4 | O31: 6678054.4 | P31: 6678054.4 | Q31: 0 | R31: 0 | S31: IDR | T31: 2701386.5 | U31: 2701386.5 | V31: 3976667.9 | W31: 0.595483 | X31: 3976667.9 | Z31: . | AA31: 2308689 | AB31: PT. NUTRIFOOD INDONESIA MM2100 | AC31: AGNESYA ADIFILIA | AD31: 94 | AE31: 0 | AF31: 960 | AH31: . | AJ31: . | AK31: T | AL31: Non-Affiliate | AM31: Domestic | AN31: =VLOOKUP(I31,Sheet1!A:D,4,FALSE) -> A320400 | AP31: Cibitung | AR31: Invoice di kasih siang pas mau makan siang. Hari Jumat tanggal 14/3/25. MB terima tanggal 14/3/25. Invoice tgl 13/3/25.
A32: 45717 | B32: Invoiced | C32: SO | D32: 25708060 | E32: 24106518 | F32: 227920 | G32: 45729 | H32: NUTRIFOOD | I32: 056011001 | J32: FD&C BLUE NO 1 POWDER 1KG | K32: 16 | L32: KG | M32: 16 | N32: 922300.17 | O32: 14756803 | P32: 14756803 | Q32: 0 | R32: 0 | S32: IDR | T32: 10722754 | U32: 10722754 | V32: 4034048.3 | W32: 0.27336872 | X32: 4034048.3 | Z32: . | AA32: 15440 | AB32: PT. NUTRIFOOD INDONESIA MM2100 | AC32: AGNESYA ADIFILIA | AD32: 94 | AE32: 0 | AF32: 961 | AG32: TCSP | AH32: TRA COL SYN DYE POWDER | AJ32: . | AK32: T | AL32: Non-Affiliate | AM32: Domestic | AN32: =VLOOKUP(I32,Sheet1!A:D,4,FALSE) -> A320400 | AP32: Cibitung | AR32: Invoice di kasih siang pas mau makan siang. Hari Jumat tanggal 14/3/25. MB terima tanggal 14/3/25. Invoice tgl 13/3/25.
A33: 45717 | B33: Invoiced | C33: SO | D33: 25708061 | E33: 24106521 | F33: 227734 | G33: 45729 | H33: NUTRIFOOD | I33: C86040O20 | J33: EUROCERT SUNSET YELLOW BG | K33: 100 | L33: KG | M33: 100 | N33: 200912.73 | O33: 20091273 | P33: 20091273 | Q33: 0 | R33: 0 | S33: IDR | T33: 11764568 | U33: 11764568 | V33: 8326704.5 | W33: 0.41444385 | X33: 8326704.5 | Z33: . | AA33: 15440 | AB33: PT. NUTRIFOOD INDONESIA MM2100 | AC33: AGNESYA ADIFILIA | AD33: 94 | AE33: 0 | AF33: 960 | AH33: . | AJ33: . | AK33: T | AL33: Non-Affiliate | AM33: Domestic | AN33: =VLOOKUP(I33,Sheet1!A:D,4,FALSE) -> A320400 | AP33: Cibitung | AR33: Invoice di kasih siang pas mau makan siang. Hari Jumat tanggal 14/3/25. MB terima tanggal 14/3/25. Invoice tgl 13/3/25.
A34: 45717 | B34: Invoiced | C34: SO | D34: 25708062 | E34: 24106526 | F34: 227921 | G34: 45729 | H34: NUTRIFOOD | I34: M70000020 | J34: CARMOISINE 20KG | K34: 40 | L34: KG | M34: 40 | N34: 572680.38 | O34: 22907215 | P34: 22907215 | Q34: 0 | R34: 0 | S34: IDR | T34: 11665296 | U34: 11665296 | V34: 11241919 | W34: 0.49075887 | X34: 11241919 | Z34: . | AA34: 15440 | AB34: PT. NUTRIFOOD INDONESIA MM2100 | AC34: AGNESYA ADIFILIA | AD34: 94 | AE34: 0 | AF34: 961 | AH34: . | AJ34: . | AK34: T | AL34: Non-Affiliate | AM34: Domestic | AN34: =VLOOKUP(I34,Sheet1!A:D,4,FALSE) -> A320400 | AP34: Cibitung | AR34: Invoice di kasih siang pas mau makan siang. Hari Jumat tanggal 14/3/25. MB terima tanggal 14/3/25. Invoice tgl 13/3/25.
A35: 45717 | B35: Invoiced | C35: SO | D35: 25708063 | E35: 25106587 | F35: 232597 | G35: 45729 | H35: NUTRIFOOD | I35: 03802 | J35: PURPLE SWEET POTATO POWDER | K35: 6.8 | L35: KG | M35: 6.8 | N35: 4170023 | O35: 28356156 | P35: 28356156 | Q35: 0 | R35: 0 | S35: IDR | T35: 22189967 | U35: 22189967 | V35: 6166189.9 | W35: 0.21745507 | X35: 6166189.9 | Y35: DEL | Z35: Delivered | AA35: 15191 | AB35: PT. NUTRIFOOD INDONESIA BOGOR | AC35: AGNESYA ADIFILIA | AD35: 94 | AE35: 0 | AF35: 960 | AH35: . | AJ35: . | AK35: T | AL35: Non-Affiliate | AM35: Domestic | AN35: =VLOOKUP(I35,Sheet1!A:D,4,FALSE) -> A320400 | AP35: Ciawi Pusat | AR35: Invoice di kasih siang pas mau makan siang. Hari Jumat tanggal 14/3/25. MB terima tanggal 14/3/25. Invoice tgl 13/3/25.
A36: 45748 | B36: Invoiced | C36: SO | D36: 25708150 | E36: 24106506 | F36: 227733 | G36: 45771 | H36: NUTRIFOOD | I36: C86040O20 | J36: EUROCERT SUNSET YELLOW BG | K36: 100 | L36: KG | M36: 100 | N36: 200912.73 | O36: 20091273 | P36: 20091273 | Q36: 0 | R36: 0 | S36: IDR | T36: 11764568 | U36: 11764568 | V36: 8326704.5 | W36: 0.41444385 | X36: 8326704.5 | Z36: . | AA36: 2308688 | AB36: PT. NUTRIFOOD INDONESIA BOGOR | AC36: AGNESYA ADIFILIA | AD36: 94 | AE36: 0 | AF36: 960 | AH36: . | AJ36: . | AK36: T | AL36: Non-Affiliate | AM36: Domestic | AN36: =VLOOKUP(I36,Sheet1!A:D,4,FALSE) -> A320400 | AP36: Ciawi Pusat | AR36: Invoice Dikasih Sore jam pulang kerja jam 17:30. Invoice tanggal 24,28/4/25. MB terima ditanggal 30/4/25. Sore jam 18:45
A37: 45748 | B37: Invoiced | C37: SO | D37: 25708151 | E37: 24106510 | F37: 227739 | G37: 45771 | H37: NUTRIFOOD | I37: M86030020 | J37: EUROCERT TARTRAZINE BG 311050 | K37: 500 | L37: KG | M37: 500 | N37: 195850.36 | O37: 97925180 | P37: 97925180 | Q37: 0 | R37: 0 | S37: IDR | T37: 65480870 | U37: 65480870 | V37: 32444310 | W37: 0.33131734 | X37: 32444310 | Z37: . | AA37: 2308688 | AB37: PT. NUTRIFOOD INDONESIA BOGOR | AC37: AGNESYA ADIFILIA | AD37: 94 | AE37: 0 | AF37: 961 | AG37: TCSP | AH37: TRA COL SYN DYE POWDER | AJ37: . | AK37: T | AL37: Non-Affiliate | AM37: Domestic | AN37: =VLOOKUP(I37,Sheet1!A:D,4,FALSE) -> A320400 | AP37: Ciawi Pusat | AR37: Invoice Dikasih Sore jam pulang kerja jam 17:30. Invoice tanggal 24,28/4/25. MB terima ditanggal 30/4/25. Sore jam 18:45
A38: 45748 | B38: Invoiced | C38: SO | D38: 25708152 | E38: 24106524 | F38: 227741 | G38: 45771 | H38: NUTRIFOOD | I38: M86030020 | J38: EUROCERT TARTRAZINE BG 311050 | K38: 500 | L38: KG | M38: 500 | N38: 195850.36 | O38: 97925180 | P38: 97925180 | Q38: 0 | R38: 0 | S38: IDR | T38: 65480870 | U38: 65480870 | V38: 32444310 | W38: 0.33131734 | X38: 32444310 | Z38: . | AA38: 15440 | AB38: PT. NUTRIFOOD INDONESIA MM2100 | AC38: AGNESYA ADIFILIA | AD38: 94 | AE38: 0 | AF38: 961 | AG38: TCSP | AH38: TRA COL SYN DYE POWDER | AJ38: . | AK38: T | AL38: Non-Affiliate | AM38: Domestic | AN38: =VLOOKUP(I38,Sheet1!A:D,4,FALSE) -> A320400 | AP38: Cibitung | AR38: Invoice Dikasih Sore jam pulang kerja jam 17:30. Invoice tanggal 24,28/4/25. MB terima ditanggal 30/4/25. Sore jam 18:45
A39: 45748 | B39: Invoiced | C39: SO | D39: 25708153 | E39: 24106527 | F39: 230904 | G39: 45771 | H39: NUTRIFOOD | I39: M70000020 | J39: CARMOISINE 20KG | K39: 40 | L39: KG | M39: 40 | N39: 572680.38 | O39: 22907215 | P39: 22907215 | Q39: 0 | R39: 0 | S39: IDR | T39: 11665296 | U39: 11665296 | V39: 11241919 | W39: 0.49075887 | X39: 11241919 | Z39: . | AA39: 15440 | AB39: PT. NUTRIFOOD INDONESIA MM2100 | AC39: AGNESYA ADIFILIA | AD39: 94 | AE39: 0 | AF39: 961 | AH39: . | AJ39: . | AK39: T | AL39: Non-Affiliate | AM39: Domestic | AN39: =VLOOKUP(I39,Sheet1!A:D,4,FALSE) -> A320400 | AP39: Cibitung | AR39: Invoice Dikasih Sore jam pulang kerja jam 17:30. Invoice tanggal 24,28/4/25. MB terima ditanggal 30/4/25. Sore jam 18:45
A40: 45778 | B40: Invoiced | C40: SO | D40: 25708233 | E40: 24106504 | F40: 230661 | G40: 45798 | H40: NUTRIFOOD | I40: 11100414 | J40: CARMINE WS 5% - 20KG | K40: 100 | L40: KG | M40: 100 | N40: 803654.11 | O40: 80365411 | P40: 80365411 | Q40: 0 | R40: 0 | S40: IDR | T40: 70550350 | U40: 70550350 | V40: 9815060.5 | W40: 0.12213041 | X40: 9815060.5 | Z40: . | AA40: 2308688 | AB40: PT. NUTRIFOOD INDONESIA BOGOR | AC40: AGNESYA ADIFILIA | AD40: 94 | AE40: 0 | AF40: 960 | AH40: . | AJ40: . | AK40: T | AL40: Non-Affiliate | AM40: Domestic | AN40: =VLOOKUP(I40,Sheet1!A:D,4,FALSE) -> A320400 | AP40: Ciawi Pusat | AR40: Invoice dikasih sore jam pulang kerja tgl 23/05/2025. Invoice tgl 26/5/25 Clossing. MB terima pagi tgl 26/5/25.
A41: 45778 | B41: Invoiced | C41: SO | D41: 25708234 | E41: 25106653 | F41: 229507 | G41: 45798 | H41: NUTRIFOOD | I41: 077001020 | J41: FD&C RED NO.40 POWDER 20KG | K41: 20 | L41: KG | M41: 20 | N41: 460445.57 | O41: 9208911.4 | P41: 9208911.4 | Q41: 0 | R41: 0 | S41: IDR | T41: 4803127.1 | U41: 4803127.1 | V41: 4405784.3 | W41: 0.47842618 | X41: 4405784.3 | Z41: . | AA41: 2308688 | AB41: PT. NUTRIFOOD INDONESIA BOGOR | AC41: AGNESYA ADIFILIA | AD41: 94 | AE41: 0 | AF41: 961 | AG41: TCSP | AH41: TRA COL SYN DYE POWDER | AJ41: . | AK41: T | AL41: Non-Affiliate | AM41: Domestic | AN41: =VLOOKUP(I41,Sheet1!A:D,4,FALSE) -> A320400 | AP41: Ciawi Pusat | AR41: Invoice dikasih sore jam pulang kerja tgl 23/05/2025. Invoice tgl 26/5/25 Clossing. MB terima pagi tgl 26/5/25.
A42: 45778 | B42: Invoiced | C42: SO | D42: 25708235 | E42: 25106654 | F42: 234103 | G42: 45798 | H42: NUTRIFOOD | I42: 97CB0361 | J42: SPIRULINA COLOR EXTRACT 1KG | K42: 1 | L42: KG | M42: 1 | N42: 6902268.7 | O42: 6902268.7 | P42: 6902268.7 | Q42: 0 | R42: 0 | S42: IDR | T42: 2653917.3 | U42: 2653917.3 | V42: 4248351.5 | W42: 0.61550073 | X42: 4248351.5 | Y42: DEL | Z42: Delivered | AA42: 15191 | AB42: PT. NUTRIFOOD INDONESIA BOGOR | AC42: AGNESYA ADIFILIA | AD42: 94 | AE42: 0 | AF42: 960 | AH42: . | AJ42: . | AK42: T | AL42: Non-Affiliate | AM42: Domestic | AN42: =VLOOKUP(I42,Sheet1!A:D,4,FALSE) -> A320400 | AP42: Ciawi Pusat | AR42: Invoice dikasih sore jam pulang kerja tgl 23/05/2025. Invoice tgl 26/5/25 Clossing. MB terima pagi tgl 26/5/25.
A43: 45778 | B43: Invoiced | C43: SO | D43: 25708236 | E43: 25106655 | F43: 234102 | G43: 45798 | H43: NUTRIFOOD | I43: 97CB1001.01 | J43: BEET RED 2000 SPWS | K43: 1 | L43: KG | M43: 1 | N43: 11236442 | O43: 11236442 | P43: 11236442 | Q43: 0 | R43: 0 | S43: IDR | T43: 5523883.8 | U43: 5523883.8 | V43: 5712557.8 | W43: 0.50839563 | X43: 5712557.8 | Y43: DEL | Z43: Delivered | AA43: 15191 | AB43: PT. NUTRIFOOD INDONESIA BOGOR | AC43: AGNESYA ADIFILIA | AD43: 94 | AE43: 0 | AF43: 960 | AH43: . | AJ43: . | AK43: T | AL43: Non-Affiliate | AM43: Domestic | AN43: =VLOOKUP(I43,Sheet1!A:D,4,FALSE) -> A320400 | AP43: Ciawi Pusat | AR43: Invoice dikasih sore jam pulang kerja tgl 23/05/2025. Invoice tgl 26/5/25 Clossing. MB terima pagi tgl 26/5/25.
A44: 45778 | B44: Invoiced | C44: SO | D44: 25708237 | E44: 25106656 | F44: 230905 | G44: 45798 | H44: NUTRIFOOD | I44: M70000020 | J44: CARMOISINE 20KG | K44: 40 | L44: KG | M44: 40 | N44: 591908.01 | O44: 23676320 | P44: 23676320 | Q44: 0 | R44: 0 | S44: IDR | T44: 12207025 | U44: 12207025 | V44: 11469296 | W44: 0.48442052 | X44: 11469296 | Z44: . | AA44: 2308688 | AB44: PT. NUTRIFOOD INDONESIA BOGOR | AC44: AGNESYA ADIFILIA | AD44: 94 | AE44: 0 | AF44: 961 | AH44: . | AJ44: . | AK44: T | AL44: Non-Affiliate | AM44: Domestic | AN44: =VLOOKUP(I44,Sheet1!A:D,4,FALSE) -> A320400 | AP44: Ciawi Pusat | AR44: Invoice dikasih sore jam pulang kerja tgl 23/05/2025. Invoice tgl 26/5/25 Clossing. MB terima pagi tgl 26/5/25.
A45: 45778 | B45: Invoiced | C45: SO | D45: 25708238 | E45: 25106657 | F45: 230899 | G45: 45798 | H45: NUTRIFOOD | I45: 056011001 | J45: FD&C BLUE NO 1 POWDER 1KG | K45: 8 | L45: KG | M45: 8 | N45: 953266.22 | O45: 7626129.8 | P45: 7626129.8 | Q45: 0 | R45: 0 | S45: IDR | T45: 5398260.9 | U45: 5398260.9 | V45: 2227868.9 | W45: 0.29213624 | X45: 2227868.9 | Z45: . | AA45: 2308688 | AB45: PT. NUTRIFOOD INDONESIA BOGOR | AC45: AGNESYA ADIFILIA | AD45: 94 | AE45: 0 | AF45: 961 | AG45: TCSP | AH45: TRA COL SYN DYE POWDER | AJ45: . | AK45: T | AL45: Non-Affiliate | AM45: Domestic | AN45: =VLOOKUP(I45,Sheet1!A:D,4,FALSE) -> A320400 | AP45: Ciawi Pusat | AR45: Invoice dikasih sore jam pulang kerja tgl 23/05/2025. Invoice tgl 26/5/25 Clossing. MB terima pagi tgl 26/5/25.
A46: 45778 | B46: Invoiced | C46: SO | D46: 25708241 | E46: 24106507 | F46: 228879 | G46: 45798 | H46: NUTRIFOOD | I46: C86040O20 | J46: EUROCERT SUNSET YELLOW BG | K46: 100 | L46: KG | M46: 100 | N46: 207658.34 | O46: 20765834 | P46: 20765834 | Q46: 0 | R46: 0 | S46: IDR | T46: 15198430 | U46: 15198430 | V46: 5567403.9 | W46: 0.26810403 | X46: 5567403.9 | Z46: . | AA46: 2308688 | AB46: PT. NUTRIFOOD INDONESIA BOGOR | AC46: AGNESYA ADIFILIA | AD46: 94 | AE46: 0 | AF46: 960 | AH46: . | AJ46: . | AK46: T | AL46: Non-Affiliate | AM46: Domestic | AN46: =VLOOKUP(I46,Sheet1!A:D,4,FALSE) -> A320400 | AP46: Ciawi Pusat | AR46: Invoice dikasih sore jam pulang kerja tgl 23/05/2025. Invoice tgl 26/5/25 Clossing. MB terima pagi tgl 26/5/25.
A47: 45778 | B47: Invoiced | C47: SO | D47: 25708242 | E47: 24106511 | F47: 228881 | G47: 45798 | H47: NUTRIFOOD | I47: M86030020 | J47: EUROCERT TARTRAZINE BG 311050 | K47: 500 | L47: KG | M47: 500 | N47: 202426 | O47: 101213000 | P47: 101213000 | Q47: 0 | R47: 0 | S47: IDR | T47: 69685290 | U47: 69685290 | V47: 31527710 | W47: 0.31149862 | X47: 31527710 | Z47: . | AA47: 2308688 | AB47: PT. NUTRIFOOD INDONESIA BOGOR | AC47: AGNESYA ADIFILIA | AD47: 94 | AE47: 0 | AF47: 961 | AG47: TCSP | AH47: TRA COL SYN DYE POWDER | AJ47: . | AK47: T | AL47: Non-Affiliate | AM47: Domestic | AN47: =VLOOKUP(I47,Sheet1!A:D,4,FALSE) -> A320400 | AP47: Ciawi Pusat | AR47: Invoice dikasih sore jam pulang kerja tgl 23/05/2025. Invoice tgl 26/5/25 Clossing. MB terima pagi tgl 26/5/25.
